Workbook

Sheet Properties
B2: Volume | C2: 78
B3: Issue | C3: 6
B4: Article Title | C4: Rethinking the Administrative Remand Rule
B5: Author | C5: Smith
B6: SE | C6: Mariah Uustal
B7: Drive Folder ID | C7: 1QraZedvhM1pqTguKecOlRKZ62GUwcgnd
B8: Drive Sourcepull ID | C8: 1VmyDEdY-rZ9IfPP9oyBpoZpjcDWGggJR
B9: Drive R1 ID | C9: 1OkcpifbUiC1Y6G2u5ApzxEwKzOL1_kpP
B10: Drive R2 ID | C10: 1ECxOEr3giAvViqLOOB3XM6YZlFhRIkcx
B11: Primary ME | C11: Managing Editor
B12: MEMs | C12: Lucia Jiang
C13: Steve Sangbeom Heo
C14: Isabel Gallegos
C15: Ben Rosenthal
C16: Lucia Zheng
C17: Jinna Lee
C18: Breeze Velazquez
C19: Marcus Ellinas

Sheet Raw Output
A1: 1 | B1: Cite# | C1: Footnote Text | D1: Citation Text | E1: Source Name | F1: Warnings | G1: 1
A2: 1 | B2: 1 | C2: Pewećeli is a character in the Washoe Tribe’s creation story, and Pewećeli Yeweš means “Pewećeli’s trail” or “path” in reference to a trade route heading west. Email correspondence with Herman Miller, Culture/Language Resources Director, Washoe Tribe of Nevada and California (Oct. 16, 2024) (on file with the author); see also Claire Cudahy, “Washoe youth follow ancestors’ footsteps in Hope Valley,” Tahoe Daily Tribune (Jan. 25, 2018), https://www.tahoedailytribune.com/news/local/washoe-youth-follow-ancestors-footsteps-in-hope-valley-video/; U.S. Forest Service, Carson Ranger District, East Carson River Strategy, 4-5 (July 2007), http://www.theanglersedge.com/downloads/East_Carson_River_Strategy_061907.pdf. For a history of the Washoe and the lands they inhabited, see The Washoe Tribe of Nevada and California, WA SHE SHU: “The Washoe People” Past and Present (2009), https://www.fs.usda.gov/Internet/FSE_DOCUMENTS/stelprdb5251066.pdf; Washoe Tribe of California and Nevada, Washoe History: A Brief Summary (2020), https://washoetribe.us/aboutpage/4-Page-washoe-history. Frank Tortorich, Jr., The Opening of the Carson River Route, 18 Overland Journal 1, 22 (Spring 2000); Jeff Munson, “Emigrant Trail tour promises spectacular colors,” Tahoe Daily Tribune (Oct. 12, 2005), https://www.tahoedailytribune.com/news/emigrant-trail-tour-promises-spectacular-colors/. | D2: Email correspondence with Herman Miller, Culture/Language Resources Director, Washoe Tribe of Nevada and California (Oct. 16, 2024) (on file with the author) | E2: Herman
A3: 1 | B3: 2 | D3: Claire Cudahy, “Washoe youth follow ancestors’ footsteps in Hope Valley,” Tahoe Daily Tribune (Jan. 25, 2018), https://www.tahoedailytribune.com/news/local/washoe-youth-follow-ancestors-footsteps-in-hope-valley-video/ | E3: Cudahy
A4: 1 | B4: 3 | D4: U.S. Forest Service, Carson Ranger District, East Carson River Strategy, 4-5 (July 2007), http://www.theanglersedge.com/downloads/East_Carson_River_Strategy_061907.pdf | E4: Carson
A5: 1 | B5: 4 | D5: The Washoe Tribe of Nevada and California, WA SHE SHU: “The Washoe People” Past and Present (2009), https://www.fs.usda.gov/Internet/FSE_DOCUMENTS/stelprdb5251066.pdf | E5: Washoe USDA
A6: 1 | B6: 5 | D6: Washoe Tribe of California and Nevada, Washoe History: A Brief Summary (2020), https://washoetribe.us/aboutpage/4-Page-washoe-history | E6: Washoe History
A7: 2 | B7: 1 | C7: Frank Tortorich, Jr., The Opening of the Carson River Route, 18 Overland Journal 1, 22 (Spring 2000); Jeff Munson, “Emigrant Trail tour promises spectacular colors,” Tahoe Daily Tribune (Oct. 12, 2005), https://www.tahoedailytribune.com/news/emigrant-trail-tour-promises-spectacular-colors/. | D7: Frank Tortorich, Jr., The Opening of the Carson River Route, 18 Overland Journal 1, 22 (Spring 2000) | E7: Tortorich | G7: {=IF(E7:E735="", "", COUNTIFS(E$7:E735, E$7:E735, ROW(E$7:E735), "<="&ROW(E$7:E735)))} -> 1 | H7: {=IF(G7:G735=1, COUNTIFS(G$7:G735, 1, ROW(G$7:G735), "<="&ROW(G$7:G735)), "")} -> 1
A8: 2 | B8: 2 | D8: Jeff Munson, “Emigrant Trail tour promises spectacular colors,” Tahoe Daily Tribune (Oct. 12, 2005), https://www.tahoedailytribune.com/news/emigrant-trail-tour-promises-spectacular-colors/ | E8: Munson | G8: 1 | H8: 2
A9: 3 | B9: 1 | C9: For the Forest Service’s most current Winter Recreation Map for Hope Valley and surrounding areas, see https://www.fs.usda.gov/Internet/FSE_DOCUMENTS/stelprdb5294291.pdf. | D9: https://www.fs.usda.gov/Internet/FSE_DOCUMENTS/stelprdb5294291.pdf. | E9: Hope Valley Recreation | G9: 1 | H9: 3
A10: 4 | B10: 1 | C10: Memorandum of Opinion and Order, Friends of Hope Valley v. U.S. Forest Serv., No. 2:00-cv-01900-DFL-KJM, 2 (E.D. Cal. Sept. 30, 2004). | D10: Memorandum of Opinion and Order, Friends of Hope Valley v. U.S. Forest Serv., No. 2:00-cv-01900-DFL-KJM, 2 (E.D. Cal. Sept. 30, 2004) | E10: Memorandum | G10: 1 | H10: 4
A11: 5 | B11: 1 | C11: Memorandum of Opinion and Order, Friends of Hope Valley v. U.S. Forest Serv., No. 2:00-cv-01900-DFL-KJM, 6 (E.D. Cal. Sept. 30, 2004). | D11: Memorandum of Opinion and Order, Friends of Hope Valley v. U.S. Forest Serv., No. 2:00-cv-01900-DFL-KJM, 6 (E.D. Cal. Sept. 30, 2004) | E11: Memorandum | G11: 2
A12: 6 | B12: 1 | C12: Friends of Hope Valley v. U.S. Forest Service, 203 Fed. Appx. 883 (9th Cir. 2006) (unpublished). | D12: Friends of Hope Valley v. U.S. Forest Service, 203 Fed. Appx. 883 (9th Cir. 2006) (unpublished) | E12: Friends of Hope Valley v US Forest Service | G12: 1 | H12: 5
A13: 7 | B13: 1 | C13: Id. The APA is found at 5 U.S.C. §§ 551-553, 701-706. This Article is concerned with only APA remands. There are, of course, many other types of remands (to administrative law judges, bankruptcy courts, state courts, and so on), and in a few footnotes I have noted ways in which jurisprudence concerning such other remands is relevant to the administrative-remand rule. See infra notes 113, 151-153. | D13: Id. | E13: Friends of Hope Valley v US Forest Service | G13: 2
A14: 7 | B14: 2 | D14: 5 U.S.C. §§ 551-553, 701-706 | E14: APA | G14: 1 | H14: 6
A15: 7 | B15: 3 | D15: infra notes 113, 151-153 | E15: Infra Notes 113, 151-153 | G15: 1 | H15: 7
A16: 8 | B16: 1 | C16: Friends of Hope Valley, 203 Fed. Appx. at 883 (citing Alsea Valley Alliance v. Dep’t of Commerce, 358 F.3d 1181, 1184 (9th Cir. 2004)). | D16: Friends of Hope Valley, 203 Fed. Appx. at 883 | E16: Friends of Hope Valley v US Forest Service | G16: 3
A17: 8 | B17: 2 | D17: Alsea Valley Alliance v. Dep’t of Commerce, 358 F.3d 1181, 1184 (9th Cir. 2004) | E17: Alsea Valley Alliance v Dep't of Commerce | G17: 1 | H17: 8
A18: 9 | B18: 1 | C18: Alsea Valley Alliance, 358 F.3d at 1184 (emphasis removed). For more detail on section 1291, see infra Part I.B. Also, as infra note 23 explains, some courts and commentators conceive of the rule as being narrower: A decision remanding an agency action is not final and appealable, and an appeal by the agency is an “exception” to that rule instead of part of the rule itself. | D18: Alsea Valley Alliance, 358 F.3d at 1184 | E18: Alsea Valley Alliance v Dep't of Commerce | G18: 2
A19: 9 | B19: 2 | D19: infra Part I.B | E19: Infra Part IB | G19: 1 | H19: 9
A20: 9 | B20: 3 | D20: infra note 23 | E20: Infra Note 23 | G20: 1 | H20: 10
A21: 10 | B21: 1 | C21: The Tenth Circuit coined the term “administrative-remand rule,” and as of 2021, it was “unique” to that circuit. C.W. by and through B.W. v. Denver Cnty. Sch. Dist. No. 1, 994 F.3d 1215, 1220 n.2 (10th Cir. 2021). However, at least two other courts have since started to use that term. See Montana Env’t Info. Ctr. v. Haaland, No. 22-36002, 2023 WL 8166779, at *1 (9th Cir. Nov. 24, 2023); DCOR, LLC v. U.S. Dep’t of the Interior, No. 3:21-CV-00120-N, 2023 WL 8628322, at *1 (N.D. Tex. Dec. 13, 2023). | D21: C.W. by and through B.W. v. Denver Cnty. Sch. Dist. No. 1, 994 F.3d 1215, 1220 n.2 (10th Cir. 2021) | E21: Denver Cnty | G21: 1 | H21: 11
A22: 10 | B22: 2 | D22: Montana Env’t Info. Ctr. v. Haaland, No. 22-36002, 2023 WL 8166779, at *1 (9th Cir. Nov. 24, 2023) | E22: Montana Env't Info CTR | G22: 1 | H22: 12
A23: 10 | B23: 3 | D23: DCOR, LLC v. U.S. Dep’t of the Interior, No. 3:21-CV-00120-N, 2023 WL 8628322, at *1 (N.D. Tex. Dec. 13, 2023) | E23: Dcor | G23: 1 | H23: 13
A24: 11 | B24: 1 | C24: Part I, infra, discusses this case law in detail. Notably, the rise of the administrative-remand rule coincided, unsurprisingly, with the rise of the administrative state. For more on the latter, see, e.g., Jon D. Michaels, Constitutional Coup: Privatization’s Threat to the American Republic, 21-77 (2017); Developments in the Law—Presidential Authority, V. Executive Appointments, 125 Harv. L. Rev. 2135, 2138 (2012); Daniel E. Ho & Erica L. Ross, Did Liberal Justices Invent the Standing Doctrine? An Empirical Study of the Evolution of Standing, 1921-2006, 62 Stan. L. Rev. 591, 647 & n.231 (2010); William S. Jordan, III, Judges, Ideology, and Policy in the Administrative State: Lessons from A Decade of Hard Look Remands of EPA Rules, 53 Admin. L. Rev. 45, 46 (2001). | D24: Part I, infra | E24: Infra Part I | G24: 1 | H24: 14
A25: 1 | D25: Jon D. Michaels, Constitutional Coup: Privatization’s Threat to the American Republic, 21-77 (2017) | E25: Michaels | G25: 1 | H25: 15
A26: 11 | B26: 2 | D26: Developments in the Law—Presidential Authority, V. Executive Appointments, 125 Harv. L. Rev. 2135, 2138 (2012) | E26: Developments | G26: 1 | H26: 16
A27: 11 | B27: 3 | D27: Daniel E. Ho & Erica L. Ross, Did Liberal Justices Invent the Standing Doctrine? An Empirical Study of the Evolution of Standing, 1921-2006, 62 Stan. L. Rev. 591, 647 & n.231 (2010) | E27: Ho | G27: 1 | H27: 17
A28: 11 | B28: 4 | D28: William S. Jordan, III, Judges, Ideology, and Policy in the Administrative State: Lessons from A Decade of Hard Look Remands of EPA Rules, 53 Admin. L. Rev. 45, 46 (2001) | E28: Jordan | G28: 1 | H28: 18
A29: 12 | B29: 1 | C29: The Court came closest to considering the rule in Sullivan v. Finkelstein, 496 U.S. 617, 625 (1990), which interpreted a specific finality statute to permit appeals of district court remands in Social Security cases. See infra notes 89-97 and accompanying text pp. 17-19 (discussing Finkelstein in detail). | D29: Sullivan v. Finkelstein, 496 U.S. 617, 625 (1990) | E29: Finkelstein | G29: 1 | H29: 19
A30: 12 | B30: 2 | D30: infra notes 89-97 and accompanying text pp. 17-19 | E30: Infra Notes 89-97 and Accompanying Text Pp 17-19 | G30: 1 | H30: 20
A31: 13 | B31: 1 | C31: Professor Bryan Lammon at the University of Toledo College of Law has written most extensively about the administrative-remand rule, though in the more general context of finality and appellate jurisdiction. See Bryan Lammon, Finality, Appealability, and the Scope of Interlocutory Review, 93 Wash. L. Rev. 1809, 1834-37 (2018); Bryan Lammon, Dizzying Gillespie: The Exaggerated Death of the Balancing Approach and the Inescapable Allure of Flexibility in Appellate Jurisdiction, 51 U. Rich. L. Rev. 371, 386-93 (2017). The rule has received passing attention in other scholarship. See, e.g., Harold J. Krent, Situating Structural Challenges to Agency Authority Within the Framework of the Finality Principle, 98 Ind. L.J. Supplement 1, 10 n.73 (2023); Jennifer L. Biever & Ana Maria Gutierrez, The Uncertain Question of Remedies Should a Challenge Prevail, 2016 NO. 5 RMMLF-INST PAPER NO. 13, 28-29 (2016); Michele D. Lynch, Remands Are A Consequence of Administrative Law, So Why Are We All So Frustrated?, 23 Tul. J. Int’l & Comp. L. 383, 392 (2015). Finally, a few treatises discuss the rule. See, e.g., Federal Practice & Procedure, § 3914.32 Orders Prior to Trial—Administrative Review, 15B Fed. Prac. & Proc. Juris. § 3914.32 (2d ed. June 2024 Update); Federal Practice & Procedure, § 3903 Pragmatic Finality, 15A Fed. Prac. & Proc. Juris. § 3913 (3d ed. June 2024 Update); see also, e.g., 73A C.J.S. Pub. Admin. Law & Proc. § 561 (May 2024); Fed. Ct. App. Manual § 2:3 (7th ed. May 2024). | D31: Bryan Lammon, Finality, Appealability, and the Scope of Interlocutory Review, 93 Wash. L. Rev. 1809, 1834-37 (2018) | E31: Lammon Appealability | G31: 1 | H31: 21
A32: 13 | B32: 2 | D32: Bryan Lammon, Dizzying Gillespie: The Exaggerated Death of the Balancing Approach and the Inescapable Allure of Flexibility in Appellate Jurisdiction, 51 U. Rich. L. Rev. 371, 386-93 (2017) | E32: Lammon Dizzying | G32: 1 | H32: 22
A33: 13 | B33: 3 | D33: Harold J. Krent, Situating Structural Challenges to Agency Authority Within the Framework of the Finality Principle, 98 Ind. L.J. Supplement 1, 10 n.73 (2023) | E33: Krent | G33: 1 | H33: 23
A34: 13 | B34: 4 | D34: Jennifer L. Biever & Ana Maria Gutierrez, The Uncertain Question of Remedies Should a Challenge Prevail, 2016 NO. 5 RMMLF-INST PAPER NO. 13, 28-29 (2016) | E34: Biever | G34: 1 | H34: 24
A35: 13 | B35: 5 | D35: Michele D. Lynch, Remands Are A Consequence of Administrative Law, So Why Are We All So Frustrated?, 23 Tul. J. Int’l & Comp. L. 383, 392 (2015) | E35: Lynch | G35: 1 | H35: 25
A36: 13 | B36: 6 | D36: Federal Practice & Procedure, § 3914.32 Orders Prior to Trial—Administrative Review, 15B Fed. Prac. & Proc. Juris. § 3914.32 (2d ed. June 2024 Update) | E36: Federal Practice 3914 32 | G36: 1 | H36: 26
A37: 13 | B37: 7 | D37: Federal Practice & Procedure, § 3903 Pragmatic Finality, 15A Fed. Prac. & Proc. Juris. § 3913 (3d ed. June 2024 Update) | E37: Federal Practice 3903 | G37: 1 | H37: 27
A38: 13 | B38: 8 | D38: 73A C.J.S. Pub. Admin. Law & Proc. § 561 (May 2024) | E38: 73a CJS | G38: 1 | H38: 28
A39: 13 | B39: 9 | D39: Fed. Ct. App. Manual § 2:3 (7th ed. May 2024) | E39: Fed Ct | G39: 1 | H39: 29
A40: 14 | B40: 1 | C40: Section 1291 is Congress’ enshrinement of the final-judgment rule. See infra notes 39-51 and accompanying text (discussing the final-judgment rule in detail). | D40: infra notes 39-51 and accompanying text | E40: Infra Notes 39-51 and Accompanying Text | G40: 1 | H40: 30
A41: 15 | B41: 1 | C41: See infra notes 46-48 and accompanying text (discussing the final-judgment rule’s rationales and benefits). | D41: infra notes 46-48 and accompanying text | E41: Infra Notes 46-48 and Accompanying Text | G41: 1 | H41: 31
A42: 16 | B42: 1 | C42: See Pueblo of Sandia v. Babbitt, 231 F.3d 878, 880 (D.C. Cir. 2000) (“Deferring review also leaves open the possibility that no appeal will be taken in the event the proceedings on remand satisfy all parties.”). | D42: Pueblo of Sandia v. Babbitt, 231 F.3d 878, 880 (D.C. Cir. 2000) | E42: Pueblo of Sandia v Babbitt | G42: 1 | H42: 32
A43: 17 | B43: 1 | C43: Two Ninth Circuit judges recently called for reconsidering the rule en banc in the remand-with-vacatur context, explaining that vacatur “operates like a final judgment or an injunction such that we should have jurisdiction over appeals of remands-with-vacatur under 28 U.S.C. § 1291, § 1292, or both.” Ctr. for Biological Diversity v. Bureau of Land Mgmt., 69 F.4th 588, 597-98 (9th Cir. 2023) (Friedland and Bennett, JJ., concurring). A Second Circuit panel has expressed similar concerns. See N.Y. Legal Assistance Grp. v. Cardona, No. 21-888-CV, 2024 WL 64220, at *3-4 (2d Cir. Jan. 5, 2024). | D43: Ctr. for Biological Diversity v. Bureau of Land Mgmt., 69 F.4th 588, 597-98 (9th Cir. 2023) (Friedland and Bennett, JJ., concurring) | E43: CTR for Biological Diversity v Bureau of Land MGMT | G43: 1 | H43: 33
A44: 17 | B44: 2 | D44: N.Y. Legal Assistance Grp. v. Cardona, No. 21-888-CV, 2024 WL 64220, at *3-4 (2d Cir. Jan. 5, 2024) | E44: NY Legal Assistance GRP v Cardona | G44: 1 | H44: 34
A45: 18 | B45: 1 | C45: See infra notes 132-192 and accompanying text. | D45: infra notes 132-192 and accompanying text | E45: Infra Notes 132-192 and Accompanying Text | G45: 1 | H45: 35
A46: 19 | B46: 1 | C46: See infra notes 193-194, 262-270 and accompanying text. | D46: infra notes 193-194, 262-270 and accompanying text | E46: Infra Notes 193-194 | G46: 1 | H46: 36
A47: 20 | B47: 1 | C47: Temporal forum-shopping is “the practice of choosing the most favorable jurisdiction or court in which a claim might be heard across time.” Zachary D. Clopton & Katherine Shaw, Public Law Litigation and Electoral Time, 2023 Wis. L. Rev. 1513, 1521–22 (2023). | D47: Zachary D. Clopton & Katherine Shaw, Public Law Litigation and Electoral Time, 2023 Wis. L. Rev. 1513, 1521–22 (2023) | E47: Clopton | G47: 1 | H47: 37
A48: 21 | B48: 1 | C48: This Article focuses on review by the federal courts of appeals of remand orders issued by federal district courts under the APA. Various states have adopted their own versions of the administrative-remand rule, which a future article could examine. See, e.g., Jackson v. Bd. of Civ. Serv. Comm’rs of City of Los Angeles, 99 Cal. App. 5th 648, 655-62, 318 Cal. Rptr. 3d 79 (2024) (applying Dhillon v. John Muir Health, 2 Cal. 5th 1109, 1116, 394 P.3d 1048 (2017)); Federman v. Bd. of Appeals of Marblehead, 35 Mass. App. Ct. 727, 729-30, 626 N.E. 2d 8 (Mass. 1994); Holton Transp., Inc. v. Kansas Corp. Comm’n, 10 Kan. App. 2d 12, 12-13, 690 P.2d 399 (Kan. 1984); Bearns v. Dep’t of Indus., Labor & Human Relations, 76-78. 306 N.W. 2d 22 (Wis. 1981). | D48: Jackson v. Bd. of Civ. Serv. Comm’rs of City of Los Angeles, 99 Cal. App. 5th 648, 655-62, 318 Cal. Rptr. 3d 79 (2024) | E48: Jackson | G48: 1 | H48: 38
A49: 21 | B49: 2 | D49: Dhillon v. John Muir Health, 2 Cal. 5th 1109, 1116, 394 P.3d 1048 (2017) | E49: John Muir Health | G49: 1 | H49: 39
A50: 21 | B50: 3 | D50: Federman v. Bd. of Appeals of Marblehead, 35 Mass. App. Ct. 727, 729-30, 626 N.E. 2d 8 (Mass. 1994) | E50: Federman | G50: 1 | H50: 40
A51: 21 | B51: 4 | D51: Holton Transp., Inc. v. Kansas Corp. Comm’n, 10 Kan. App. 2d 12, 12-13, 690 P.2d 399 (Kan. 1984) | E51: Holton | G51: 1 | H51: 41
A52: 21 | B52: 5 | D52: Bearns v. Dep’t of Indus., Labor & Human Relations, 76-78. 306 N.W. 2d 22 (Wis. 1981) | E52: Bearns | G52: 1 | H52: 42
A53: 22 | B53: 1 | C53: The administrative-remand rule applies to appeals to the circuit courts of district-court remand orders. There is no equivalent rule that covers appeals to the Supreme Court of circuit-court remand orders or of circuit-court decisions upholding district-court remand orders. The Supreme Court does have, however, a longstanding, general rule against interlocutory review. See Am. Constr. Co. v. Jacksonville, Tampa & Key West Ry. Co., 148 U.S. 372, 384 (1893) (“[M]any orders made in the progress of a suit become quite unimportant by reason of the final result, or of intervening matters.”). | D53: Am. Constr. Co. v. Jacksonville, Tampa & Key West Ry. Co., 148 U.S. 372, 384 (1893) | E53: Am Constr Co | G53: 1 | H53: 43
A54: 23 | B54: 1 | C54: Some courts and commentators conceive of the rule as being narrower: A decision remanding an agency action is not final and appealable, and an appeal by the agency is an “exception” to that rule instead of part of the rule itself. See infra notes 29, 94, 113. This narrow framing allows a circuit court to reject an appeal of a remand by an agency, which, we will see, the circuits almost never do. As a result, under either this narrower or my broader framing the result is the same: Typically only agencies may appeal orders remanding their decisions for further proceedings. | D54: infra notes 29, 94, 113 | E54: Infra Notes 29 | G54: 1 | H54: 44
A55: 24 | B55: 1 | C55: 28 U.S.C. § 1291. Some types of administrative-agency remands occur under special final-judgment statutes that either mimic or intentionally depart from section 1291. I discuss those below where relevant. | D55: 28 U.S.C. § 1291 | E55: 1291 | G55: 1 | H55: 45
A56: 25 | B56: 1 | C56: 28 U.S.C. § 1292(a). | D56: 28 U.S.C. § 1292 | E56: 1292 | G56: 1 | H56: 46
A57: 26 | B57: 1 | C57: The two most common vehicles for certification are Federal Rule of Civil Procedure 54(b) and 28 U.S.C. § 1292(b). See infra notes 280, 298 and accompanying text (discussing relationship between certification under these provisions and the administrative-remand rule). | D57: Federal Rule of Civil Procedure 54(b) | E57: Federal Rule | G57: 1 | H57: 47
A58: 26 | B58: 2 | D58: 28 U.S.C. § 1292(b) | E58: 1292 | G58: 2
A59: 26 | B59: 3 | D59: infra notes 280, 298 and accompanying text | E59: Infra Notes 280 | G59: 1 | H59: 48
A60: 27 | B60: 1 | C60: Collord v. U.S. Dep’t of the Interior, 154 F.3d 933, 935 (9th Cir. 1998); see also infra notes 132-181 (discussing the primacy of this concern across the circuits and citing many cases that discuss it). | D60: Collord v. U.S. Dep’t of the Interior, 154 F.3d 933, 935 (9th Cir. 1998) | E60: Collord v US Dep't of the Interior | G60: 1 | H60: 49
A61: 27 | B61: 2 | D61: infra notes 132-181 | E61: Infra Notes 132-181 | G61: 1 | H61: 50
A62: 28 | B62: 1 | C62: Alsea Valley Alliance, 358. F3d at 1184 (“An agency, after all, cannot appeal the result of its own decision.”). As the Seventh Circuit put it, “an order remanding a case to an agency is final for purposes of 28 U.S.C. § 1291 if it terminates the agency’s judicial remedies other than contempt.” Crowder v. Sullivan, 897 F.2d 252, 253 (7th Cir. 1990) (per curiam); see also 15B Fed. Prac. & Proc. Juris. § 3914.32 (“The most cogent explanation for most of these decisions must be that administrative agencies, as more or less coordinate branches of government, deserve the protection of special appeal opportunities. The need to settle important questions, and to get them right, underlies the most persuasive decisions. There actually is reason to worry that an agency cannot appeal its own decision in favor of a claimant if the decision was compelled by a district court remand that the agency believes wrong.”). | D62: Alsea Valley Alliance, 358. F3d at 1184 | E62: Alsea Valley Alliance v Dep't of Commerce | G62: 3
A63: 28 | B63: 2 | D63: Crowder v. Sullivan, 897 F.2d 252, 253 (7th Cir. 1990) (per curiam) | E63: Crowder v Sullivan | G63: 1 | H63: 51
A64: 28 | B64: 3 | D64: 15B Fed. Prac. & Proc. Juris. § 3914.32 | E64: Federal Practice 3914 32 | G64: 2
A65: 29 | B65: 1 | C65: This Article avoids framing the circumstances in which the circuit courts deem remands appealable as “exceptions” to the final-judgment rule or administrative-remand rule, even though many courts do just that. The “courts of appeals do not have authority to create exceptions to congressional limits on jurisdiction.” Papotto v. Hartford Life & Accid. Insur. Co., 731 F.3d 265, 270-71 (3d Cir. 2013) (citing supporting cases). Rather, the circuit courts’ prudential development of circumstances in which remands are final, despite the general rule they are not, is simply a “practical construction of finality.” Kreider Dairy Farms, Inc. v. Glickman, 190 F.3d 113, 124 (3d Cir. 1999) (Sloviter, J., concurring); see also Digital Equip. Corp. v. Desktop Direct, Inc., 511 U.S. 863, 867 (1994) (“The collateral order doctrine is best understood not as an exception to the ‘final decision’ rule laid down in Congress in § 1291, but as a ‘practical construction’ of it.”). | D65: Papotto v. Hartford Life & Accid. Insur. Co., 731 F.3d 265, 270-71 (3d Cir. 2013) | E65: Papotto | G65: 1 | H65: 52
A66: 29 | B66: 2 | D66: Kreider Dairy Farms, Inc. v. Glickman, 190 F.3d 113, 124 (3d Cir. 1999) (Sloviter, J., concurring) | E66: Kreider | G66: 1 | H66: 53
A67: 29 | B67: 3 | D67: Digital Equip. Corp. v. Desktop Direct, Inc., 511 U.S. 863, 867 (1994) | E67: Digital Equip Corp | G67: 1 | H67: 54
A68: 30 | B68: 1 | C68: Nicholas Bagley, Remedial Restraint in Administrative Law, 117 Colum. L. Rev. 253, 258 (2017) (quoting 5 U.S.C. § 706(2)). | D68: Nicholas Bagley, Remedial Restraint in Administrative Law, 117 Colum. L. Rev. 253, 258 (2017) | E68: Bagley | G68: 1 | H68: 55
A69: 30 | B69: 2 | D69: 5 U.S.C. § 706(2) | E69: 706 | G69: 1 | H69: 56
A70: 31 | B70: 1 | C70: Securities & Exch. Comm’n v. Chenery Corp., 332 U.S. 194, 196 (1947); see also Food & Drug Admin. v. Wages & White Lion Invs., LLC, 604 U.S. 542, 588-91 (2025) (most recent Supreme Court case discussing history and bounds of ordinary-remand rule); Robert L. Glicksman & Emily Hammond, Agency Behavior and Discretion on Remand, 32 J. Land Use & Env’t L. 483, 492-93 (2017) (discussing ordinary-remand rule); Christopher J. Walker, Referral, Remand, and Dialogue in Administrative Law, 101 Iowa L. Rev. Online 84, 86 (2016) (same); Christopher J. Walker, The Ordinary Remand Rule and the Judicial Toolbox for Agency Dialogue, 82 Geo. Wash. L. Rev. 1553, 1563 (2014) (same). | D70: Securities & Exch. Comm’n v. Chenery Corp., 332 U.S. 194, 196 (1947) | E70: Chenery Corp | G70: 1 | H70: 57
A71: 31 | B71: 2 | D71: Food & Drug Admin. v. Wages & White Lion Invs., LLC, 604 U.S. 542, 588-91 (2025) | E71: Wages and White Lion Invs | G71: 1 | H71: 58
A72: 31 | B72: 3 | D72: Robert L. Glicksman & Emily Hammond, Agency Behavior and Discretion on Remand, 32 J. Land Use & Env’t L. 483, 492-93 (2017) | E72: Glicksman | G72: 1 | H72: 59
A73: 31 | B73: 4 | D73: Christopher J. Walker, Referral, Remand, and Dialogue in Administrative Law, 101 Iowa L. Rev. Online 84, 86 (2016) | E73: Walker Referral | G73: 1 | H73: 60
A74: 31 | B74: 5 | D74: Christopher J. Walker, The Ordinary Remand Rule and the Judicial Toolbox for Agency Dialogue, 82 Geo. Wash. L. Rev. 1553, 1563 (2014) | E74: Walker Ordinary | G74: 1 | H74: 61
A75: 32 | B75: 1 | C75: See infra notes 257-261 and accompanying text for more discussion of remands with and without vacatur. | D75: infra notes 257-261 and accompanying text | E75: Infra Notes 257-261 and Accompanying Text | G75: 1 | H75: 62
A76: 33 | B76: 1 | C76: Joshua Revesz, Voluntary Remands: A Critical Reassessment, 70 Admin. L. Rev. 361, 366-69 (2018); Toni M. Fine, Agency Requests for “Voluntary” Remand: A Proposal for the Development of Judicial Standards, 28 Ariz. St. L.J. 1079, 1080 (1996). | D76: Joshua Revesz, Voluntary Remands: A Critical Reassessment, 70 Admin. L. Rev. 361, 366-69 (2018) | E76: Revesz | G76: 1 | H76: 63
A77: 33 | B77: 2 | D77: Toni M. Fine, Agency Requests for “Voluntary” Remand: A Proposal for the Development of Judicial Standards, 28 Ariz. St. L.J. 1079, 1080 (1996) | E77: Fine | G77: 1 | H77: 64
A78: 34 | B78: 1 | C78: Motor Vehicle Mfrs. Ass’n of U.S., Inc. v. State Farm Mut. Auto. Ins. Co., 463 U.S. 29, 43 (1983). | D78: Motor Vehicle Mfrs. Ass’n of U.S., Inc. v. State Farm Mut. Auto. Ins. Co., 463 U.S. 29, 43 (1983) | E78: Motor Vehicle Mfrs | G78: 1 | H78: 65
A79: 35 | B79: 1 | C79: Henry J. Friendly, Chenery Revisited: Reflections on Reversal and Remand of Administrative Orders, 1969 Duke L.J. 199, 205-18 (1969); Lynch, supra note 13, at 388. | D79: Henry J. Friendly, Chenery Revisited: Reflections on Reversal and Remand of Administrative Orders, 1969 Duke L.J. 199, 205-18 (1969) | E79: Friendly | G79: 1 | H79: 66
A80: 35 | B80: 2 | D80: Lynch, supra note 13, at 388 | E80: Lynch | G80: 2
A81: 36 | B81: 1 | C81: Julie C. Mendoza & R. Will Planert, Agency Remands Before the United States Court of International Trade: Objectives and Obstacles, 17 Tul. J. Int’l & Comp. L. 463, 470-89 (2009). | D81: Julie C. Mendoza & R. Will Planert, Agency Remands Before the United States Court of International Trade: Objectives and Obstacles, 17 Tul. J. Int’l & Comp. L. 463, 470-89 (2009) | E81: Mendoza | G81: 1 | H81: 67
A82: 37 | B82: 1 | C82: Pauly v. U.S. Dept. of Agri., 348 F.3d 1143, 1148 (9th Cir. 2003). | D82: Pauly v. U.S. Dept. of Agri., 348 F.3d 1143, 1148 (9th Cir. 2003) | E82: Pauly v US Dept of Agri | G82: 1 | H82: 68
A83: 38 | B83: 1 | C83: Vista Health Plan, Inc. v. U.S. Dep’t of Health & Human Servs., 31 F.4th 946, 951 (5th Cir. 2022). | D83: Vista Health Plan, Inc. v. U.S. Dep’t of Health & Human Servs., 31 F.4th 946, 951 (5th Cir. 2022) | E83: Vista | G83: 1 | H83: 69
A84: 39 | B84: 1 | C84: Act of Sept. 24, 1789, 1 Stat. 73, c. 20 §§ 21-22. | D84: Act of Sept. 24, 1789, 1 Stat. 73, c. 20 §§ 21-22 | E84: Act of Sept 24 | G84: 1 | H84: 70
A85: 40 | B85: 1 | C85: Federal Practice & Procedure, § 3906 History, 15A Fed. Prac. & Proc. Juris. § 3906 (3d ed. June 2024 Update) (citing Metcalfe’s Case, 11 Co. Rep. 38a, 77 Eng. Rep. 1193 (K.B. 1615) and intervening American cases). | D85: Federal Practice & Procedure, § 3906 History, 15A Fed. Prac. & Proc. Juris. § 3906 (3d ed. June 2024 Update) | E85: Federal Practice 3906 | G85: 1 | H85: 71
A86: 40 | B86: 2 | D86: Metcalfe’s Case, 11 Co. Rep. 38a, 77 Eng. Rep. 1193 (K.B. 1615) | E86: Metcalfe | G86: 1 | H86: 72
A87: 41 | B87: 1 | C87: Catlin v. United States, 324 U.S. 229, 233 (1945). | D87: Catlin v. United States, 324 U.S. 229, 233 (1945) | E87: Catlin v United States | G87: 1 | H87: 73
A88: 42 | B88: 1 | C88: 28 U.S.C. §§ 1291-1292, 62 Stat. 929 (1948). | D88: 28 U.S.C. § 1291 | E88: 1291 | G88: 2
A89: 1 | D89: 28 U.S.C. § 1292 | E89: 1292 | G89: 3
A90: 42 | B90: 2 | D90: 62 Stat. 929 (1948) | E90: 62 Stat | G90: 1 | H90: 74
A91: 43 | B91: 1 | C91: Bachowski v. Usery, 545 F.2d 363, 367 (3d Cir. 1976). These “instances” included grants or denials of preliminary injunctions, orders in receivership cases, and orders determining liability in admiralty cases prior to the assessment of damages. Katz v. Carte Blanche Corp., 496 F.2d 747, 753 (3d Cir. 1974). These interlocutory orders still make up the orders appealable under section 1292(a). See 28 U.S.C. § 1292(a). | D91: Bachowski v. Usery, 545 F.2d 363, 367 (3d Cir. 1976) | E91: Bachowski v Usery | G91: 1 | H91: 75
A92: 43 | B92: 2 | D92: Katz v. Carte Blanche Corp., 496 F.2d 747, 753 (3d Cir. 1974) | E92: Katz v Carte Blanche Corp | G92: 1 | H92: 76
A93: 43 | B93: 3 | D93: 28 U.S.C. § 1292(a) | E93: 1292 | G93: 4
A94: 44 | B94: 1 | C94: Bachowski, 545 F.2d at 367. | D94: Bachowski, 545 F.2d at 367 | E94: Bachowski v Usery | G94: 2
A95: 45 | B95: 1 | C95: Congress enacted 28 U.S.C. §§ 1291 and 1292 in 1948, only two years after enacting the APA. See P. Law 79-404, 60 Stat. 237 (1946). | D95: 28 U.S.C. § 1291 | E95: 1291 | G95: 3
A96: 1 | D96: 28 U.S.C. § 1292 | E96: 1292 | G96: 5
A97: 45 | B97: 2 | D97: P. Law 79-404, 60 Stat. 237 (1946) | E97: P. Law 79 | G97: 1 | H97: 77
A98: 46 | B98: 1 | C98: Cobbledick v. United States, 309 U.S. 323, 326 (1940); see also § 3907 Purposes, 15A Fed. Prac. & Proc. Juris. § 3907 (3d ed.) (describing the final-judgment rule as “the heart of appellate jurisdiction in the federal system”). | D98: Cobbledick v. United States, 309 U.S. 323, 326 (1940) | E98: Cobbledick | G98: 1 | H98: 78
A99: 46 | B99: 2 | D99: § 3907 Purposes, 15A Fed. Prac. & Proc. Juris. § 3907 (3d ed.) | E99: Federal Practice 3907 | G99: 1 | H99: 79
A100: 47 | B100: 1 | C100: See, e.g., Microsoft Corp. v. Baker, 582 U.S. 23, 27-29 (2017); Mohawk Indus., Inc. v. Carpenter, 558 U.S. 100, 106-07 (2009); Johnson v. Jones, 515 U.S. 304, 309 (1995); Digital Equip. Corp., 511 U.S. at 867-84; Di Bella v. United States, 369 U.S. 121, 124-26 (1962); Cobbledick, 309 U.S. at 325; Federal Practice & Procedure, § 3907 Purposes, 15A Fed. Prac. & Proc. Juris. § 3907 (3d ed. June 2024 Update); Bryan Lammon, Disarming the Finality Trap, 97 NYU L. Rev. Online 173, 178 (2022); Theodore D. Frank, Requiem for the Final Judgment Rule, 45 Tex. L. Rev. 292, 294-98 (1966); see also infra notes 53-97 and accompanying text (discussing these and other Supreme Court finality cases, many of which examine the final-judgment rule’s rationales and benefits). | D100: Microsoft Corp. v. Baker, 582 U.S. 23, 27-29 (2017) | E100: Microsoft Corp v Baker | G100: 1 | H100: 80
...

Sheet Sourcepull (Old)
A1: ID | B1: Short Name | C1: Fn# | D1: Full Source Citation | F1: Sourcepull File Name (DNE) | G1: Sourcepuller | H1: Completed? | I1: All Pincites (for books) | J1: Consecutively Paginated? | K1: Subseqent History / Negative Treatment? | L1: Location of Source (Green, Crown, etc.) | M1: ILL or Recall and Date of Request (books only) | N1: Problems or Comments | O1: Sourcepull checked by SE?
B2: =IFERROR(__xludf.DUMMYFUNCTION("FILTER('Raw Output'!E:E, 'Raw Output'!$G:$G=1)"),"Source Name") -> Source Name | C2: =IFERROR(__xludf.DUMMYFUNCTION("FILTER(TEXT('Raw Output'!A:A, ""000""), 'Raw Output'!$G:$G=1)"),"001") -> 001 | D2: =IFERROR(__xludf.DUMMYFUNCTION("FILTER('Raw Output'!D:D, 'Raw Output'!$G:$G=1)"),"Citation Text") -> Citation Text | E2: {=if($B$2:$B952 <> "", hyperlink("https://drive.google.com/drive/search?q=parent:" & Properties!$C$8 & "%20" & char(34) & $F$2:$F952 & char(34), "➔"), "")} -> ➔ | F2: {=if($B$2:$B952<>"","SP-"&$A$2:$A952 &"-"&$B$2:$B952&".pdf", "")} -> SP--Source Name.pdf
A3: 001 | B3: =IFERROR(__xludf.DUMMYFUNCTION("""COMPUTED_VALUE"""),"Tortorich") -> Tortorich | C3: =IFERROR(__xludf.DUMMYFUNCTION("""COMPUTED_VALUE"""),"002") -> 002 | D3: =IFERROR(__xludf.DUMMYFUNCTION("""COMPUTED_VALUE"""),"Frank Tortorich, Jr., The Opening of the Carson River Route, 18 Overland Journal 1, 22 (Spring 2000)") -> Frank Tortorich, Jr., The Opening of the Carson River Route, 18 Overland Journal 1, 22 (Spring 2000) | E3: ➔ | F3: SP-001-Tortorich.pdf | G3: ME
A4: 002 | B4: =IFERROR(__xludf.DUMMYFUNCTION("""COMPUTED_VALUE"""),"Munson") -> Munson | C4: =IFERROR(__xludf.DUMMYFUNCTION("""COMPUTED_VALUE"""),"002") -> 002 | D4: =IFERROR(__xludf.DUMMYFUNCTION("""COMPUTED_VALUE"""),"Jeff Munson, “Emigrant Trail tour promises spectacular colors,” Tahoe Daily Tribune (Oct. 12, 2005), https://www.tahoedailytribune.com/news/emigrant-trail-tour-promises-spectacular-colors/") -> Jeff Munson, “Emigrant Trail tour promises spectacular colors,” Tahoe Daily Tribune (Oct. 12, 2005), https://www.tahoedailytribune.com/news/emigrant-trail-tour-promises-spectacular-colors/ | E4: ➔ | F4: SP-002-Munson.pdf | G4: ME
A5: 003 | B5: =IFERROR(__xludf.DUMMYFUNCTION("""COMPUTED_VALUE"""),"Hope Valley Recreation") -> Hope Valley Recreation | C5: =IFERROR(__xludf.DUMMYFUNCTION("""COMPUTED_VALUE"""),"003") -> 003 | D5: =IFERROR(__xludf.DUMMYFUNCTION("""COMPUTED_VALUE"""),"https://www.fs.usda.gov/Internet/FSE_DOCUMENTS/stelprdb5294291.pdf.") -> https://www.fs.usda.gov/Internet/FSE_DOCUMENTS/stelprdb5294291.pdf. | E5: ➔ | F5: SP-003-Hope Valley Recreation.pdf | G5: ME
A6: 004 | B6: =IFERROR(__xludf.DUMMYFUNCTION("""COMPUTED_VALUE"""),"Memorandum") -> Memorandum | C6: =IFERROR(__xludf.DUMMYFUNCTION("""COMPUTED_VALUE"""),"004") -> 004 | D6: =IFERROR(__xludf.DUMMYFUNCTION("""COMPUTED_VALUE"""),"Memorandum of Opinion and Order, Friends of Hope Valley v. U.S. Forest Serv., No. 2:00-cv-01900-DFL-KJM, 2 (E.D. Cal. Sept. 30, 2004)") -> Memorandum of Opinion and Order, Friends of Hope Valley v. U.S. Forest Serv., No. 2:00-cv-01900-DFL-KJM, 2 (E.D. Cal. Sept. 30, 2004) | E6: ➔ | F6: SP-004-Memorandum.pdf | G6: ME
A7: 005 | B7: =IFERROR(__xludf.DUMMYFUNCTION("""COMPUTED_VALUE"""),"Friends of Hope Valley v US Forest Service") -> Friends of Hope Valley v US Forest Service | C7: =IFERROR(__xludf.DUMMYFUNCTION("""COMPUTED_VALUE"""),"006") -> 006 | D7: =IFERROR(__xludf.DUMMYFUNCTION("""COMPUTED_VALUE"""),"Friends of Hope Valley v. U.S. Forest Service, 203 Fed. Appx. 883 (9th Cir. 2006) (unpublished)") -> Friends of Hope Valley v. U.S. Forest Service, 203 Fed. Appx. 883 (9th Cir. 2006) (unpublished) | E7: ➔ | F7: SP-005-Friends of Hope Valley v US Forest Service.pdf | G7: ME
A8: 006 | B8: =IFERROR(__xludf.DUMMYFUNCTION("""COMPUTED_VALUE"""),"APA") -> APA | C8: =IFERROR(__xludf.DUMMYFUNCTION("""COMPUTED_VALUE"""),"007") -> 007 | D8: =IFERROR(__xludf.DUMMYFUNCTION("""COMPUTED_VALUE"""),"5 U.S.C. §§ 551-553, 701-706") -> 5 U.S.C. §§ 551-553, 701-706 | E8: ➔ | F8: SP-006-APA.pdf | G8: ME
A9: 007 | B9: =IFERROR(__xludf.DUMMYFUNCTION("""COMPUTED_VALUE"""),"Infra Notes 113, 151-153") -> Infra Notes 113, 151-153 | C9: =IFERROR(__xludf.DUMMYFUNCTION("""COMPUTED_VALUE"""),"007") -> 007 | D9: =IFERROR(__xludf.DUMMYFUNCTION("""COMPUTED_VALUE"""),"infra notes 113, 151-153") -> infra notes 113, 151-153 | E9: ➔ | F9: SP-007-Infra Notes 113, 151-153.pdf | G9: ME
A10: 008 | B10: =IFERROR(__xludf.DUMMYFUNCTION("""COMPUTED_VALUE"""),"Alsea Valley Alliance v Dep't of Commerce") -> Alsea Valley Alliance v Dep't of Commerce | C10: =IFERROR(__xludf.DUMMYFUNCTION("""COMPUTED_VALUE"""),"008") -> 008 | D10: =IFERROR(__xludf.DUMMYFUNCTION("""COMPUTED_VALUE"""),"Alsea Valley Alliance v. Dep’t of Commerce, 358 F.3d 1181, 1184 (9th Cir. 2004)") -> Alsea Valley Alliance v. Dep’t of Commerce, 358 F.3d 1181, 1184 (9th Cir. 2004) | E10: ➔ | F10: SP-008-Alsea Valley Alliance v Dep't of Commerce.pdf | G10: ME
A11: 009 | B11: =IFERROR(__xludf.DUMMYFUNCTION("""COMPUTED_VALUE"""),"Infra Part IB") -> Infra Part IB | C11: =IFERROR(__xludf.DUMMYFUNCTION("""COMPUTED_VALUE"""),"009") -> 009 | D11: =IFERROR(__xludf.DUMMYFUNCTION("""COMPUTED_VALUE"""),"infra Part I.B") -> infra Part I.B | E11: ➔ | F11: SP-009-Infra Part IB.pdf | G11: ME
A12: 010 | B12: =IFERROR(__xludf.DUMMYFUNCTION("""COMPUTED_VALUE"""),"Infra Note 23") -> Infra Note 23 | C12: =IFERROR(__xludf.DUMMYFUNCTION("""COMPUTED_VALUE"""),"009") -> 009 | D12: =IFERROR(__xludf.DUMMYFUNCTION("""COMPUTED_VALUE"""),"infra note 23") -> infra note 23 | E12: ➔ | F12: SP-010-Infra Note 23.pdf | G12: ME
A13: 011 | B13: =IFERROR(__xludf.DUMMYFUNCTION("""COMPUTED_VALUE"""),"Denver Cnty") -> Denver Cnty | C13: =IFERROR(__xludf.DUMMYFUNCTION("""COMPUTED_VALUE"""),"010") -> 010 | D13: =IFERROR(__xludf.DUMMYFUNCTION("""COMPUTED_VALUE"""),"C.W. by and through B.W. v. Denver Cnty. Sch. Dist. No. 1, 994 F.3d 1215, 1220 n.2 (10th Cir. 2021)") -> C.W. by and through B.W. v. Denver Cnty. Sch. Dist. No. 1, 994 F.3d 1215, 1220 n.2 (10th Cir. 2021) | E13: ➔ | F13: SP-011-Denver Cnty.pdf | G13: ME
A14: 012 | B14: =IFERROR(__xludf.DUMMYFUNCTION("""COMPUTED_VALUE"""),"Montana Env't Info CTR") -> Montana Env't Info CTR | C14: =IFERROR(__xludf.DUMMYFUNCTION("""COMPUTED_VALUE"""),"010") -> 010 | D14: =IFERROR(__xludf.DUMMYFUNCTION("""COMPUTED_VALUE"""),"Montana Env’t Info. Ctr. v. Haaland, No. 22-36002, 2023 WL 8166779, at *1 (9th Cir. Nov. 24, 2023)") -> Montana Env’t Info. Ctr. v. Haaland, No. 22-36002, 2023 WL 8166779, at *1 (9th Cir. Nov. 24, 2023) | E14: ➔ | F14: SP-012-Montana Env't Info CTR.pdf | G14: ME
A15: 013 | B15: =IFERROR(__xludf.DUMMYFUNCTION("""COMPUTED_VALUE"""),"Dcor") -> Dcor | C15: =IFERROR(__xludf.DUMMYFUNCTION("""COMPUTED_VALUE"""),"010") -> 010 | D15: =IFERROR(__xludf.DUMMYFUNCTION("""COMPUTED_VALUE"""),"DCOR, LLC v. U.S. Dep’t of the Interior, No. 3:21-CV-00120-N, 2023 WL 8628322, at *1 (N.D. Tex. Dec. 13, 2023)") -> DCOR, LLC v. U.S. Dep’t of the Interior, No. 3:21-CV-00120-N, 2023 WL 8628322, at *1 (N.D. Tex. Dec. 13, 2023) | E15: ➔ | F15: SP-013-Dcor.pdf | G15: ME
A16: 014 | B16: =IFERROR(__xludf.DUMMYFUNCTION("""COMPUTED_VALUE"""),"Infra Part I") -> Infra Part I | C16: =IFERROR(__xludf.DUMMYFUNCTION("""COMPUTED_VALUE"""),"011") -> 011 | D16: =IFERROR(__xludf.DUMMYFUNCTION("""COMPUTED_VALUE"""),"Part I, infra") -> Part I, infra | E16: ➔ | F16: SP-014-Infra Part I.pdf | G16: ME
A17: 015 | B17: =IFERROR(__xludf.DUMMYFUNCTION("""COMPUTED_VALUE"""),"Michaels") -> Michaels | C17: =IFERROR(__xludf.DUMMYFUNCTION("""COMPUTED_VALUE"""),"001") -> 001 | D17: =IFERROR(__xludf.DUMMYFUNCTION("""COMPUTED_VALUE"""),"Jon D. Michaels, Constitutional Coup: Privatization’s Threat to the American Republic, 21-77 (2017)") -> Jon D. Michaels, Constitutional Coup: Privatization’s Threat to the American Republic, 21-77 (2017) | E17: ➔ | F17: SP-015-Michaels.pdf | G17: ME
A18: 016 | B18: =IFERROR(__xludf.DUMMYFUNCTION("""COMPUTED_VALUE"""),"Developments") -> Developments | C18: =IFERROR(__xludf.DUMMYFUNCTION("""COMPUTED_VALUE"""),"011") -> 011 | D18: =IFERROR(__xludf.DUMMYFUNCTION("""COMPUTED_VALUE"""),"Developments in the Law—Presidential Authority, V. Executive Appointments, 125 Harv. L. Rev. 2135, 2138 (2012)") -> Developments in the Law—Presidential Authority, V. Executive Appointments, 125 Harv. L. Rev. 2135, 2138 (2012) | E18: ➔ | F18: SP-016-Developments.pdf | G18: ME
A19: 017 | B19: =IFERROR(__xludf.DUMMYFUNCTION("""COMPUTED_VALUE"""),"Ho") -> Ho | C19: =IFERROR(__xludf.DUMMYFUNCTION("""COMPUTED_VALUE"""),"011") -> 011 | D19: =IFERROR(__xludf.DUMMYFUNCTION("""COMPUTED_VALUE"""),"Daniel E. Ho & Erica L. Ross, Did Liberal Justices Invent the Standing Doctrine? An Empirical Study of the Evolution of Standing, 1921-2006, 62 Stan. L. Rev. 591, 647 & n.231 (2010)") -> Daniel E. Ho & Erica L. Ross, Did Liberal Justices Invent the Standing Doctrine? An Empirical Study of the Evolution of Standing, 1921-2006, 62 Stan. L. Rev. 591, 647 & n.231 (2010) | E19: ➔ | F19: SP-017-Ho.pdf | G19: ME
A20: 018 | B20: =IFERROR(__xludf.DUMMYFUNCTION("""COMPUTED_VALUE"""),"Jordan") -> Jordan | C20: =IFERROR(__xludf.DUMMYFUNCTION("""COMPUTED_VALUE"""),"011") -> 011 | D20: =IFERROR(__xludf.DUMMYFUNCTION("""COMPUTED_VALUE"""),"William S. Jordan, III, Judges, Ideology, and Policy in the Administrative State: Lessons from A Decade of Hard Look Remands of EPA Rules, 53 Admin. L. Rev. 45, 46 (2001)") -> William S. Jordan, III, Judges, Ideology, and Policy in the Administrative State: Lessons from A Decade of Hard Look Remands of EPA Rules, 53 Admin. L. Rev. 45, 46 (2001) | E20: ➔ | F20: SP-018-Jordan.pdf | G20: ME
A21: 019 | B21: =IFERROR(__xludf.DUMMYFUNCTION("""COMPUTED_VALUE"""),"Finkelstein") -> Finkelstein | C21: =IFERROR(__xludf.DUMMYFUNCTION("""COMPUTED_VALUE"""),"012") -> 012 | D21: =IFERROR(__xludf.DUMMYFUNCTION("""COMPUTED_VALUE"""),"Sullivan v. Finkelstein, 496 U.S. 617, 625 (1990)") -> Sullivan v. Finkelstein, 496 U.S. 617, 625 (1990) | E21: ➔ | F21: SP-019-Finkelstein.pdf | G21: ME
A22: 020 | B22: =IFERROR(__xludf.DUMMYFUNCTION("""COMPUTED_VALUE"""),"Infra Notes 89-97 and Accompanying Text Pp 17-19") -> Infra Notes 89-97 and Accompanying Text Pp 17-19 | C22: =IFERROR(__xludf.DUMMYFUNCTION("""COMPUTED_VALUE"""),"012") -> 012 | D22: =IFERROR(__xludf.DUMMYFUNCTION("""COMPUTED_VALUE"""),"infra notes 89-97 and accompanying text pp. 17-19") -> infra notes 89-97 and accompanying text pp. 17-19 | E22: ➔ | F22: SP-020-Infra Notes 89-97 and Accompanying Text Pp 17-19.pdf | G22: ME
A23: 021 | B23: =IFERROR(__xludf.DUMMYFUNCTION("""COMPUTED_VALUE"""),"Lammon Appealability") -> Lammon Appealability | C23: =IFERROR(__xludf.DUMMYFUNCTION("""COMPUTED_VALUE"""),"013") -> 013 | D23: =IFERROR(__xludf.DUMMYFUNCTION("""COMPUTED_VALUE"""),"Bryan Lammon, Finality, Appealability, and the Scope of Interlocutory Review, 93 Wash. L. Rev. 1809, 1834-37 (2018)") -> Bryan Lammon, Finality, Appealability, and the Scope of Interlocutory Review, 93 Wash. L. Rev. 1809, 1834-37 (2018) | E23: ➔ | F23: SP-021-Lammon Appealability.pdf | G23: ME
A24: 022 | B24: =IFERROR(__xludf.DUMMYFUNCTION("""COMPUTED_VALUE"""),"Lammon Dizzying") -> Lammon Dizzying | C24: =IFERROR(__xludf.DUMMYFUNCTION("""COMPUTED_VALUE"""),"013") -> 013 | D24: =IFERROR(__xludf.DUMMYFUNCTION("""COMPUTED_VALUE"""),"Bryan Lammon, Dizzying Gillespie: The Exaggerated Death of the Balancing Approach and the Inescapable Allure of Flexibility in Appellate Jurisdiction, 51 U. Rich. L. Rev. 371, 386-93 (2017)") -> Bryan Lammon, Dizzying Gillespie: The Exaggerated Death of the Balancing Approach and the Inescapable Allure of Flexibility in Appellate Jurisdiction, 51 U. Rich. L. Rev. 371, 386-93 (2017) | E24: ➔ | F24: SP-022-Lammon Dizzying.pdf | G24: ME
A25: 023 | B25: =IFERROR(__xludf.DUMMYFUNCTION("""COMPUTED_VALUE"""),"Krent") -> Krent | C25: =IFERROR(__xludf.DUMMYFUNCTION("""COMPUTED_VALUE"""),"013") -> 013 | D25: =IFERROR(__xludf.DUMMYFUNCTION("""COMPUTED_VALUE"""),"Harold J. Krent, Situating Structural Challenges to Agency Authority Within the Framework of the Finality Principle, 98 Ind. L.J. Supplement 1, 10 n.73 (2023)") -> Harold J. Krent, Situating Structural Challenges to Agency Authority Within the Framework of the Finality Principle, 98 Ind. L.J. Supplement 1, 10 n.73 (2023) | E25: ➔ | F25: SP-023-Krent.pdf | G25: ME
A26: 024 | B26: =IFERROR(__xludf.DUMMYFUNCTION("""COMPUTED_VALUE"""),"Biever") -> Biever | C26: =IFERROR(__xludf.DUMMYFUNCTION("""COMPUTED_VALUE"""),"013") -> 013 | D26: =IFERROR(__xludf.DUMMYFUNCTION("""COMPUTED_VALUE"""),"Jennifer L. Biever & Ana Maria Gutierrez, The Uncertain Question of Remedies Should a Challenge Prevail, 2016 NO. 5 RMMLF-INST PAPER NO. 13, 28-29 (2016)") -> Jennifer L. Biever & Ana Maria Gutierrez, The Uncertain Question of Remedies Should a Challenge Prevail, 2016 NO. 5 RMMLF-INST PAPER NO. 13, 28-29 (2016) | E26: ➔ | F26: SP-024-Biever.pdf | G26: ME
A27: 025 | B27: =IFERROR(__xludf.DUMMYFUNCTION("""COMPUTED_VALUE"""),"Lynch") -> Lynch | C27: =IFERROR(__xludf.DUMMYFUNCTION("""COMPUTED_VALUE"""),"013") -> 013 | D27: =IFERROR(__xludf.DUMMYFUNCTION("""COMPUTED_VALUE"""),"Michele D. Lynch, Remands Are A Consequence of Administrative Law, So Why Are We All So Frustrated?, 23 Tul. J. Int’l & Comp. L. 383, 392 (2015)") -> Michele D. Lynch, Remands Are A Consequence of Administrative Law, So Why Are We All So Frustrated?, 23 Tul. J. Int’l & Comp. L. 383, 392 (2015) | E27: ➔ | F27: SP-025-Lynch.pdf | G27: ME
A28: 026 | B28: =IFERROR(__xludf.DUMMYFUNCTION("""COMPUTED_VALUE"""),"Federal Practice 3914 32") -> Federal Practice 3914 32 | C28: =IFERROR(__xludf.DUMMYFUNCTION("""COMPUTED_VALUE"""),"013") -> 013 | D28: =IFERROR(__xludf.DUMMYFUNCTION("""COMPUTED_VALUE"""),"Federal Practice & Procedure, § 3914.32 Orders Prior to Trial—Administrative Review, 15B Fed. Prac. & Proc. Juris. § 3914.32 (2d ed. June 2024 Update)") -> Federal Practice & Procedure, § 3914.32 Orders Prior to Trial—Administrative Review, 15B Fed. Prac. & Proc. Juris. § 3914.32 (2d ed. June 2024 Update) | E28: ➔ | F28: SP-026-Federal Practice 3914 32.pdf | G28: ME
A29: 027 | B29: =IFERROR(__xludf.DUMMYFUNCTION("""COMPUTED_VALUE"""),"Federal Practice 3903") -> Federal Practice 3903 | C29: =IFERROR(__xludf.DUMMYFUNCTION("""COMPUTED_VALUE"""),"013") -> 013 | D29: =IFERROR(__xludf.DUMMYFUNCTION("""COMPUTED_VALUE"""),"Federal Practice & Procedure, § 3903 Pragmatic Finality, 15A Fed. Prac. & Proc. Juris. § 3913 (3d ed. June 2024 Update)") -> Federal Practice & Procedure, § 3903 Pragmatic Finality, 15A Fed. Prac. & Proc. Juris. § 3913 (3d ed. June 2024 Update) | E29: ➔ | F29: SP-027-Federal Practice 3903.pdf | G29: ME
A30: 028 | B30: =IFERROR(__xludf.DUMMYFUNCTION("""COMPUTED_VALUE"""),"73a CJS") -> 73a CJS | C30: =IFERROR(__xludf.DUMMYFUNCTION("""COMPUTED_VALUE"""),"013") -> 013 | D30: =IFERROR(__xludf.DUMMYFUNCTION("""COMPUTED_VALUE"""),"73A C.J.S. Pub. Admin. Law & Proc. § 561 (May 2024)") -> 73A C.J.S. Pub. Admin. Law & Proc. § 561 (May 2024) | E30: ➔ | F30: SP-028-73a CJS.pdf | G30: ME
A31: 029 | B31: =IFERROR(__xludf.DUMMYFUNCTION("""COMPUTED_VALUE"""),"Fed Ct") -> Fed Ct | C31: =IFERROR(__xludf.DUMMYFUNCTION("""COMPUTED_VALUE"""),"013") -> 013 | D31: =IFERROR(__xludf.DUMMYFUNCTION("""COMPUTED_VALUE"""),"Fed. Ct. App. Manual § 2:3 (7th ed. May 2024)") -> Fed. Ct. App. Manual § 2:3 (7th ed. May 2024) | E31: ➔ | F31: SP-029-Fed Ct.pdf | G31: ME
A32: 030 | B32: =IFERROR(__xludf.DUMMYFUNCTION("""COMPUTED_VALUE"""),"Infra Notes 39-51 and Accompanying Text") -> Infra Notes 39-51 and Accompanying Text | C32: =IFERROR(__xludf.DUMMYFUNCTION("""COMPUTED_VALUE"""),"014") -> 014 | D32: =IFERROR(__xludf.DUMMYFUNCTION("""COMPUTED_VALUE"""),"infra notes 39-51 and accompanying text") -> infra notes 39-51 and accompanying text | E32: ➔ | F32: SP-030-Infra Notes 39-51 and Accompanying Text.pdf | G32: ME
A33: 031 | B33: =IFERROR(__xludf.DUMMYFUNCTION("""COMPUTED_VALUE"""),"Infra Notes 46-48 and Accompanying Text") -> Infra Notes 46-48 and Accompanying Text | C33: =IFERROR(__xludf.DUMMYFUNCTION("""COMPUTED_VALUE"""),"015") -> 015 | D33: =IFERROR(__xludf.DUMMYFUNCTION("""COMPUTED_VALUE"""),"infra notes 46-48 and accompanying text") -> infra notes 46-48 and accompanying text | E33: ➔ | F33: SP-031-Infra Notes 46-48 and Accompanying Text.pdf | G33: ME
A34: 032 | B34: =IFERROR(__xludf.DUMMYFUNCTION("""COMPUTED_VALUE"""),"Pueblo of Sandia v Babbitt") -> Pueblo of Sandia v Babbitt | C34: =IFERROR(__xludf.DUMMYFUNCTION("""COMPUTED_VALUE"""),"016") -> 016 | D34: =IFERROR(__xludf.DUMMYFUNCTION("""COMPUTED_VALUE"""),"Pueblo of Sandia v. Babbitt, 231 F.3d 878, 880 (D.C. Cir. 2000)") -> Pueblo of Sandia v. Babbitt, 231 F.3d 878, 880 (D.C. Cir. 2000) | E34: ➔ | F34: SP-032-Pueblo of Sandia v Babbitt.pdf | G34: ME
A35: 033 | B35: =IFERROR(__xludf.DUMMYFUNCTION("""COMPUTED_VALUE"""),"CTR for Biological Diversity v Bureau of Land MGMT") -> CTR for Biological Diversity v Bureau of Land MGMT | C35: =IFERROR(__xludf.DUMMYFUNCTION("""COMPUTED_VALUE"""),"017") -> 017 | D35: =IFERROR(__xludf.DUMMYFUNCTION("""COMPUTED_VALUE"""),"Ctr. for Biological Diversity v. Bureau of Land Mgmt., 69 F.4th 588, 597-98 (9th Cir. 2023) (Friedland and Bennett, JJ., concurring)") -> Ctr. for Biological Diversity v. Bureau of Land Mgmt., 69 F.4th 588, 597-98 (9th Cir. 2023) (Friedland and Bennett, JJ., concurring) | E35: ➔ | F35: SP-033-CTR for Biological Diversity v Bureau of Land MGMT.pdf | G35: ME
A36: 034 | B36: =IFERROR(__xludf.DUMMYFUNCTION("""COMPUTED_VALUE"""),"NY Legal Assistance GRP v Cardona") -> NY Legal Assistance GRP v Cardona | C36: =IFERROR(__xludf.DUMMYFUNCTION("""COMPUTED_VALUE"""),"017") -> 017 | D36: =IFERROR(__xludf.DUMMYFUNCTION("""COMPUTED_VALUE"""),"N.Y. Legal Assistance Grp. v. Cardona, No. 21-888-CV, 2024 WL 64220, at *3-4 (2d Cir. Jan. 5, 2024)") -> N.Y. Legal Assistance Grp. v. Cardona, No. 21-888-CV, 2024 WL 64220, at *3-4 (2d Cir. Jan. 5, 2024) | E36: ➔ | F36: SP-034-NY Legal Assistance GRP v Cardona.pdf | G36: ME
A37: 035 | B37: =IFERROR(__xludf.DUMMYFUNCTION("""COMPUTED_VALUE"""),"Infra Notes 132-192 and Accompanying Text") -> Infra Notes 132-192 and Accompanying Text | C37: =IFERROR(__xludf.DUMMYFUNCTION("""COMPUTED_VALUE"""),"018") -> 018 | D37: =IFERROR(__xludf.DUMMYFUNCTION("""COMPUTED_VALUE"""),"infra notes 132-192 and accompanying text") -> infra notes 132-192 and accompanying text | E37: ➔ | F37: SP-035-Infra Notes 132-192 and Accompanying Text.pdf | G37: ME
A38: 036 | B38: =IFERROR(__xludf.DUMMYFUNCTION("""COMPUTED_VALUE"""),"Infra Notes 193-194") -> Infra Notes 193-194 | C38: =IFERROR(__xludf.DUMMYFUNCTION("""COMPUTED_VALUE"""),"019") -> 019 | D38: =IFERROR(__xludf.DUMMYFUNCTION("""COMPUTED_VALUE"""),"infra notes 193-194, 262-270 and accompanying text") -> infra notes 193-194, 262-270 and accompanying text | E38: ➔ | F38: SP-036-Infra Notes 193-194.pdf | G38: ME
A39: 037 | B39: =IFERROR(__xludf.DUMMYFUNCTION("""COMPUTED_VALUE"""),"Clopton") -> Clopton | C39: =IFERROR(__xludf.DUMMYFUNCTION("""COMPUTED_VALUE"""),"020") -> 020 | D39: =IFERROR(__xludf.DUMMYFUNCTION("""COMPUTED_VALUE"""),"Zachary D. Clopton & Katherine Shaw, Public Law Litigation and Electoral Time, 2023 Wis. L. Rev. 1513, 1521–22 (2023)") -> Zachary D. Clopton & Katherine Shaw, Public Law Litigation and Electoral Time, 2023 Wis. L. Rev. 1513, 1521–22 (2023) | E39: ➔ | F39: SP-037-Clopton.pdf | G39: ME
A40: 038 | B40: =IFERROR(__xludf.DUMMYFUNCTION("""COMPUTED_VALUE"""),"Jackson") -> Jackson | C40: =IFERROR(__xludf.DUMMYFUNCTION("""COMPUTED_VALUE"""),"021") -> 021 | D40: =IFERROR(__xludf.DUMMYFUNCTION("""COMPUTED_VALUE"""),"Jackson v. Bd. of Civ. Serv. Comm’rs of City of Los Angeles, 99 Cal. App. 5th 648, 655-62, 318 Cal. Rptr. 3d 79 (2024)") -> Jackson v. Bd. of Civ. Serv. Comm’rs of City of Los Angeles, 99 Cal. App. 5th 648, 655-62, 318 Cal. Rptr. 3d 79 (2024) | E40: ➔ | F40: SP-038-Jackson.pdf | G40: ME
A41: 039 | B41: =IFERROR(__xludf.DUMMYFUNCTION("""COMPUTED_VALUE"""),"John Muir Health") -> John Muir Health | C41: =IFERROR(__xludf.DUMMYFUNCTION("""COMPUTED_VALUE"""),"021") -> 021 | D41: =IFERROR(__xludf.DUMMYFUNCTION("""COMPUTED_VALUE"""),"Dhillon v. John Muir Health, 2 Cal. 5th 1109, 1116, 394 P.3d 1048 (2017)") -> Dhillon v. John Muir Health, 2 Cal. 5th 1109, 1116, 394 P.3d 1048 (2017) | E41: ➔ | F41: SP-039-John Muir Health.pdf | G41: ME
A42: 040 | B42: =IFERROR(__xludf.DUMMYFUNCTION("""COMPUTED_VALUE"""),"Federman") -> Federman | C42: =IFERROR(__xludf.DUMMYFUNCTION("""COMPUTED_VALUE"""),"021") -> 021 | D42: =IFERROR(__xludf.DUMMYFUNCTION("""COMPUTED_VALUE"""),"Federman v. Bd. of Appeals of Marblehead, 35 Mass. App. Ct. 727, 729-30, 626 N.E. 2d 8 (Mass. 1994)") -> Federman v. Bd. of Appeals of Marblehead, 35 Mass. App. Ct. 727, 729-30, 626 N.E. 2d 8 (Mass. 1994) | E42: ➔ | F42: SP-040-Federman.pdf | G42: ME
A43: 041 | B43: =IFERROR(__xludf.DUMMYFUNCTION("""COMPUTED_VALUE"""),"Holton") -> Holton | C43: =IFERROR(__xludf.DUMMYFUNCTION("""COMPUTED_VALUE"""),"021") -> 021 | D43: =IFERROR(__xludf.DUMMYFUNCTION("""COMPUTED_VALUE"""),"Holton Transp., Inc. v. Kansas Corp. Comm’n, 10 Kan. App. 2d 12, 12-13, 690 P.2d 399 (Kan. 1984)") -> Holton Transp., Inc. v. Kansas Corp. Comm’n, 10 Kan. App. 2d 12, 12-13, 690 P.2d 399 (Kan. 1984) | E43: ➔ | F43: SP-041-Holton.pdf | G43: LJ
A44: 042 | B44: =IFERROR(__xludf.DUMMYFUNCTION("""COMPUTED_VALUE"""),"Bearns") -> Bearns | C44: =IFERROR(__xludf.DUMMYFUNCTION("""COMPUTED_VALUE"""),"021") -> 021 | D44: =IFERROR(__xludf.DUMMYFUNCTION("""COMPUTED_VALUE"""),"Bearns v. Dep’t of Indus., Labor & Human Relations, 76-78. 306 N.W. 2d 22 (Wis. 1981)") -> Bearns v. Dep’t of Indus., Labor & Human Relations, 76-78. 306 N.W. 2d 22 (Wis. 1981) | E44: ➔ | F44: SP-042-Bearns.pdf | G44: LJ
A45: 043 | B45: =IFERROR(__xludf.DUMMYFUNCTION("""COMPUTED_VALUE"""),"Am Constr Co") -> Am Constr Co | C45: =IFERROR(__xludf.DUMMYFUNCTION("""COMPUTED_VALUE"""),"022") -> 022 | D45: =IFERROR(__xludf.DUMMYFUNCTION("""COMPUTED_VALUE"""),"Am. Constr. Co. v. Jacksonville, Tampa & Key West Ry. Co., 148 U.S. 372, 384 (1893)") -> Am. Constr. Co. v. Jacksonville, Tampa & Key West Ry. Co., 148 U.S. 372, 384 (1893) | E45: ➔ | F45: SP-043-Am Constr Co.pdf | G45: LJ
A46: 044 | B46: =IFERROR(__xludf.DUMMYFUNCTION("""COMPUTED_VALUE"""),"Infra Notes 29") -> Infra Notes 29 | C46: =IFERROR(__xludf.DUMMYFUNCTION("""COMPUTED_VALUE"""),"023") -> 023 | D46: =IFERROR(__xludf.DUMMYFUNCTION("""COMPUTED_VALUE"""),"infra notes 29, 94, 113") -> infra notes 29, 94, 113 | E46: ➔ | F46: SP-044-Infra Notes 29.pdf | G46: LJ
A47: 045 | B47: =IFERROR(__xludf.DUMMYFUNCTION("""COMPUTED_VALUE"""),1291.0) -> 1291 | C47: =IFERROR(__xludf.DUMMYFUNCTION("""COMPUTED_VALUE"""),"024") -> 024 | D47: =IFERROR(__xludf.DUMMYFUNCTION("""COMPUTED_VALUE"""),"28 U.S.C. § 1291") -> 28 U.S.C. § 1291 | E47: ➔ | F47: SP-045-1291.pdf | G47: LJ
A48: 046 | B48: =IFERROR(__xludf.DUMMYFUNCTION("""COMPUTED_VALUE"""),1292.0) -> 1292 | C48: =IFERROR(__xludf.DUMMYFUNCTION("""COMPUTED_VALUE"""),"025") -> 025 | D48: =IFERROR(__xludf.DUMMYFUNCTION("""COMPUTED_VALUE"""),"28 U.S.C. § 1292") -> 28 U.S.C. § 1292 | E48: ➔ | F48: SP-046-1292.pdf | G48: LJ
A49: 047 | B49: =IFERROR(__xludf.DUMMYFUNCTION("""COMPUTED_VALUE"""),"Federal Rule") -> Federal Rule | C49: =IFERROR(__xludf.DUMMYFUNCTION("""COMPUTED_VALUE"""),"026") -> 026 | D49: =IFERROR(__xludf.DUMMYFUNCTION("""COMPUTED_VALUE"""),"Federal Rule of Civil Procedure 54(b)") -> Federal Rule of Civil Procedure 54(b) | E49: ➔ | F49: SP-047-Federal Rule.pdf | G49: LJ
A50: 048 | B50: =IFERROR(__xludf.DUMMYFUNCTION("""COMPUTED_VALUE"""),"Infra Notes 280") -> Infra Notes 280 | C50: =IFERROR(__xludf.DUMMYFUNCTION("""COMPUTED_VALUE"""),"026") -> 026 | D50: =IFERROR(__xludf.DUMMYFUNCTION("""COMPUTED_VALUE"""),"infra notes 280, 298 and accompanying text") -> infra notes 280, 298 and accompanying text | E50: ➔ | F50: SP-048-Infra Notes 280.pdf | G50: LJ
A51: 049 | B51: =IFERROR(__xludf.DUMMYFUNCTION("""COMPUTED_VALUE"""),"Collord v US Dep't of the Interior") -> Collord v US Dep't of the Interior | C51: =IFERROR(__xludf.DUMMYFUNCTION("""COMPUTED_VALUE"""),"027") -> 027 | D51: =IFERROR(__xludf.DUMMYFUNCTION("""COMPUTED_VALUE"""),"Collord v. U.S. Dep’t of the Interior, 154 F.3d 933, 935 (9th Cir. 1998)") -> Collord v. U.S. Dep’t of the Interior, 154 F.3d 933, 935 (9th Cir. 1998) | E51: ➔ | F51: SP-049-Collord v US Dep't of the Interior.pdf | G51: LJ
A52: 050 | B52: =IFERROR(__xludf.DUMMYFUNCTION("""COMPUTED_VALUE"""),"Infra Notes 132-181") -> Infra Notes 132-181 | C52: =IFERROR(__xludf.DUMMYFUNCTION("""COMPUTED_VALUE"""),"027") -> 027 | D52: =IFERROR(__xludf.DUMMYFUNCTION("""COMPUTED_VALUE"""),"infra notes 132-181") -> infra notes 132-181 | E52: ➔ | F52: SP-050-Infra Notes 132-181.pdf | G52: LJ
A53: 051 | B53: =IFERROR(__xludf.DUMMYFUNCTION("""COMPUTED_VALUE"""),"Crowder v Sullivan") -> Crowder v Sullivan | C53: =IFERROR(__xludf.DUMMYFUNCTION("""COMPUTED_VALUE"""),"028") -> 028 | D53: =IFERROR(__xludf.DUMMYFUNCTION("""COMPUTED_VALUE"""),"Crowder v. Sullivan, 897 F.2d 252, 253 (7th Cir. 1990) (per curiam)") -> Crowder v. Sullivan, 897 F.2d 252, 253 (7th Cir. 1990) (per curiam) | E53: ➔ | F53: SP-051-Crowder v Sullivan.pdf | G53: LJ
A54: 052 | B54: =IFERROR(__xludf.DUMMYFUNCTION("""COMPUTED_VALUE"""),"Papotto") -> Papotto | C54: =IFERROR(__xludf.DUMMYFUNCTION("""COMPUTED_VALUE"""),"029") -> 029 | D54: =IFERROR(__xludf.DUMMYFUNCTION("""COMPUTED_VALUE"""),"Papotto v. Hartford Life & Accid. Insur. Co., 731 F.3d 265, 270-71 (3d Cir. 2013)") -> Papotto v. Hartford Life & Accid. Insur. Co., 731 F.3d 265, 270-71 (3d Cir. 2013) | E54: ➔ | F54: SP-052-Papotto.pdf | G54: LJ
A55: 053 | B55: =IFERROR(__xludf.DUMMYFUNCTION("""COMPUTED_VALUE"""),"Kreider") -> Kreider | C55: =IFERROR(__xludf.DUMMYFUNCTION("""COMPUTED_VALUE"""),"029") -> 029 | D55: =IFERROR(__xludf.DUMMYFUNCTION("""COMPUTED_VALUE"""),"Kreider Dairy Farms, Inc. v. Glickman, 190 F.3d 113, 124 (3d Cir. 1999) (Sloviter, J., concurring)") -> Kreider Dairy Farms, Inc. v. Glickman, 190 F.3d 113, 124 (3d Cir. 1999) (Sloviter, J., concurring) | E55: ➔ | F55: SP-053-Kreider.pdf | G55: LJ
A56: 054 | B56: =IFERROR(__xludf.DUMMYFUNCTION("""COMPUTED_VALUE"""),"Digital Equip Corp") -> Digital Equip Corp | C56: =IFERROR(__xludf.DUMMYFUNCTION("""COMPUTED_VALUE"""),"029") -> 029 | D56: =IFERROR(__xludf.DUMMYFUNCTION("""COMPUTED_VALUE"""),"Digital Equip. Corp. v. Desktop Direct, Inc., 511 U.S. 863, 867 (1994)") -> Digital Equip. Corp. v. Desktop Direct, Inc., 511 U.S. 863, 867 (1994) | E56: ➔ | F56: SP-054-Digital Equip Corp.pdf | G56: LJ
A57: 055 | B57: =IFERROR(__xludf.DUMMYFUNCTION("""COMPUTED_VALUE"""),"Bagley") -> Bagley | C57: =IFERROR(__xludf.DUMMYFUNCTION("""COMPUTED_VALUE"""),"030") -> 030 | D57: =IFERROR(__xludf.DUMMYFUNCTION("""COMPUTED_VALUE"""),"Nicholas Bagley, Remedial Restraint in Administrative Law, 117 Colum. L. Rev. 253, 258 (2017)") -> Nicholas Bagley, Remedial Restraint in Administrative Law, 117 Colum. L. Rev. 253, 258 (2017) | E57: ➔ | F57: SP-055-Bagley.pdf | G57: LJ
A58: 056 | B58: =IFERROR(__xludf.DUMMYFUNCTION("""COMPUTED_VALUE"""),706.0) -> 706 | C58: =IFERROR(__xludf.DUMMYFUNCTION("""COMPUTED_VALUE"""),"030") -> 030 | D58: =IFERROR(__xludf.DUMMYFUNCTION("""COMPUTED_VALUE"""),"5 U.S.C. § 706(2)") -> 5 U.S.C. § 706(2) | E58: ➔ | F58: SP-056-706.pdf | G58: LJ
A59: 057 | B59: =IFERROR(__xludf.DUMMYFUNCTION("""COMPUTED_VALUE"""),"Chenery Corp") -> Chenery Corp | C59: =IFERROR(__xludf.DUMMYFUNCTION("""COMPUTED_VALUE"""),"031") -> 031 | D59: =IFERROR(__xludf.DUMMYFUNCTION("""COMPUTED_VALUE"""),"Securities & Exch. Comm’n v. Chenery Corp., 332 U.S. 194, 196 (1947)") -> Securities & Exch. Comm’n v. Chenery Corp., 332 U.S. 194, 196 (1947) | E59: ➔ | F59: SP-057-Chenery Corp.pdf | G59: LJ
A60: 058 | B60: =IFERROR(__xludf.DUMMYFUNCTION("""COMPUTED_VALUE"""),"Wages and White Lion Invs") -> Wages and White Lion Invs | C60: =IFERROR(__xludf.DUMMYFUNCTION("""COMPUTED_VALUE"""),"031") -> 031 | D60: =IFERROR(__xludf.DUMMYFUNCTION("""COMPUTED_VALUE"""),"Food & Drug Admin. v. Wages & White Lion Invs., LLC, 604 U.S. 542, 588-91 (2025)") -> Food & Drug Admin. v. Wages & White Lion Invs., LLC, 604 U.S. 542, 588-91 (2025) | E60: ➔ | F60: SP-058-Wages and White Lion Invs.pdf | G60: LJ
A61: 059 | B61: =IFERROR(__xludf.DUMMYFUNCTION("""COMPUTED_VALUE"""),"Glicksman") -> Glicksman | C61: =IFERROR(__xludf.DUMMYFUNCTION("""COMPUTED_VALUE"""),"031") -> 031 | D61: =IFERROR(__xludf.DUMMYFUNCTION("""COMPUTED_VALUE"""),"Robert L. Glicksman & Emily Hammond, Agency Behavior and Discretion on Remand, 32 J. Land Use & Env’t L. 483, 492-93 (2017)") -> Robert L. Glicksman & Emily Hammond, Agency Behavior and Discretion on Remand, 32 J. Land Use & Env’t L. 483, 492-93 (2017) | E61: ➔ | F61: SP-059-Glicksman.pdf | G61: LJ
A62: 060 | B62: =IFERROR(__xludf.DUMMYFUNCTION("""COMPUTED_VALUE"""),"Walker Referral") -> Walker Referral | C62: =IFERROR(__xludf.DUMMYFUNCTION("""COMPUTED_VALUE"""),"031") -> 031 | D62: =IFERROR(__xludf.DUMMYFUNCTION("""COMPUTED_VALUE"""),"Christopher J. Walker, Referral, Remand, and Dialogue in Administrative Law, 101 Iowa L. Rev. Online 84, 86 (2016)") -> Christopher J. Walker, Referral, Remand, and Dialogue in Administrative Law, 101 Iowa L. Rev. Online 84, 86 (2016) | E62: ➔ | F62: SP-060-Walker Referral.pdf | G62: LJ
A63: 061 | B63: =IFERROR(__xludf.DUMMYFUNCTION("""COMPUTED_VALUE"""),"Walker Ordinary") -> Walker Ordinary | C63: =IFERROR(__xludf.DUMMYFUNCTION("""COMPUTED_VALUE"""),"031") -> 031 | D63: =IFERROR(__xludf.DUMMYFUNCTION("""COMPUTED_VALUE"""),"Christopher J. Walker, The Ordinary Remand Rule and the Judicial Toolbox for Agency Dialogue, 82 Geo. Wash. L. Rev. 1553, 1563 (2014)") -> Christopher J. Walker, The Ordinary Remand Rule and the Judicial Toolbox for Agency Dialogue, 82 Geo. Wash. L. Rev. 1553, 1563 (2014) | E63: ➔ | F63: SP-061-Walker Ordinary.pdf | G63: LJ
A64: 062 | B64: =IFERROR(__xludf.DUMMYFUNCTION("""COMPUTED_VALUE"""),"Infra Notes 257-261 and Accompanying Text") -> Infra Notes 257-261 and Accompanying Text | C64: =IFERROR(__xludf.DUMMYFUNCTION("""COMPUTED_VALUE"""),"032") -> 032 | D64: =IFERROR(__xludf.DUMMYFUNCTION("""COMPUTED_VALUE"""),"infra notes 257-261 and accompanying text") -> infra notes 257-261 and accompanying text | E64: ➔ | F64: SP-062-Infra Notes 257-261 and Accompanying Text.pdf | G64: LJ
A65: 063 | B65: =IFERROR(__xludf.DUMMYFUNCTION("""COMPUTED_VALUE"""),"Revesz") -> Revesz | C65: =IFERROR(__xludf.DUMMYFUNCTION("""COMPUTED_VALUE"""),"033") -> 033 | D65: =IFERROR(__xludf.DUMMYFUNCTION("""COMPUTED_VALUE"""),"Joshua Revesz, Voluntary Remands: A Critical Reassessment, 70 Admin. L. Rev. 361, 366-69 (2018)") -> Joshua Revesz, Voluntary Remands: A Critical Reassessment, 70 Admin. L. Rev. 361, 366-69 (2018) | E65: ➔ | F65: SP-063-Revesz.pdf | G65: LJ
A66: 064 | B66: =IFERROR(__xludf.DUMMYFUNCTION("""COMPUTED_VALUE"""),"Fine") -> Fine | C66: =IFERROR(__xludf.DUMMYFUNCTION("""COMPUTED_VALUE"""),"033") -> 033 | D66: =IFERROR(__xludf.DUMMYFUNCTION("""COMPUTED_VALUE"""),"Toni M. Fine, Agency Requests for “Voluntary” Remand: A Proposal for the Development of Judicial Standards, 28 Ariz. St. L.J. 1079, 1080 (1996)") -> Toni M. Fine, Agency Requests for “Voluntary” Remand: A Proposal for the Development of Judicial Standards, 28 Ariz. St. L.J. 1079, 1080 (1996) | E66: ➔ | F66: SP-064-Fine.pdf | G66: LJ
A67: 065 | B67: =IFERROR(__xludf.DUMMYFUNCTION("""COMPUTED_VALUE"""),"Motor Vehicle Mfrs") -> Motor Vehicle Mfrs | C67: =IFERROR(__xludf.DUMMYFUNCTION("""COMPUTED_VALUE"""),"034") -> 034 | D67: =IFERROR(__xludf.DUMMYFUNCTION("""COMPUTED_VALUE"""),"Motor Vehicle Mfrs. Ass’n of U.S., Inc. v. State Farm Mut. Auto. Ins. Co., 463 U.S. 29, 43 (1983)") -> Motor Vehicle Mfrs. Ass’n of U.S., Inc. v. State Farm Mut. Auto. Ins. Co., 463 U.S. 29, 43 (1983) | E67: ➔ | F67: SP-065-Motor Vehicle Mfrs.pdf | G67: LJ
A68: 066 | B68: =IFERROR(__xludf.DUMMYFUNCTION("""COMPUTED_VALUE"""),"Friendly") -> Friendly | C68: =IFERROR(__xludf.DUMMYFUNCTION("""COMPUTED_VALUE"""),"035") -> 035 | D68: =IFERROR(__xludf.DUMMYFUNCTION("""COMPUTED_VALUE"""),"Henry J. Friendly, Chenery Revisited: Reflections on Reversal and Remand of Administrative Orders, 1969 Duke L.J. 199, 205-18 (1969)") -> Henry J. Friendly, Chenery Revisited: Reflections on Reversal and Remand of Administrative Orders, 1969 Duke L.J. 199, 205-18 (1969) | E68: ➔ | F68: SP-066-Friendly.pdf | G68: LJ
A69: 067 | B69: =IFERROR(__xludf.DUMMYFUNCTION("""COMPUTED_VALUE"""),"Mendoza") -> Mendoza | C69: =IFERROR(__xludf.DUMMYFUNCTION("""COMPUTED_VALUE"""),"036") -> 036 | D69: =IFERROR(__xludf.DUMMYFUNCTION("""COMPUTED_VALUE"""),"Julie C. Mendoza & R. Will Planert, Agency Remands Before the United States Court of International Trade: Objectives and Obstacles, 17 Tul. J. Int’l & Comp. L. 463, 470-89 (2009)") -> Julie C. Mendoza & R. Will Planert, Agency Remands Before the United States Court of International Trade: Objectives and Obstacles, 17 Tul. J. Int’l & Comp. L. 463, 470-89 (2009) | E69: ➔ | F69: SP-067-Mendoza.pdf | G69: LJ
A70: 068 | B70: =IFERROR(__xludf.DUMMYFUNCTION("""COMPUTED_VALUE"""),"Pauly v US Dept of Agri") -> Pauly v US Dept of Agri | C70: =IFERROR(__xludf.DUMMYFUNCTION("""COMPUTED_VALUE"""),"037") -> 037 | D70: =IFERROR(__xludf.DUMMYFUNCTION("""COMPUTED_VALUE"""),"Pauly v. U.S. Dept. of Agri., 348 F.3d 1143, 1148 (9th Cir. 2003)") -> Pauly v. U.S. Dept. of Agri., 348 F.3d 1143, 1148 (9th Cir. 2003) | E70: ➔ | F70: SP-068-Pauly v US Dept of Agri.pdf | G70: LJ
A71: 069 | B71: =IFERROR(__xludf.DUMMYFUNCTION("""COMPUTED_VALUE"""),"Vista") -> Vista | C71: =IFERROR(__xludf.DUMMYFUNCTION("""COMPUTED_VALUE"""),"038") -> 038 | D71: =IFERROR(__xludf.DUMMYFUNCTION("""COMPUTED_VALUE"""),"Vista Health Plan, Inc. v. U.S. Dep’t of Health & Human Servs., 31 F.4th 946, 951 (5th Cir. 2022)") -> Vista Health Plan, Inc. v. U.S. Dep’t of Health & Human Servs., 31 F.4th 946, 951 (5th Cir. 2022) | E71: ➔ | F71: SP-069-Vista.pdf | G71: LJ
A72: 070 | B72: =IFERROR(__xludf.DUMMYFUNCTION("""COMPUTED_VALUE"""),"Act of Sept 24") -> Act of Sept 24 | C72: =IFERROR(__xludf.DUMMYFUNCTION("""COMPUTED_VALUE"""),"039") -> 039 | D72: =IFERROR(__xludf.DUMMYFUNCTION("""COMPUTED_VALUE"""),"Act of Sept. 24, 1789, 1 Stat. 73, c. 20 §§ 21-22") -> Act of Sept. 24, 1789, 1 Stat. 73, c. 20 §§ 21-22 | E72: ➔ | F72: SP-070-Act of Sept 24.pdf | G72: LJ
A73: 071 | B73: =IFERROR(__xludf.DUMMYFUNCTION("""COMPUTED_VALUE"""),"Federal Practice 3906") -> Federal Practice 3906 | C73: =IFERROR(__xludf.DUMMYFUNCTION("""COMPUTED_VALUE"""),"040") -> 040 | D73: =IFERROR(__xludf.DUMMYFUNCTION("""COMPUTED_VALUE"""),"Federal Practice & Procedure, § 3906 History, 15A Fed. Prac. & Proc. Juris. § 3906 (3d ed. June 2024 Update)") -> Federal Practice & Procedure, § 3906 History, 15A Fed. Prac. & Proc. Juris. § 3906 (3d ed. June 2024 Update) | E73: ➔ | F73: SP-071-Federal Practice 3906.pdf | G73: LJ
A74: 072 | B74: =IFERROR(__xludf.DUMMYFUNCTION("""COMPUTED_VALUE"""),"Metcalfe") -> Metcalfe | C74: =IFERROR(__xludf.DUMMYFUNCTION("""COMPUTED_VALUE"""),"040") -> 040 | D74: =IFERROR(__xludf.DUMMYFUNCTION("""COMPUTED_VALUE"""),"Metcalfe’s Case, 11 Co. Rep. 38a, 77 Eng. Rep. 1193 (K.B. 1615)") -> Metcalfe’s Case, 11 Co. Rep. 38a, 77 Eng. Rep. 1193 (K.B. 1615) | E74: ➔ | F74: SP-072-Metcalfe.pdf | G74: LJ
A75: 073 | B75: =IFERROR(__xludf.DUMMYFUNCTION("""COMPUTED_VALUE"""),"Catlin v United States") -> Catlin v United States | C75: =IFERROR(__xludf.DUMMYFUNCTION("""COMPUTED_VALUE"""),"041") -> 041 | D75: =IFERROR(__xludf.DUMMYFUNCTION("""COMPUTED_VALUE"""),"Catlin v. United States, 324 U.S. 229, 233 (1945)") -> Catlin v. United States, 324 U.S. 229, 233 (1945) | E75: ➔ | F75: SP-073-Catlin v United States.pdf | G75: LJ
A76: 074 | B76: =IFERROR(__xludf.DUMMYFUNCTION("""COMPUTED_VALUE"""),"62 Stat") -> 62 Stat | C76: =IFERROR(__xludf.DUMMYFUNCTION("""COMPUTED_VALUE"""),"042") -> 042 | D76: =IFERROR(__xludf.DUMMYFUNCTION("""COMPUTED_VALUE"""),"62 Stat. 929 (1948)") -> 62 Stat. 929 (1948) | E76: ➔ | F76: SP-074-62 Stat.pdf | G76: LJ
A77: 075 | B77: =IFERROR(__xludf.DUMMYFUNCTION("""COMPUTED_VALUE"""),"Bachowski v Usery") -> Bachowski v Usery | C77: =IFERROR(__xludf.DUMMYFUNCTION("""COMPUTED_VALUE"""),"043") -> 043 | D77: =IFERROR(__xludf.DUMMYFUNCTION("""COMPUTED_VALUE"""),"Bachowski v. Usery, 545 F.2d 363, 367 (3d Cir. 1976)") -> Bachowski v. Usery, 545 F.2d 363, 367 (3d Cir. 1976) | E77: ➔ | F77: SP-075-Bachowski v Usery.pdf | G77: LJ
A78: 076 | B78: =IFERROR(__xludf.DUMMYFUNCTION("""COMPUTED_VALUE"""),"Katz v Carte Blanche Corp") -> Katz v Carte Blanche Corp | C78: =IFERROR(__xludf.DUMMYFUNCTION("""COMPUTED_VALUE"""),"043") -> 043 | D78: =IFERROR(__xludf.DUMMYFUNCTION("""COMPUTED_VALUE"""),"Katz v. Carte Blanche Corp., 496 F.2d 747, 753 (3d Cir. 1974)") -> Katz v. Carte Blanche Corp., 496 F.2d 747, 753 (3d Cir. 1974) | E78: ➔ | F78: SP-076-Katz v Carte Blanche Corp.pdf | G78: LJ
A79: 077 | B79: =IFERROR(__xludf.DUMMYFUNCTION("""COMPUTED_VALUE"""),"P. Law 79") -> P. Law 79 | C79: =IFERROR(__xludf.DUMMYFUNCTION("""COMPUTED_VALUE"""),"045") -> 045 | D79: =IFERROR(__xludf.DUMMYFUNCTION("""COMPUTED_VALUE"""),"P. Law 79-404, 60 Stat. 237 (1946)") -> P. Law 79-404, 60 Stat. 237 (1946) | E79: ➔ | F79: SP-077-P. Law 79.pdf | G79: LJ
A80: 078 | B80: =IFERROR(__xludf.DUMMYFUNCTION("""COMPUTED_VALUE"""),"Cobbledick") -> Cobbledick | C80: =IFERROR(__xludf.DUMMYFUNCTION("""COMPUTED_VALUE"""),"046") -> 046 | D80: =IFERROR(__xludf.DUMMYFUNCTION("""COMPUTED_VALUE"""),"Cobbledick v. United States, 309 U.S. 323, 326 (1940)") -> Cobbledick v. United States, 309 U.S. 323, 326 (1940) | E80: ➔ | F80: SP-078-Cobbledick.pdf | G80: LJ
A81: 079 | B81: =IFERROR(__xludf.DUMMYFUNCTION("""COMPUTED_VALUE"""),"Federal Practice 3907") -> Federal Practice 3907 | C81: =IFERROR(__xludf.DUMMYFUNCTION("""COMPUTED_VALUE"""),"046") -> 046 | D81: =IFERROR(__xludf.DUMMYFUNCTION("""COMPUTED_VALUE"""),"§ 3907 Purposes, 15A Fed. Prac. & Proc. Juris. § 3907 (3d ed.)") -> § 3907 Purposes, 15A Fed. Prac. & Proc. Juris. § 3907 (3d ed.) | E81: ➔ | F81: SP-079-Federal Practice 3907.pdf | G81: LJ
A82: 080 | B82: =IFERROR(__xludf.DUMMYFUNCTION("""COMPUTED_VALUE"""),"Microsoft Corp v Baker") -> Microsoft Corp v Baker | C82: =IFERROR(__xludf.DUMMYFUNCTION("""COMPUTED_VALUE"""),"047") -> 047 | D82: =IFERROR(__xludf.DUMMYFUNCTION("""COMPUTED_VALUE"""),"Microsoft Corp. v. Baker, 582 U.S. 23, 27-29 (2017)") -> Microsoft Corp. v. Baker, 582 U.S. 23, 27-29 (2017) | E82: ➔ | F82: SP-080-Microsoft Corp v Baker.pdf | G82: LJ
A83: 081 | B83: =IFERROR(__xludf.DUMMYFUNCTION("""COMPUTED_VALUE"""),"Mohawk") -> Mohawk | C83: =IFERROR(__xludf.DUMMYFUNCTION("""COMPUTED_VALUE"""),"047") -> 047 | D83: =IFERROR(__xludf.DUMMYFUNCTION("""COMPUTED_VALUE"""),"Mohawk Indus., Inc. v. Carpenter, 558 U.S. 100, 106-07 (2009)") -> Mohawk Indus., Inc. v. Carpenter, 558 U.S. 100, 106-07 (2009) | E83: ➔ | F83: SP-081-Mohawk.pdf | G83: JL
A84: 082 | B84: =IFERROR(__xludf.DUMMYFUNCTION("""COMPUTED_VALUE"""),"Johnson v Jones") -> Johnson v Jones | C84: =IFERROR(__xludf.DUMMYFUNCTION("""COMPUTED_VALUE"""),"047") -> 047 | D84: =IFERROR(__xludf.DUMMYFUNCTION("""COMPUTED_VALUE"""),"Johnson v. Jones, 515 U.S. 304, 309 (1995)") -> Johnson v. Jones, 515 U.S. 304, 309 (1995) | E84: ➔ | F84: SP-082-Johnson v Jones.pdf | G84: JL
A85: 083 | B85: =IFERROR(__xludf.DUMMYFUNCTION("""COMPUTED_VALUE"""),"Di Bella v United States") -> Di Bella v United States | C85: =IFERROR(__xludf.DUMMYFUNCTION("""COMPUTED_VALUE"""),"047") -> 047 | D85: =IFERROR(__xludf.DUMMYFUNCTION("""COMPUTED_VALUE"""),"Di Bella v. United States, 369 U.S. 121, 124-26 (1962)") -> Di Bella v. United States, 369 U.S. 121, 124-26 (1962) | E85: ➔ | F85: SP-083-Di Bella v United States.pdf | G85: JL
A86: 084 | B86: =IFERROR(__xludf.DUMMYFUNCTION("""COMPUTED_VALUE"""),"Lammon Disarming") -> Lammon Disarming | C86: =IFERROR(__xludf.DUMMYFUNCTION("""COMPUTED_VALUE"""),"047") -> 047 | D86: =IFERROR(__xludf.DUMMYFUNCTION("""COMPUTED_VALUE"""),"Bryan Lammon, Disarming the Finality Trap, 97 NYU L. Rev. Online 173, 178 (2022)") -> Bryan Lammon, Disarming the Finality Trap, 97 NYU L. Rev. Online 173, 178 (2022) | E86: ➔ | F86: SP-084-Lammon Disarming.pdf | G86: JL
A87: 085 | B87: =IFERROR(__xludf.DUMMYFUNCTION("""COMPUTED_VALUE"""),"Frank") -> Frank | C87: =IFERROR(__xludf.DUMMYFUNCTION("""COMPUTED_VALUE"""),"047") -> 047 | D87: =IFERROR(__xludf.DUMMYFUNCTION("""COMPUTED_VALUE"""),"Theodore D. Frank, Requiem for the Final Judgment Rule, 45 Tex. L. Rev. 292, 294-98 (1966)") -> Theodore D. Frank, Requiem for the Final Judgment Rule, 45 Tex. L. Rev. 292, 294-98 (1966) | E87: ➔ | F87: SP-085-Frank.pdf | G87: JL
A88: 086 | B88: =IFERROR(__xludf.DUMMYFUNCTION("""COMPUTED_VALUE"""),"Infra Notes 53-97 and Accompanying Text") -> Infra Notes 53-97 and Accompanying Text | C88: =IFERROR(__xludf.DUMMYFUNCTION("""COMPUTED_VALUE"""),"047") -> 047 | D88: =IFERROR(__xludf.DUMMYFUNCTION("""COMPUTED_VALUE"""),"infra notes 53-97 and accompanying text") -> infra notes 53-97 and accompanying text | E88: ➔ | F88: SP-086-Infra Notes 53-97 and Accompanying Text.pdf | G88: JL
A89: 087 | B89: =IFERROR(__xludf.DUMMYFUNCTION("""COMPUTED_VALUE"""),"Firestone Tire and Rubber Co v Risjord") -> Firestone Tire and Rubber Co v Risjord | C89: =IFERROR(__xludf.DUMMYFUNCTION("""COMPUTED_VALUE"""),"049") -> 049 | D89: =IFERROR(__xludf.DUMMYFUNCTION("""COMPUTED_VALUE"""),"Firestone Tire & Rubber Co. v. Risjord, 449 U.S. 368, 374 (1981)") -> Firestone Tire & Rubber Co. v. Risjord, 449 U.S. 368, 374 (1981) | E89: ➔ | F89: SP-087-Firestone Tire and Rubber Co v Risjord.pdf | G89: JL
A90: 088 | B90: =IFERROR(__xludf.DUMMYFUNCTION("""COMPUTED_VALUE"""),"Richardson-Merrell Inc v Koller") -> Richardson-Merrell Inc v Koller | C90: =IFERROR(__xludf.DUMMYFUNCTION("""COMPUTED_VALUE"""),"049") -> 049 | D90: =IFERROR(__xludf.DUMMYFUNCTION("""COMPUTED_VALUE"""),"Richardson-Merrell Inc. v. Koller, 472 U.S. 424, 436 (1985)") -> Richardson-Merrell Inc. v. Koller, 472 U.S. 424, 436 (1985) | E90: ➔ | F90: SP-088-Richardson-Merrell Inc v Koller.pdf | G90: JL
A91: 089 | B91: =IFERROR(__xludf.DUMMYFUNCTION("""COMPUTED_VALUE"""),"Cochran") -> Cochran | C91: =IFERROR(__xludf.DUMMYFUNCTION("""COMPUTED_VALUE"""),"050") -> 050 | D91: =IFERROR(__xludf.DUMMYFUNCTION("""COMPUTED_VALUE"""),"Rebecca A. Cochran, Gaining Appellate Review by “Manufacturing” A Final Judgment Through Voluntary Dismissal of Peripheral Claims, 48 Mercer L. Rev. 979, 979-80 (1997)") -> Rebecca A. Cochran, Gaining Appellate Review by “Manufacturing” A Final Judgment Through Voluntary Dismissal of Peripheral Claims, 48 Mercer L. Rev. 979, 979-80 (1997) | E91: ➔ | F91: SP-089-Cochran.pdf | G91: JL
A92: 090 | B92: =IFERROR(__xludf.DUMMYFUNCTION("""COMPUTED_VALUE"""),"Infra Part IC") -> Infra Part IC | C92: =IFERROR(__xludf.DUMMYFUNCTION("""COMPUTED_VALUE"""),"050") -> 050 | D92: =IFERROR(__xludf.DUMMYFUNCTION("""COMPUTED_VALUE"""),"Part I.C, infra") -> Part I.C, infra | E92: ➔ | F92: SP-090-Infra Part IC.pdf | G92: JL
A93: 091 | B93: =IFERROR(__xludf.DUMMYFUNCTION("""COMPUTED_VALUE"""),"Heppner") -> Heppner | C93: =IFERROR(__xludf.DUMMYFUNCTION("""COMPUTED_VALUE"""),"051") -> 051 | D93: =IFERROR(__xludf.DUMMYFUNCTION("""COMPUTED_VALUE"""),"Richard L. Heppner, Jr., Conceptualizing Appealability: Resisting the Supreme Court’s Categorical Imperative, 55 Tulsa L. Rev. 395, 398 (2020)") -> Richard L. Heppner, Jr., Conceptualizing Appealability: Resisting the Supreme Court’s Categorical Imperative, 55 Tulsa L. Rev. 395, 398 (2020) | E93: ➔ | F93: SP-091-Heppner.pdf | G93: JL
A94: 092 | B94: =IFERROR(__xludf.DUMMYFUNCTION("""COMPUTED_VALUE"""),"Federal Practice 3909") -> Federal Practice 3909 | C94: =IFERROR(__xludf.DUMMYFUNCTION("""COMPUTED_VALUE"""),"053") -> 053 | D94: =IFERROR(__xludf.DUMMYFUNCTION("""COMPUTED_VALUE"""),"Federal Practice & Procedure, § 3909 Leading Finality Decisions, 15A Fed. Prac. & Proc. Juris. § 3909 (3d ed. June 2024 Update)") -> Federal Practice & Procedure, § 3909 Leading Finality Decisions, 15A Fed. Prac. & Proc. Juris. § 3909 (3d ed. June 2024 Update) | E94: ➔ | F94: SP-092-Federal Practice 3909.pdf | G94: JL
A95: 093 | B95: =IFERROR(__xludf.DUMMYFUNCTION("""COMPUTED_VALUE"""),"28 USC 225") -> 28 USC 225 | C95: =IFERROR(__xludf.DUMMYFUNCTION("""COMPUTED_VALUE"""),"055") -> 055 | D95: =IFERROR(__xludf.DUMMYFUNCTION("""COMPUTED_VALUE"""),"28 U.S.C. § 225") -> 28 U.S.C. § 225 | E95: ➔ | F95: SP-093-28 USC 225.pdf | G95: JL
A96: 094 | B96: =IFERROR(__xludf.DUMMYFUNCTION("""COMPUTED_VALUE"""),"Cohen") -> Cohen | C96: =IFERROR(__xludf.DUMMYFUNCTION("""COMPUTED_VALUE"""),"063") -> 063 | D96: =IFERROR(__xludf.DUMMYFUNCTION("""COMPUTED_VALUE"""),"337 U.S. 541 (1949)") -> 337 U.S. 541 (1949) | E96: ➔ | F96: SP-094-Cohen.pdf | G96: JL
A97: 095 | B97: =IFERROR(__xludf.DUMMYFUNCTION("""COMPUTED_VALUE"""),"Baker") -> Baker | C97: =IFERROR(__xludf.DUMMYFUNCTION("""COMPUTED_VALUE"""),"064") -> 064 | D97: =IFERROR(__xludf.DUMMYFUNCTION("""COMPUTED_VALUE"""),"Thomas E. Baker, Fed. Judicial Ctr., A Primer on the Jurisdiction of the U.S. Courts of Appeals, 85-90 (2d ed. 2009), https://www.fjc.gov/sites/default/files/materials/06/PrimerBakerFinal0802.pdf") -> Thomas E. Baker, Fed. Judicial Ctr., A Primer on the Jurisdiction of the U.S. Courts of Appeals, 85-90 (2d ed. 2009), https://www.fjc.gov/sites/default/files/materials/06/PrimerBakerFinal0802.pdf | E97: ➔ | F97: SP-095-Baker.pdf | G97: JL
A98: 096 | B98: =IFERROR(__xludf.DUMMYFUNCTION("""COMPUTED_VALUE"""),"Pikor") -> Pikor | C98: =IFERROR(__xludf.DUMMYFUNCTION("""COMPUTED_VALUE"""),"067") -> 067 | D98: =IFERROR(__xludf.DUMMYFUNCTION("""COMPUTED_VALUE"""),"Matthew R. Pikor, The Collateral Order Doctrine in Disorder: Redefining Finality, 92 Chi.-Kent L. Rev. 619, 622 (2017)") -> Matthew R. Pikor, The Collateral Order Doctrine in Disorder: Redefining Finality, 92 Chi.-Kent L. Rev. 619, 622 (2017) | E98: ➔ | F98: SP-096-Pikor.pdf | G98: JL
A99: 097 | B99: =IFERROR(__xludf.DUMMYFUNCTION("""COMPUTED_VALUE"""),"Van Cauwenberghe v Biard") -> Van Cauwenberghe v Biard | C99: =IFERROR(__xludf.DUMMYFUNCTION("""COMPUTED_VALUE"""),"068") -> 068 | D99: =IFERROR(__xludf.DUMMYFUNCTION("""COMPUTED_VALUE"""),"Van Cauwenberghe v. Biard, 486 U.S. 517, 522 (1988)") -> Van Cauwenberghe v. Biard, 486 U.S. 517, 522 (1988) | E99: ➔ | F99: SP-097-Van Cauwenberghe v Biard.pdf | G99: JL
A100: 098 | B100: =IFERROR(__xludf.DUMMYFUNCTION("""COMPUTED_VALUE"""),"Infra Notes 98-194 and Accompanying Text") -> Infra Notes 98-194 and Accompanying Text | C100: =IFERROR(__xludf.DUMMYFUNCTION("""COMPUTED_VALUE"""),"069") -> 069 | D100: =IFERROR(__xludf.DUMMYFUNCTION("""COMPUTED_VALUE"""),"infra notes 98-194 and accompanying text") -> infra notes 98-194 and accompanying text | E100: ➔ | F100: SP-098-Infra Notes 98-194 and Accompanying Text.pdf | G100: JL
...

Sheet CC
A1: Source | F1: Drive | I1: Round 1 | Q1: Round 2
A2: Short Name | B2: ID | C2: SP String (DNE) | D2: R1 String (DNE) | E2: R2 String (DNE) | F2: SP | G2: R1 | H2: R2 | I2: MEM | J2: Fn# | K2: Cite# | L2: Supports? | M2: Citation Elements | N2: MEM Comments | O2: SE Response | P2: Kickback Response | Q2: MEM | R2: Fn# | S2: Cite# | T2: Supports? | U2: Citation Elements | V2: MEM Comments | W2: SE Response | X2: Kickback Response
A3: Keep this row hidden / do not edit! | B3: {=IF($A$3:$A11<>"", XLOOKUP($A$3:$A11, Sourcepull!$B$3:$B11, Sourcepull!$A$3:$A11, ""), "")} | C3: {=if($A$3:$A11<>"","SP-"&$B$3:$B11&"-"&$A$3:$A11&".pdf", "")} -> SP--Keep this row hidden / do not edit!.pdf | D3: {=if($J$3:$J11<>"","R1-"&$J$3:$J11&"-"&$K$3:$K11&"-"&$B$3:$B11&"-"&$A$3:$A11&".pdf", "")} | E3: {=if($R$3:$R11<>"","R2-"&$R$3:$R11&"-"&$S$3:$S11&"-"&$B$3:$B11&"-"&$A$3:$A11&".pdf", "")} | F3: {=if($C$3:$C11 <> "", hyperlink("https://drive.google.com/drive/search?q=parent:" & Properties!$C$8 & "%20" & char(34) & $C$3:$C11 & char(34), "➔"), "")} -> ➔ | G3: {=if($D$3:$D11 <> "", hyperlink("https://drive.google.com/drive/search?q=parent:" & Properties!$C$9 & "%20" & char(34) & $D$3:$D11 & char(34), "➔"), "")} | H3: {=if($E$3:$E11 <> "", hyperlink("https://drive.google.com/drive/search?q=parent:" & Properties!$C$10 & "%20" & char(34) & $E$3:$E11 & char(34), "➔"), "")}

Sheet Sourcepull
A1: ID | B1: Short Name | C1: Fn# | D1: Full Source Citation | F1: Sourcepull File Name (DNE) | G1: Sourcepuller | H1: Completed? | I1: All Pincites (for books) | J1: Consecutively Paginated? | K1: Subseqent History / Negative Treatment? | L1: Location of Source (Green, Crown, etc.) | M1: ILL or Recall and Date of Request (books only) | N1: Problems or Comments | O1: Sourcepull checked by SE?
B2: =IFERROR(__xludf.DUMMYFUNCTION("FILTER('Raw Output'!E:E, 'Raw Output'!$G:$G=1)"),"#REF!") -> #REF! | D2: =IFERROR(__xludf.DUMMYFUNCTION("FILTER('Raw Output'!D:D, 'Raw Output'!$G:$G=1)"),"#REF!") -> #REF! | E2: {=if($B$2:$B952 <> "", hyperlink("https://drive.google.com/drive/search?q=parent:" & Properties!$C$8 & "%20" & char(34) & $F$2:$F952 & char(34), "➔"), "")} -> #REF! | F2: {=if($B$2:$B952<>"","SP-"&$A$2:$A952 &"-"&$B$2:$B952&".pdf", "")} -> #REF!
A3: 001 | B3: Tortorich | C3: 002 | D3: Frank Tortorich, Jr., The Opening of the Carson River Route, 18 Overland Journal 1, 22 (Spring 2000) | E3: ➔ | F3: SP-001-Tortorich.pdf | G3: ME | H3: Y | I3: N/A | J3: Y | K3: None | L3: Stanford Searchworks | M3: N/A
A4: 002 | B4: Munson | C4: 002 | D4: Jeff Munson, “Emigrant Trail tour promises spectacular colors,” Tahoe Daily Tribune (Oct. 12, 2005), https://www.tahoedailytribune.com/news/emigrant-trail-tour-promises-spectacular-colors/ | E4: ➔ | F4: SP-002-Munson.pdf | G4: ME | H4: Y | I4: N/A | J4: N/A | K4: None | L4: Website | M4: N/A
A5: 003 | B5: Hope Valley Recreation | C5: 003 | D5: https://www.fs.usda.gov/Internet/FSE_DOCUMENTS/stelprdb5294291.pdf. | E5: ➔ | F5: SP-003-Hope Valley Recreation.pdf | G5: ME | H5: N | N5: The URL in the foonote leads to a 404 error. I tried finding the winter recreation map separately, just via google search, and arrived at this page: https://www.fs.usda.gov/r04/humboldt-toiyabe/recreation/hope-valley-sno-parktrailhead. Unfortunately, clicking the "Click here for a map" button on that page also yields a 404 error. I think the map may no longer exist.
A6: 004 | B6: Memorandum | C6: 004 | D6: Memorandum of Opinion and Order, Friends of Hope Valley v. U.S. Forest Serv., No. 2:00-cv-01900-DFL-KJM, 2 (E.D. Cal. Sept. 30, 2004) | E6: ➔ | F6: SP-004-Memorandum.pdf | G6: ME | H6: Y | I6: N/A | J6: N/A | K6: Yes: aff’d in part, dismissed in part, Friends of Hope Valley v. U.S. Forest Serv., 203 F. App'x 883 (9th Cir. 2006). | L6: Bloomberg (not available on Westlaw or Lexis) | M6: N/A | N6: I didn't merge the subsequent history into this sourcepull pdf, because we already have the 9th Circuit case as a separate source ID.
A7: 005 | B7: Friends of Hope Valley v US Forest Service | C7: 006 | D7: Friends of Hope Valley v. U.S. Forest Service, 203 Fed. Appx. 883 (9th Cir. 2006) (unpublished) | E7: ➔ | F7: SP-005-Friends of Hope Valley v US Forest Service.pdf | G7: ME | H7: Y | I7: N/A | J7: N/A | K7: None | L7: Westlaw | M7: N/A
A8: 006 | B8: APA | C8: 007 | D8: 5 U.S.C. §§ 551-553, 701-706 | E8: ➔ | F8: SP-006-APA.pdf | G8: ME | H8: Y | I8: N/A | J8: N/A | K8: None | L8: GPO | M8: N/A | N8: The sourcepull PDF includes §§ 551-553 and 701-706, in accordance with the author's footnote.
A9: 007 | B9: Infra Notes 113, 151-153 | C9: 007 | D9: infra notes 113, 151-153 | E9: ➔ | F9: SP-007-Infra Notes 113, 151-153.pdf | G9: ME | H9: Y | I9: N/A | J9: N/A | K9: None | L9: Internal Cross Ref | M9: N/A
A10: 008 | B10: Alsea Valley Alliance v Dep't of Commerce | C10: 008 | D10: Alsea Valley Alliance v. Dep’t of Commerce, 358 F.3d 1181, 1184 (9th Cir. 2004) | E10: ➔ | F10: SP-008-Alsea Valley Alliance v Dep't of Commerce.pdf | G10: ME | H10: Y | I10: N/A | J10: N/A | K10: None | L10: Westlaw | M10: N/A
A11: 009 | B11: Infra Part IB | C11: 009 | D11: infra Part I.B | E11: ➔ | F11: SP-009-Infra Part IB.pdf | G11: ME | H11: Y | I11: N/A | J11: N/A | K11: None | L11: Internal Cross Ref | M11: N/A
A12: 010 | B12: Infra Note 23 | C12: 009 | D12: infra note 23 | E12: ➔ | F12: SP-010-Infra Note 23.pdf | G12: ME | H12: Y | I12: N/A | J12: N/A | K12: None | L12: Internal Cross Ref | M12: N/A
A13: 011 | B13: Denver Cnty | C13: 010 | D13: C.W. by and through B.W. v. Denver Cnty. Sch. Dist. No. 1, 994 F.3d 1215, 1220 n.2 (10th Cir. 2021) | E13: ➔ | F13: SP-011-Denver Cnty.pdf | G13: ME | H13: Y | I13: N/A | J13: N/A | K13: None | L13: Westlaw | M13: N/A
A14: 012 | B14: Montana Env't Info CTR | C14: 010 | D14: Montana Env’t Info. Ctr. v. Haaland, No. 22-36002, 2023 WL 8166779, at *1 (9th Cir. Nov. 24, 2023) | E14: ➔ | F14: SP-012-Montana Env't Info CTR.pdf | G14: ME | H14: Y | I14: N/A | J14: N/A | K14: None | L14: Westlaw | M14: N/A
A15: 013 | B15: Dcor | C15: 010 | D15: DCOR, LLC v. U.S. Dep’t of the Interior, No. 3:21-CV-00120-N, 2023 WL 8628322, at *1 (N.D. Tex. Dec. 13, 2023) | E15: ➔ | F15: SP-013-Dcor.pdf | G15: ME | H15: Y | I15: N/A | J15: N/A | K15: None | L15: Westlaw | M15: N/A
A16: 014 | B16: Infra Part I | C16: 011 | D16: Part I, infra | E16: ➔ | F16: SP-014-Infra Part I.pdf | G16: ME | H16: Y | I16: N/A | J16: N/A | K16: None | L16: Internal Cross Ref | M16: N/A
A17: 015 | B17: Michaels | C17: 001 | D17: Jon D. Michaels, Constitutional Coup: Privatization’s Threat to the American Republic, 21-77 (2017) | E17: ➔ | F17: SP-015-Michaels.pdf | G17: ME | H17: Y | I17: Y (included both p.21-77 and 143-220; the latter range is cited in FN 200) | J17: N/A | K17: None | L17: Stanford Searchworks (full format-preserving ebook was available) | M17: N/A
A18: 016 | B18: Developments | C18: 011 | D18: Developments in the Law—Presidential Authority, V. Executive Appointments, 125 Harv. L. Rev. 2135, 2138 (2012) | E18: ➔ | F18: SP-016-Developments.pdf | G18: ME | H18: Y | I18: N/A | J18: Y | K18: None | L18: HeinOnline | M18: N/A
A19: 017 | B19: Ho | C19: 011 | D19: Daniel E. Ho & Erica L. Ross, Did Liberal Justices Invent the Standing Doctrine? An Empirical Study of the Evolution of Standing, 1921-2006, 62 Stan. L. Rev. 591, 647 & n.231 (2010) | E19: ➔ | F19: SP-017-Ho.pdf | G19: ME | H19: Y | I19: N/A | J19: Y | K19: None | L19: HeinOnline | M19: N/A
A20: 018 | B20: Jordan | C20: 011 | D20: William S. Jordan, III, Judges, Ideology, and Policy in the Administrative State: Lessons from A Decade of Hard Look Remands of EPA Rules, 53 Admin. L. Rev. 45, 46 (2001) | E20: ➔ | F20: SP-018-Jordan.pdf | G20: ME | H20: Y | I20: N/A | J20: Y | K20: None | L20: HeinOnline | M20: N/A
A21: 019 | B21: Finkelstein | C21: 012 | D21: Sullivan v. Finkelstein, 496 U.S. 617, 625 (1990) | E21: ➔ | F21: SP-019-Finkelstein.pdf | G21: ME | H21: Y | I21: N/A | J21: N/A | K21: None | L21: HeinOnline | M21: N/A
A22: 020 | B22: Infra Notes 89-97 and Accompanying Text Pp 17-19 | C22: 012 | D22: infra notes 89-97 and accompanying text pp. 17-19 | E22: ➔ | F22: SP-020-Infra Notes 89-97 and Accompanying Text Pp 17-19.pdf | G22: ME | H22: Y | I22: N/A | J22: N/A | K22: None | L22: Internal Cross Ref | M22: N/A | N22: I kept p.19 in the PDF because the author includes that page in the cross-reference, even though footnote 97 ends on p.18.
A23: 021 | B23: Lammon Appealability | C23: 013 | D23: Bryan Lammon, Finality, Appealability, and the Scope of Interlocutory Review, 93 Wash. L. Rev. 1809, 1834-37 (2018) | E23: ➔ | F23: SP-021-Lammon Appealability.pdf | G23: ME | H23: Y | I23: N/A | J23: Y | K23: None | L23: HeinOnline | M23: N/A
A24: 022 | B24: Lammon Dizzying | C24: 013 | D24: Bryan Lammon, Dizzying Gillespie: The Exaggerated Death of the Balancing Approach and the Inescapable Allure of Flexibility in Appellate Jurisdiction, 51 U. Rich. L. Rev. 371, 386-93 (2017) | E24: ➔ | F24: SP-022-Lammon Dizzying.pdf | G24: ME | H24: Y | I24: N/A | J24: Y | K24: None | L24: HeinOnline | M24: N/A
A25: 023 | B25: Krent | C25: 013 | D25: Harold J. Krent, Situating Structural Challenges to Agency Authority Within the Framework of the Finality Principle, 98 Ind. L.J. Supplement 1, 10 n.73 (2023) | E25: ➔ | F25: SP-023-Krent.pdf | G25: ME | H25: Y | I25: N/A | J25: Y | K25: None | L25: Indiana Law Journal Website (unavailable elsewhere) | M25: N/A | N25: This source is from the Indiana Law Journal "Supplement," which is Indaina's online law journal. No table of contents was available, so I included some additional screenshots/information in the sourcepull pdf to show consecutive pagination and provide the necessary citation information.
A26: 024 | B26: Biever | C26: 013 | D26: Jennifer L. Biever & Ana Maria Gutierrez, The Uncertain Question of Remedies Should a Challenge Prevail, 2016 NO. 5 RMMLF-INST PAPER NO. 13, 28-29 (2016) | E26: ➔ | F26: SP-024-Biever.pdf | G26: ME | H26: Y | I26: N/A | J26: No | K26: None | L26: Westlaw | M26: N/A | N26: This appears to be a paper that was presented at a conference; all of the papers presented at the conference were subsequently published in a volume that is available for purchase here: https://www.fnrel.org/publications/bookstore/challenging-and-defending-federal-natural-resource-agency-decisions. As far as I can tell, Stanford libraries do not have that volume. The paper is also available on Westlaw, which is presumably where the author found it. I pulled the Westlaw version, but I'm happy to try something else.
A27: 025 | B27: Lynch | C27: 013 | D27: Michele D. Lynch, Remands Are A Consequence of Administrative Law, So Why Are We All So Frustrated?, 23 Tul. J. Int’l & Comp. L. 383, 392 (2015) | E27: ➔ | F27: SP-025-Lynch.pdf | G27: ME | H27: Y | I27: N/A | J27: Y | K27: None | L27: HeinOnline | M27: N/A
A28: 026 | B28: Federal Practice 3914 32 | C28: 013 | D28: Federal Practice & Procedure, § 3914.32 Orders Prior to Trial—Administrative Review, 15B Fed. Prac. & Proc. Juris. § 3914.32 (2d ed. June 2024 Update) | E28: ➔ | F28: SP-026-Federal Practice 3914 32.pdf | G28: ME | H28: Y | I28: N/A | J28: N/A | K28: None | L28: Westlaw | M28: N/A | N28: Per RB 15.4, I pulled the online (Westlaw) version of this treatise, because it is regularly updated.
A29: 027 | B29: Federal Practice 3903 | C29: 013 | D29: Federal Practice & Procedure, § 3903 Pragmatic Finality, 15A Fed. Prac. & Proc. Juris. § 3913 (3d ed. June 2024 Update) | E29: ➔ | F29: SP-027-Federal Practice 3903.pdf | G29: ME | H29: Y | I29: N/A | J29: N/A | K29: None | L29: Westlaw | M29: N/A | N29: Same comment as previous row.
A30: 028 | B30: 73a CJS | C30: 013 | D30: 73A C.J.S. Pub. Admin. Law & Proc. § 561 (May 2024) | E30: ➔ | F30: SP-028-73a CJS.pdf | G30: ME | H30: Y | I30: N/A | J30: N/A | K30: None | L30: Westlaw | M30: N/A | N30: Same comment as previous row.
A31: 029 | B31: Fed Ct | C31: 013 | D31: Fed. Ct. App. Manual § 2:3 (7th ed. May 2024) | E31: ➔ | F31: SP-029-Fed Ct.pdf | G31: ME | H31: Y | I31: N/A | J31: N/A | K31: None | L31: Westlaw | M31: N/A | N31: Same comment as previous row.
A32: 030 | B32: Infra Notes 39-51 and Accompanying Text | C32: 014 | D32: infra notes 39-51 and accompanying text | E32: ➔ | F32: SP-030-Infra Notes 39-51 and Accompanying Text.pdf | G32: ME | H32: Y | I32: N/A | J32: N/A | K32: None | L32: Internal Cross Ref | M32: N/A
A33: 031 | B33: Infra Notes 46-48 and Accompanying Text | C33: 015 | D33: infra notes 46-48 and accompanying text | E33: ➔ | F33: SP-031-Infra Notes 46-48 and Accompanying Text.pdf | G33: ME | H33: Y | I33: N/A | J33: N/A | K33: None | L33: Internal Cross Ref | M33: N/A
A34: 032 | B34: Pueblo of Sandia v Babbitt | C34: 016 | D34: Pueblo of Sandia v. Babbitt, 231 F.3d 878, 880 (D.C. Cir. 2000) | E34: ➔ | F34: SP-032-Pueblo of Sandia v Babbitt.pdf | G34: ME | H34: Y | I34: N/A | J34: N/A | K34: None | L34: Westlaw | M34: N/A
A35: 033 | B35: CTR for Biological Diversity v Bureau of Land MGMT | C35: 017 | D35: Ctr. for Biological Diversity v. Bureau of Land Mgmt., 69 F.4th 588, 597-98 (9th Cir. 2023) (Friedland and Bennett, JJ., concurring) | E35: ➔ | F35: SP-033-CTR for Biological Diversity v Bureau of Land MGMT.pdf | G35: ME | H35: Y | I35: N/A | J35: N/A | K35: None | L35: Westlaw | M35: N/A
A36: 034 | B36: NY Legal Assistance GRP v Cardona | C36: 017 | D36: N.Y. Legal Assistance Grp. v. Cardona, No. 21-888-CV, 2024 WL 64220, at *3-4 (2d Cir. Jan. 5, 2024) | E36: ➔ | F36: SP-034-NY Legal Assistance GRP v Cardona.pdf | G36: ME | H36: Y | I36: N/A | J36: N/A | K36: None | L36: Westlaw | M36: N/A
A37: 035 | B37: Infra Notes 132-192 and Accompanying Text | C37: 018 | D37: infra notes 132-192 and accompanying text | E37: ➔ | F37: SP-035-Infra Notes 132-192 and Accompanying Text.pdf | G37: ME | H37: Y | I37: N/A | J37: N/A | K37: None | L37: Internal Cross Ref | M37: N/A
A38: 036 | B38: Infra Notes 193-194 | C38: 019 | D38: infra notes 193-194, 262-270 and accompanying text | E38: ➔ | F38: SP-036-Infra Notes 193-194.pdf | G38: ME | H38: Y | I38: N/A | J38: N/A | K38: None | L38: Internal Cross Ref | M38: N/A | N38: Flagging that this cross reference refers to two ranges of footnotes, which is not reflected in the source ID name.
A39: 037 | B39: Clopton | C39: 020 | D39: Zachary D. Clopton & Katherine Shaw, Public Law Litigation and Electoral Time, 2023 Wis. L. Rev. 1513, 1521–22 (2023) | E39: ➔ | F39: SP-037-Clopton.pdf | G39: ME | H39: Y | I39: N/A | J39: Y | K39: None | L39: HeinOnline | M39: N/A
A40: 038 | B40: Jackson | C40: 021 | D40: Jackson v. Bd. of Civ. Serv. Comm’rs of City of Los Angeles, 99 Cal. App. 5th 648, 655-62, 318 Cal. Rptr. 3d 79 (2024) | E40: ➔ | F40: SP-038-Jackson.pdf | G40: ME | H40: Y | I40: N/A | J40: N/A | K40: None | L40: Westlaw | M40: N/A
A41: 039 | B41: John Muir Health | C41: 021 | D41: Dhillon v. John Muir Health, 2 Cal. 5th 1109, 1116, 394 P.3d 1048 (2017) | E41: ➔ | F41: SP-039-John Muir Health.pdf | G41: ME | H41: Y | I41: N/A | J41: N/A | K41: None | L41: Westlaw | M41: N/A
A42: 040 | B42: Federman | C42: 021 | D42: Federman v. Bd. of Appeals of Marblehead, 35 Mass. App. Ct. 727, 729-30, 626 N.E. 2d 8 (Mass. 1994) | E42: ➔ | F42: SP-040-Federman.pdf | G42: ME | H42: Y | I42: N/A | J42: N/A | K42: None | L42: Westlaw | M42: N/A
A43: 041 | B43: Holton | C43: 021 | D43: Holton Transp., Inc. v. Kansas Corp. Comm’n, 10 Kan. App. 2d 12, 12-13, 690 P.2d 399 (Kan. 1984) | E43: ➔ | F43: SP-041-Holton.pdf | G43: LJ | H43: Yes | I43: N/A | J43: N/A | K43: None | L43: Westlaw | M43: N/A
A44: 042 | B44: Bearns | C44: 021 | D44: Bearns v. Dep’t of Indus., Labor & Human Relations, 76-78. 306 N.W. 2d 22 (Wis. 1981) | E44: ➔ | F44: SP-042-Bearns.pdf | G44: LJ | H44: Yes | I44: N/A | J44: N/A | K44: None | L44: Westlaw | M44: N/A
A45: 043 | B45: Am Constr Co | C45: 022 | D45: Am. Constr. Co. v. Jacksonville, Tampa & Key West Ry. Co., 148 U.S. 372, 384 (1893) | E45: ➔ | F45: SP-043-Am Constr Co.pdf | G45: LJ | H45: Yes | I45: N/A | J45: N/A | K45: None | L45: Author Provided | M45: N/A
A46: 044 | B46: Infra Notes 29 | C46: 023 | D46: infra notes 29, 94, 113 | E46: ➔ | F46: SP-044-Infra Notes 29.pdf | G46: LJ | H46: Yes | I46: N/A | J46: N/A | K46: N/A | L46: Article | M46: N/A
A47: 045 | B47: 1291 | C47: 024 | D47: 28 U.S.C. § 1291 | E47: ➔ | F47: SP-045-1291.pdf | G47: LJ | H47: Yes | I47: N/A | J47: N/A | K47: N/A | L47: GPO | M47: N/A
A48: 046 | B48: 1292 | C48: 025 | D48: 28 U.S.C. § 1292 | E48: ➔ | F48: SP-046-1292.pdf | G48: LJ | H48: Yes | I48: N/A | J48: N/A | K48: N/A | L48: GPO | M48: N/A
A49: 047 | B49: Federal Rule | C49: 026 | D49: Federal Rule of Civil Procedure 54(b) | E49: ➔ | F49: SP-047-Federal Rule.pdf | G49: LJ | H49: Yes | I49: N/A | J49: N/A | K49: N/A | L49: uscourts.gov | M49: N/A
A50: 048 | B50: Infra Notes 280 | C50: 026 | D50: infra notes 280, 298 and accompanying text | E50: ➔ | F50: SP-048-Infra Notes 280.pdf | G50: LJ | H50: Yes | I50: N/A | J50: N/A | K50: N/A | L50: Article | M50: N/A
A51: 049 | B51: Collord v US Dep't of the Interior | C51: 027 | D51: Collord v. U.S. Dep’t of the Interior, 154 F.3d 933, 935 (9th Cir. 1998) | E51: ➔ | F51: SP-049-Collord v US Dep't of the Interior.pdf | G51: LJ | H51: Yes | I51: N/A | J51: N/A | K51: None | L51: Author Provided | M51: N/A
A52: 050 | B52: Infra Notes 132-181 | C52: 027 | D52: infra notes 132-181 | E52: ➔ | F52: SP-050-Infra Notes 132-181.pdf | G52: LJ | H52: Yes | I52: N/A | J52: N/A | K52: N/A | L52: Article | M52: N/A
A53: 051 | B53: Crowder v Sullivan | C53: 028 | D53: Crowder v. Sullivan, 897 F.2d 252, 253 (7th Cir. 1990) (per curiam) | E53: ➔ | F53: SP-051-Crowder v Sullivan.pdf | G53: LJ | H53: Yes | I53: N/A | J53: N/A | K53: None | L53: Author Provided | M53: N/A
A54: 052 | B54: Papotto | C54: 029 | D54: Papotto v. Hartford Life & Accid. Insur. Co., 731 F.3d 265, 270-71 (3d Cir. 2013) | E54: ➔ | F54: SP-052-Papotto.pdf | G54: LJ | H54: Yes | I54: N/A | J54: N/A | K54: None | L54: Author Provided | M54: N/A
A55: 053 | B55: Kreider | C55: 029 | D55: Kreider Dairy Farms, Inc. v. Glickman, 190 F.3d 113, 124 (3d Cir. 1999) (Sloviter, J., concurring) | E55: ➔ | F55: SP-053-Kreider.pdf | G55: LJ | H55: Yes | I55: N/A | J55: N/A | K55: None | L55: Author Provided | M55: N/A
A56: 054 | B56: Digital Equip Corp | C56: 029 | D56: Digital Equip. Corp. v. Desktop Direct, Inc., 511 U.S. 863, 867 (1994) | E56: ➔ | F56: SP-054-Digital Equip Corp.pdf | G56: LJ | H56: Yes | I56: N/A | J56: N/A | K56: None | L56: Author Provided | M56: N/A
A57: 055 | B57: Bagley | C57: 030 | D57: Nicholas Bagley, Remedial Restraint in Administrative Law, 117 Colum. L. Rev. 253, 258 (2017) | E57: ➔ | F57: SP-055-Bagley.pdf | G57: LJ | H57: Yes | I57: N/A | J57: Yes | K57: N/A | L57: JSTOR | M57: N/A
A58: 056 | B58: 706 | C58: 030 | D58: 5 U.S.C. § 706(2) | E58: ➔ | F58: SP-056-706.pdf | G58: LJ | H58: Yes | I58: N/A | J58: N/A | K58: N/A | L58: GPO | M58: N/A
A59: 057 | B59: Chenery Corp | C59: 031 | D59: Securities & Exch. Comm’n v. Chenery Corp., 332 U.S. 194, 196 (1947) | E59: ➔ | F59: SP-057-Chenery Corp.pdf | G59: LJ | H59: Yes | I59: N/A | J59: N/A | K59: N/A | L59: Library of Congress | M59: N/A
A60: 058 | B60: Wages and White Lion Invs | C60: 031 | D60: Food & Drug Admin. v. Wages & White Lion Invs., LLC, 604 U.S. 542, 588-91 (2025) | E60: ➔ | F60: SP-058-Wages and White Lion Invs.pdf | G60: LJ | H60: Yes | I60: N/A | J60: N/A | K60: N/A | L60: Westlaw | M60: N/A | N60: Because SLR doesn't allow citing to preliminary prints, I tried to find a copy of the S. Ct. reporter (and we will have to change the pincites). Westlaw didn't have a pdf of the Supreme Court reporter, so I just directly downloaded from Westlaw. I'll check the library to see if they have it.
A61: 059 | B61: Glicksman | C61: 031 | D61: Robert L. Glicksman & Emily Hammond, Agency Behavior and Discretion on Remand, 32 J. Land Use & Env’t L. 483, 492-93 (2017) | E61: ➔ | F61: SP-059-Glicksman.pdf | G61: LJ | H61: Yes | I61: N/A | J61: N/A | K61: N/A | L61: JSTOR | M61: N/A
A62: 060 | B62: Walker Referral | C62: 031 | D62: Christopher J. Walker, Referral, Remand, and Dialogue in Administrative Law, 101 Iowa L. Rev. Online 84, 86 (2016) | E62: ➔ | F62: SP-060-Walker Referral.pdf | G62: LJ | H62: Yes | I62: N/A | J62: Yes | K62: N/A | L62: Iowa Law Review Website | M62: N/A | N62: I confirmed that the Iowa Law Review Online is consecutively paginated by clicking on a couple of volumes and seeing whether the beginning pages varied (they do), but I'm not sure what to link onto the document to prove that since there's no singular table of contents.
A63: 061 | B63: Walker Ordinary | C63: 031 | D63: Christopher J. Walker, The Ordinary Remand Rule and the Judicial Toolbox for Agency Dialogue, 82 Geo. Wash. L. Rev. 1553, 1563 (2014) | E63: ➔ | F63: SP-061-Walker Ordinary.pdf | G63: LJ | H63: Yes | I63: N/A | J63: Yes | K63: N/A | L63: George Washington Law Review Website | M63: N/A
A64: 062 | B64: Infra Notes 257-261 and Accompanying Text | C64: 032 | D64: infra notes 257-261 and accompanying text | E64: ➔ | F64: SP-062-Infra Notes 257-261 and Accompanying Text.pdf | G64: LJ | H64: Yes | I64: N/A | J64: N/A | K64: N/A | L64: Article | M64: N/A
A65: 063 | B65: Revesz | C65: 033 | D65: Joshua Revesz, Voluntary Remands: A Critical Reassessment, 70 Admin. L. Rev. 361, 366-69 (2018) | E65: ➔ | F65: SP-063-Revesz.pdf | G65: LJ | H65: Yes | I65: N/A | J65: Yes | K65: N/A | L65: JSTOR | M65: N/A | N65: The Administrative Law Review classifies the piece as an Article but the author is a student, so I'm not sure what this should be.
A66: 064 | B66: Fine | C66: 033 | D66: Toni M. Fine, Agency Requests for “Voluntary” Remand: A Proposal for the Development of Judicial Standards, 28 Ariz. St. L.J. 1079, 1080 (1996) | E66: ➔ | F66: SP-064-Fine.pdf | G66: LJ | H66: Yes | I66: N/A | J66: Yes | K66: N/A | L66: HeinOnline | M66: N/A
A67: 065 | B67: Motor Vehicle Mfrs | C67: 034 | D67: Motor Vehicle Mfrs. Ass’n of U.S., Inc. v. State Farm Mut. Auto. Ins. Co., 463 U.S. 29, 43 (1983) | E67: ➔ | F67: SP-065-Motor Vehicle Mfrs.pdf | G67: LJ | H67: Yes | I67: N/A | J67: N/A | K67: None | L67: Author Provided | M67: N/A
A68: 066 | B68: Friendly | C68: 035 | D68: Henry J. Friendly, Chenery Revisited: Reflections on Reversal and Remand of Administrative Orders, 1969 Duke L.J. 199, 205-18 (1969) | E68: ➔ | F68: SP-066-Friendly.pdf | G68: LJ | H68: Yes | I68: N/A | J68: Yes | K68: N/A | L68: JSTOR | M68: N/A
A69: 067 | B69: Mendoza | C69: 036 | D69: Julie C. Mendoza & R. Will Planert, Agency Remands Before the United States Court of International Trade: Objectives and Obstacles, 17 Tul. J. Int’l & Comp. L. 463, 470-89 (2009) | E69: ➔ | F69: SP-067-Mendoza.pdf | G69: LJ | H69: Yes | I69: N/A | J69: Yes | K69: N/A | L69: Tulane Library | M69: N/A | N69: I confirmed that the journal is consecutively paginated by clicking on a couple of volumes and seeing whether the beginning pages varied (they do), but I'm not sure what to link onto the document to prove that since there's no singular table of contents.
A70: 068 | B70: Pauly v US Dept of Agri | C70: 037 | D70: Pauly v. U.S. Dept. of Agri., 348 F.3d 1143, 1148 (9th Cir. 2003) | E70: ➔ | F70: SP-068-Pauly v US Dept of Agri.pdf | G70: LJ | H70: Yes | I70: N/A | J70: N/A | K70: None | L70: Author Provided | M70: N/A
A71: 069 | B71: Vista | C71: 038 | D71: Vista Health Plan, Inc. v. U.S. Dep’t of Health & Human Servs., 31 F.4th 946, 951 (5th Cir. 2022) | E71: ➔ | F71: SP-069-Vista.pdf | G71: LJ | H71: Yes | I71: N/A | J71: N/A | K71: None | L71: Author Provided | M71: N/A
A72: 070 | B72: Act of Sept 24 | C72: 039 | D72: Act of Sept. 24, 1789, 1 Stat. 73, c. 20 §§ 21-22 | E72: ➔ | F72: SP-070-Act of Sept 24.pdf | G72: LJ | H72: Yes | I72: N/A | J72: N/A | K72: N/A | L72: GovInfo | M72: N/A
A73: 071 | B73: Federal Practice 3906 | C73: 040 | D73: Federal Practice & Procedure, § 3906 History, 15A Fed. Prac. & Proc. Juris. § 3906 (3d ed. June 2024 Update) | E73: ➔ | F73: SP-071-Federal Practice 3906.pdf | G73: LJ | H73: Yes | I73: N/A | J73: N/A | K73: N/A | L73: Westlaw | M73: N/A | N73: Tried to find in the library but they only had the supplement and not the original.
A74: 072 | B74: Metcalfe | C74: 040 | D74: Metcalfe’s Case, 11 Co. Rep. 38a, 77 Eng. Rep. 1193 (K.B. 1615) | E74: ➔ | F74: SP-072-Metcalfe.pdf | G74: LJ | H74: Yes | I74: N/A | J74: N/A | K74: N/A | L74: HathiTrust | M74: N/A | N74: This is a reprint of the Eng. Rep. report. I have a copy of the Co. Rep. in case this doesn't count as format preserving but it's from 1800 and really horrible to look at.
A75: 073 | B75: Catlin v United States | C75: 041 | D75: Catlin v. United States, 324 U.S. 229, 233 (1945) | E75: ➔ | F75: SP-073-Catlin v United States.pdf | G75: LJ | H75: Yes | I75: N/A | J75: N/A | K75: N/A | L75: Author Provided | M75: N/A
A76: 074 | B76: 62 Stat | C76: 042 | D76: 28 U.S.C. §§ 1291-1292, 62 Stat. 929 (1948). | E76: ➔ | F76: SP-074-62 Stat.pdf | G76: LJ | H76: Yes | I76: N/A | J76: N/A | K76: N/A | L76: GPO | M76: N/A | N76: Original full cite truncated what was in the article. Updated that cell to have the actual full cite.
A77: 075 | B77: Bachowski v Usery | C77: 043 | D77: Bachowski v. Usery, 545 F.2d 363, 367 (3d Cir. 1976) | E77: ➔ | F77: SP-075-Bachowski v Usery.pdf | G77: LJ | H77: Yes | I77: N/A | J77: N/A | K77: None | L77: Westlaw | M77: N/A
A78: 076 | B78: Katz v Carte Blanche Corp | C78: 043 | D78: Katz v. Carte Blanche Corp., 496 F.2d 747, 753 (3d Cir. 1974) | E78: ➔ | F78: SP-076-Katz v Carte Blanche Corp.pdf | G78: LJ | H78: Yes | I78: N/A | J78: N/A | K78: None | L78: Author Provided | M78: N/A
A79: 077 | B79: P. Law 79 | C79: 045 | D79: P. Law 79-404, 60 Stat. 237 (1946) | E79: ➔ | F79: SP-077-P. Law 79.pdf | G79: LJ | H79: Yes | I79: N/A | J79: N/A | K79: N/A | L79: GPO | M79: N/A
A80: 078 | B80: Cobbledick | C80: 046 | D80: Cobbledick v. United States, 309 U.S. 323, 326 (1940) | E80: ➔ | F80: SP-078-Cobbledick.pdf | G80: LJ | H80: Yes | I80: N/A | J80: N/A | K80: None | L80: Author Provided | M80: N/A
A81: 079 | B81: Federal Practice 3907 | C81: 046 | D81: § 3907 Purposes, 15A Fed. Prac. & Proc. Juris. § 3907 (3d ed.) | E81: ➔ | F81: SP-079-Federal Practice 3907.pdf | G81: LJ | H81: Yes | I81: N/A | J81: N/A | K81: N/A | L81: Westlaw | M81: N/A | N81: Tried to find in the library but they only had the supplement and not the original.
A82: 080 | B82: Microsoft Corp v Baker | C82: 047 | D82: Microsoft Corp. v. Baker, 582 U.S. 23, 27-29 (2017) | E82: ➔ | F82: SP-080-Microsoft Corp v Baker.pdf | G82: LJ | H82: Yes | I82: N/A | J82: N/A | K82: None | L82: Author Provided | M82: N/A
A83: 081 | B83: Mohawk | C83: 047 | D83: Mohawk Indus., Inc. v. Carpenter, 558 U.S. 100, 106-07 (2009) | E83: ➔ | F83: SP-081-Mohawk.pdf | G83: JL | H83: Yes | I83: N/A | J83: N/A | K83: N/A | L83: Westlaw | M83: N/A | N83: Seems like there are two different reporter versions, with S.Ct being the default. I can only seem to find the page numbers for the US reporter starting from pg. 103, rather than pg. 100.
A84: 082 | B84: Johnson v Jones | C84: 047 | D84: Johnson v. Jones, 515 U.S. 304, 309 (1995) | E84: ➔ | F84: SP-082-Johnson v Jones.pdf | G84: JL | H84: Yes | I84: N/A | J84: N/A | K84: There seems to be an "implied overruing" by a 5th Circ court, but that overruling was then vacated – do we still need to include this? | L84: Westlaw | M84: N/A
A85: 083 | B85: Di Bella v United States | C85: 047 | D85: Di Bella v. United States, 369 U.S. 121, 124-26 (1962) | E85: ➔ | F85: SP-083-Di Bella v United States.pdf | G85: JL | H85: Yes | I85: N/A | J85: N/A | K85: N/A | L85: Westlaw | M85: N/A
A86: 084 | B86: Lammon Disarming | C86: 047 | D86: Bryan Lammon, Disarming the Finality Trap, 97 NYU L. Rev. Online 173, 178 (2022) | E86: ➔ | F86: SP-084-Lammon Disarming.pdf | G86: JL
A87: 085 | B87: Frank | C87: 047 | D87: Theodore D. Frank, Requiem for the Final Judgment Rule, 45 Tex. L. Rev. 292, 294-98 (1966) | E87: ➔ | F87: SP-085-Frank.pdf | G87: JL
A88: 086 | B88: Infra Notes 53-97 and Accompanying Text | C88: 047 | D88: infra notes 53-97 and accompanying text | E88: ➔ | F88: SP-086-Infra Notes 53-97 and Accompanying Text.pdf | G88: JL
A89: 087 | B89: Firestone Tire and Rubber Co v Risjord | C89: 049 | D89: Firestone Tire & Rubber Co. v. Risjord, 449 U.S. 368, 374 (1981) | E89: ➔ | F89: SP-087-Firestone Tire and Rubber Co v Risjord.pdf | G89: JL | H89: Yes | I89: N/A | J89: N/A | K89: N/A | L89: Westlaw | M89: N/A
A90: 088 | B90: Richardson-Merrell Inc v Koller | C90: 049 | D90: Richardson-Merrell Inc. v. Koller, 472 U.S. 424, 436 (1985) | E90: ➔ | F90: SP-088-Richardson-Merrell Inc v Koller.pdf | G90: JL | H90: Yes | I90: N/A | J90: N/A | K90: Does "criticized in" count? | L90: Westlaw | M90: N/A
A91: 089 | B91: Cochran | C91: 050 | D91: Rebecca A. Cochran, Gaining Appellate Review by “Manufacturing” A Final Judgment Through Voluntary Dismissal of Peripheral Claims, 48 Mercer L. Rev. 979, 979-80 (1997) | E91: ➔ | F91: SP-089-Cochran.pdf | G91: JL
A92: 090 | B92: Infra Part IC | C92: 050 | D92: Part I.C, infra | E92: ➔ | F92: SP-090-Infra Part IC.pdf | G92: JL
A93: 091 | B93: Heppner | C93: 051 | D93: Richard L. Heppner, Jr., Conceptualizing Appealability: Resisting the Supreme Court’s Categorical Imperative, 55 Tulsa L. Rev. 395, 398 (2020) | E93: ➔ | F93: SP-091-Heppner.pdf | G93: JL
A94: 092 | B94: Federal Practice 3909 | C94: 053 | D94: Federal Practice & Procedure, § 3909 Leading Finality Decisions, 15A Fed. Prac. & Proc. Juris. § 3909 (3d ed. June 2024 Update) | E94: ➔ | F94: SP-092-Federal Practice 3909.pdf | G94: JL
A95: 093 | B95: 28 USC 225 | C95: 055 | D95: 28 U.S.C. § 225 | E95: ➔ | F95: SP-093-28 USC 225.pdf | G95: JL
A96: 094 | B96: Cohen | C96: 063 | D96: 337 U.S. 541 (1949) | E96: ➔ | F96: SP-094-Cohen.pdf | G96: JL
A97: 095 | B97: Baker | C97: 064 | D97: Thomas E. Baker, Fed. Judicial Ctr., A Primer on the Jurisdiction of the U.S. Courts of Appeals, 85-90 (2d ed. 2009), https://www.fjc.gov/sites/default/files/materials/06/PrimerBakerFinal0802.pdf | E97: ➔ | F97: SP-095-Baker.pdf | G97: JL
A98: 096 | B98: Pikor | C98: 067 | D98: Matthew R. Pikor, The Collateral Order Doctrine in Disorder: Redefining Finality, 92 Chi.-Kent L. Rev. 619, 622 (2017) | E98: ➔ | F98: SP-096-Pikor.pdf | G98: JL
A99: 097 | B99: Van Cauwenberghe v Biard | C99: 068 | D99: Van Cauwenberghe v. Biard, 486 U.S. 517, 522 (1988) | E99: ➔ | F99: SP-097-Van Cauwenberghe v Biard.pdf | G99: JL | H99: Yes | I99: N/A | J99: N/A | K99: N/A | L99: Westlaw | M99: N/A
A100: 098 | B100: Infra Notes 98-194 and Accompanying Text | C100: 069 | D100: infra notes 98-194 and accompanying text | E100: ➔ | F100: SP-098-Infra Notes 98-194 and Accompanying Text.pdf | G100: JL
...

Sheet CC (nn. 1-37); LJ
A1: Source | F1: Drive | I1: Round 1 | Q1: Round 2
A2: Short Name | B2: ID | C2: SP String (DNE) | D2: R1 String (DNE) | E2: R2 String (DNE) | F2: SP | G2: R1 | H2: R2 | I2: MEM | J2: Fn# | K2: Cite# | L2: Supports? | M2: Citation Elements | N2: MEM Comments | O2: SE Response | P2: Kickback Response | Q2: MEM | R2: Fn# | S2: Cite# | T2: Supports? | U2: Citation Elements | V2: MEM Comments | W2: SE Response | X2: Kickback Response
A3: Keep this row hidden / do not edit! | B3: {=IF($A$3:$A88<>"", XLOOKUP($A$3:$A88, Sourcepull!$B$3:$B88, Sourcepull!$A$3:$A88, ""), "")} | C3: {=if($A$3:$A88<>"","SP-"&$B$3:$B88&"-"&$A$3:$A88&".pdf", "")} -> SP--Keep this row hidden / do not edit!.pdf | D3: {=if($J$3:$J88<>"","R1-"&$J$3:$J88&"-"&$K$3:$K88&"-"&$B$3:$B88&"-"&$A$3:$A88&".pdf", "")} | E3: {=if($R$3:$R88<>"","R2-"&$R$3:$R88&"-"&$S$3:$S88&"-"&$B$3:$B88&"-"&$A$3:$A88&".pdf", "")} | F3: {=if($C$3:$C88 <> "", hyperlink("https://drive.google.com/drive/search?q=parent:" & Properties!$C$8 & "%20" & char(34) & $C$3:$C88 & char(34), "➔"), "")} -> ➔ | G3: {=if($D$3:$D88 <> "", hyperlink("https://drive.google.com/drive/search?q=parent:" & Properties!$C$9 & "%20" & char(34) & $D$3:$D88 & char(34), "➔"), "")} | H3: {=if($E$3:$E88 <> "", hyperlink("https://drive.google.com/drive/search?q=parent:" & Properties!$C$10 & "%20" & char(34) & $E$3:$E88 & char(34), "➔"), "")}
A4: Herman | B4: 328 | C4: SP-328-Herman.pdf | D4: R1-001-01-328-Herman.pdf | F4: ➔ | G4: ➔ | I4: LJ | J4: 001 | K4: 01
A5: Cudahy | B5: 329 | C5: SP-329-Cudahy.pdf | D5: R1-001-02-329-Cudahy.pdf | F5: ➔ | G5: ➔ | I5: LJ | J5: 001 | K5: 02
A6: Carson | B6: 330 | C6: SP-330-Carson.pdf | D6: R1-001-03-330-Carson.pdf | F6: ➔ | G6: ➔ | I6: LJ | J6: 001 | K6: 03
A7: Washoe USDA | B7: 331 | C7: SP-331-Washoe USDA.pdf | D7: R1-001-04-331-Washoe USDA.pdf | F7: ➔ | G7: ➔ | I7: LJ | J7: 001 | K7: 04
A8: Washoe History | B8: 332 | C8: SP-332-Washoe History.pdf | D8: R1-001-05-332-Washoe History.pdf | F8: ➔ | G8: ➔ | I8: LJ | J8: 001 | K8: 05
A9: Tortorich | B9: 001 | C9: SP-001-Tortorich.pdf | D9: R1-002-01-001-Tortorich.pdf | F9: ➔ | G9: ➔ | I9: LJ | J9: 002 | K9: 01
A10: Munson | B10: 002 | C10: SP-002-Munson.pdf | D10: R1-002-02-002-Munson.pdf | F10: ➔ | G10: ➔ | I10: LJ | J10: 002 | K10: 02
A11: Hope Valley Recreation | B11: 003 | C11: SP-003-Hope Valley Recreation.pdf | D11: R1-003-01-003-Hope Valley Recreation.pdf | F11: ➔ | G11: ➔ | I11: LJ | J11: 003 | K11: 01
A12: Memorandum | B12: 004 | C12: SP-004-Memorandum.pdf | D12: R1-004-01-004-Memorandum.pdf | F12: ➔ | G12: ➔ | I12: LJ | J12: 004 | K12: 01
A13: Memorandum | B13: 004 | C13: SP-004-Memorandum.pdf | D13: R1-005-01-004-Memorandum.pdf | F13: ➔ | G13: ➔ | I13: LJ | J13: 005 | K13: 01
A14: Friends of Hope Valley v US Forest Service | B14: 005 | C14: SP-005-Friends of Hope Valley v US Forest Service.pdf | D14: R1-006-01-005-Friends of Hope Valley v US Forest Service.pdf | F14: ➔ | G14: ➔ | I14: LJ | J14: 006 | K14: 01
A15: Friends of Hope Valley v US Forest Service | B15: 005 | C15: SP-005-Friends of Hope Valley v US Forest Service.pdf | D15: R1-007-01-005-Friends of Hope Valley v US Forest Service.pdf | F15: ➔ | G15: ➔ | I15: LJ | J15: 007 | K15: 01
... A56: Infra Notes 29 | B56: 044 | C56: SP-044-Infra Notes 29.pdf | D56: R1-023-01-044-Infra Notes 29.pdf | F56: ➔ | G56: ➔ | I56: LJ | J56: 023 | K56: 01
A57: 1291 | B57: 045 | C57: SP-045-1291.pdf | D57: R1-024-01-045-1291.pdf | F57: ➔ | G57: ➔ | I57: LJ | J57: 024 | K57: 01
A58: 1292 | B58: 046 | C58: SP-046-1292.pdf | D58: R1-025-01-046-1292.pdf | F58: ➔ | G58: ➔ | I58: LJ | J58: 025 | K58: 01
A59: Federal Rule | B59: 047 | C59: SP-047-Federal Rule.pdf | D59: R1-026-01-047-Federal Rule.pdf | F59: ➔ | G59: ➔ | I59: LJ | J59: 026 | K59: 01
A60: 1292 | B60: 046 | C60: SP-046-1292.pdf | D60: R1-026-02-046-1292.pdf | F60: ➔ | G60: ➔ | I60: LJ | J60: 026 | K60: 02
A61: Infra Notes 280 | B61: 048 | C61: SP-048-Infra Notes 280.pdf | D61: R1-026-03-048-Infra Notes 280.pdf | F61: ➔ | G61: ➔ | I61: LJ | J61: 026 | K61: 03
A62: Collord v US Dep't of the Interior | B62: 049 | C62: SP-049-Collord v US Dep't of the Interior.pdf | D62: R1-027-01-049-Collord v US Dep't of the Interior.pdf | F62: ➔ | G62: ➔ | I62: LJ | J62: 027 | K62: 01
A63: Infra Notes 132-181 | B63: 050 | C63: SP-050-Infra Notes 132-181.pdf | D63: R1-027-02-050-Infra Notes 132-181.pdf | F63: ➔ | G63: ➔ | I63: LJ | J63: 027 | K63: 02
A64: Alsea Valley Alliance v Dep't of Commerce | B64: 008 | C64: SP-008-Alsea Valley Alliance v Dep't of Commerce.pdf | D64: R1-028-01-008-Alsea Valley Alliance v Dep't of Commerce.pdf | F64: ➔ | G64: ➔ | I64: LJ | J64: 028 | K64: 01
A65: Crowder v Sullivan | B65: 051 | C65: SP-051-Crowder v Sullivan.pdf | D65: R1-028-02-051-Crowder v Sullivan.pdf | F65: ➔ | G65: ➔ | I65: LJ | J65: 028 | K65: 02
A66: Federal Practice 3914 32 | B66: 026 | C66: SP-026-Federal Practice 3914 32.pdf | D66: R1-028-03-026-Federal Practice 3914 32.pdf | F66: ➔ | G66: ➔ | I66: LJ | J66: 028 | K66: 03
A67: Papotto | B67: 052 | C67: SP-052-Papotto.pdf | D67: R1-029-01-052-Papotto.pdf | F67: ➔ | G67: ➔ | I67: LJ | J67: 029 | K67: 01
A68: Kreider | B68: 053 | C68: SP-053-Kreider.pdf | D68: R1-029-02-053-Kreider.pdf | F68: ➔ | G68: ➔ | I68: LJ | J68: 029 | K68: 02
A69: Digital Equip Corp | B69: 054 | C69: SP-054-Digital Equip Corp.pdf | D69: R1-029-03-054-Digital Equip Corp.pdf | F69: ➔ | G69: ➔ | I69: LJ | J69: 029 | K69: 03
A70: Bagley | B70: 055 | C70: SP-055-Bagley.pdf | D70: R1-030-01-055-Bagley.pdf | F70: ➔ | G70: ➔ | I70: LJ | J70: 030 | K70: 01
A71: 706 | B71: 056 | C71: SP-056-706.pdf | D71: R1-030-02-056-706.pdf | F71: ➔ | G71: ➔ | I71: LJ | J71: 030 | K71: 02
A72: Chenery Corp | B72: 057 | C72: SP-057-Chenery Corp.pdf | D72: R1-031-01-057-Chenery Corp.pdf | F72: ➔ | G72: ➔ | I72: LJ | J72: 031 | K72: 01
A73: Wages and White Lion Invs | B73: 058 | C73: SP-058-Wages and White Lion Invs.pdf | D73: R1-031-02-058-Wages and White Lion Invs.pdf | F73: ➔ | G73: ➔ | I73: LJ | J73: 031 | K73: 02
A74: Glicksman | B74: 059 | C74: SP-059-Glicksman.pdf | D74: R1-031-03-059-Glicksman.pdf | F74: ➔ | G74: ➔ | I74: LJ | J74: 031 | K74: 03
A75: Walker Referral | B75: 060 | C75: SP-060-Walker Referral.pdf | D75: R1-031-04-060-Walker Referral.pdf | F75: ➔ | G75: ➔ | I75: LJ | J75: 031 | K75: 04
A76: Walker Ordinary | B76: 061 | C76: SP-061-Walker Ordinary.pdf | D76: R1-031-05-061-Walker Ordinary.pdf | F76: ➔ | G76: ➔ | I76: LJ | J76: 031 | K76: 05
A77: Infra Notes 257-261 and Accompanying Text | B77: 062 | C77: SP-062-Infra Notes 257-261 and Accompanying Text.pdf | D77: R1-032-01-062-Infra Notes 257-261 and Accompanying Text.pdf | F77: ➔ | G77: ➔ | I77: LJ | J77: 032 | K77: 01
A78: Revesz | B78: 063 | C78: SP-063-Revesz.pdf | D78: R1-033-01-063-Revesz.pdf | F78: ➔ | G78: ➔ | I78: LJ | J78: 033 | K78: 01
A79: Fine | B79: 064 | C79: SP-064-Fine.pdf | D79: R1-033-02-064-Fine.pdf | F79: ➔ | G79: ➔ | I79: LJ | J79: 033 | K79: 02
A80: Motor Vehicle Mfrs | B80: 065 | C80: SP-065-Motor Vehicle Mfrs.pdf | D80: R1-034-01-065-Motor Vehicle Mfrs.pdf | F80: ➔ | G80: ➔ | I80: LJ | J80: 034 | K80: 01
A81: Friendly | B81: 066 | C81: SP-066-Friendly.pdf | D81: R1-035-01-066-Friendly.pdf | F81: ➔ | G81: ➔ | I81: LJ | J81: 035 | K81: 01
A82: Lynch | B82: 025 | C82: SP-025-Lynch.pdf | D82: R1-035-02-025-Lynch.pdf | F82: ➔ | G82: ➔ | I82: LJ | J82: 035 | K82: 02
A83: Mendoza | B83: 067 | C83: SP-067-Mendoza.pdf | D83: R1-036-01-067-Mendoza.pdf | F83: ➔ | G83: ➔ | I83: LJ | J83: 036 | K83: 01
A84: Pauly v US Dept of Agri | B84: 068 | C84: SP-068-Pauly v US Dept of Agri.pdf | D84: R1-037-01-068-Pauly v US Dept of Agri.pdf | F84: ➔ | G84: ➔ | I84: LJ | J84: 037 | K84: 01
A85: 1292 | B85: 046 | C85: SP-046-1292.pdf | D85: R1-001-00-046-1292.pdf | F85: ➔ | G85: ➔ | I85: LJ | J85: 001 | K85: 00
A86: 1292 | B86: 046 | C86: SP-046-1292.pdf | D86: R1-001-00-046-1292.pdf | F86: ➔ | G86: ➔ | I86: LJ | J86: 001 | K86: 00
A87: Billboard (1976) | B87: 159 | C87: SP-159-Billboard (1976).pdf | D87: R1-001-00-159-Billboard (1976).pdf | F87: ➔ | G87: ➔ | I87: LJ | J87: 001 | K87: 00
A88: Friends 2008 | B88: 259 | C88: SP-259-Friends 2008.pdf | D88: R1-001-00-259-Friends 2008.pdf | F88: ➔ | G88: ➔ | I88: LJ | J88: 001 | K88: 00

Sheet Copy of CC
A1: Source | F1: Drive | I1: Round 1 | Q1: Round 2
A2: Short Name | B2: ID | C2: SP String (DNE) | D2: R1 String (DNE) | E2: R2 String (DNE) | F2: SP | G2: R1 | H2: R2 | I2: MEM | J2: Fn# | K2: Cite# | L2: Supports? | M2: Citation Elements | N2: MEM Comments | O2: SE Response | P2: Kickback Response | Q2: MEM | R2: Fn# | S2: Cite# | T2: Supports? | U2: Citation Elements | V2: MEM Comments | W2: SE Response | X2: Kickback Response
A3: Keep this row hidden / do not edit! | B3: {=IF($A$3:$A11<>"", XLOOKUP($A$3:$A11, Sourcepull!$B$3:$B11, Sourcepull!$A$3:$A11, ""), "")} | C3: {=if($A$3:$A11<>"","SP-"&$B$3:$B11&"-"&$A$3:$A11&".pdf", "")} -> SP--Keep this row hidden / do not edit!.pdf | D3: {=if($J$3:$J11<>"","R1-"&$J$3:$J11&"-"&$K$3:$K11&"-"&$B$3:$B11&"-"&$A$3:$A11&".pdf", "")} | E3: {=if($R$3:$R11<>"","R2-"&$R$3:$R11&"-"&$S$3:$S11&"-"&$B$3:$B11&"-"&$A$3:$A11&".pdf", "")} | F3: {=if($C$3:$C11 <> "", hyperlink("https://drive.google.com/drive/search?q=parent:" & Properties!$C$8 & "%20" & char(34) & $C$3:$C11 & char(34), "➔"), "")} -> ➔ | G3: {=if($D$3:$D11 <> "", hyperlink("https://drive.google.com/drive/search?q=parent:" & Properties!$C$9 & "%20" & char(34) & $D$3:$D11 & char(34), "➔"), "")} | H3: {=if($E$3:$E11 <> "", hyperlink("https://drive.google.com/drive/search?q=parent:" & Properties!$C$10 & "%20" & char(34) & $E$3:$E11 & char(34), "➔"), "")}

Sheet CC (nn. 38-81); SSH
A1: Source | F1: Drive | I1: Round 1 | Q1: Round 2
A2: Short Name | B2: ID | C2: SP String (DNE) | D2: R1 String (DNE) | E2: R2 String (DNE) | F2: SP | G2: R1 | H2: R2 | I2: MEM | J2: Fn# | K2: Cite# | L2: Supports? | M2: Citation Elements | N2: MEM Comments | O2: SE Response | P2: Kickback Response | Q2: MEM | R2: Fn# | S2: Cite# | T2: Supports? | U2: Citation Elements | V2: MEM Comments | W2: SE Response | X2: Kickback Response
A3: Keep this row hidden / do not edit! | B3: {=IF($A$3:$A82<>"", XLOOKUP($A$3:$A82, Sourcepull!$B$3:$B82, Sourcepull!$A$3:$A82, ""), "")} | C3: {=if($A$3:$A82<>"","SP-"&$B$3:$B82&"-"&$A$3:$A82&".pdf", "")} -> SP--Keep this row hidden / do not edit!.pdf | D3: {=if($J$3:$J82<>"","R1-"&$J$3:$J82&"-"&$K$3:$K82&"-"&$B$3:$B82&"-"&$A$3:$A82&".pdf", "")} | E3: {=if($R$3:$R82<>"","R2-"&$R$3:$R82&"-"&$S$3:$S82&"-"&$B$3:$B82&"-"&$A$3:$A82&".pdf", "")} | F3: {=if($C$3:$C82 <> "", hyperlink("https://drive.google.com/drive/search?q=parent:" & Properties!$C$8 & "%20" & char(34) & $C$3:$C82 & char(34), "➔"), "")} -> ➔ | G3: {=if($D$3:$D82 <> "", hyperlink("https://drive.google.com/drive/search?q=parent:" & Properties!$C$9 & "%20" & char(34) & $D$3:$D82 & char(34), "➔"), "")} | H3: {=if($E$3:$E82 <> "", hyperlink("https://drive.google.com/drive/search?q=parent:" & Properties!$C$10 & "%20" & char(34) & $E$3:$E82 & char(34), "➔"), "")}
A4: Vista | B4: 069 | C4: SP-069-Vista.pdf | D4: R1-038-01-069-Vista.pdf | F4: ➔ | G4: ➔ | I4: SSH | J4: 038 | K4: 01
A5: Act of Sept 24 | B5: 070 | C5: SP-070-Act of Sept 24.pdf | D5: R1-039-01-070-Act of Sept 24.pdf | F5: ➔ | G5: ➔ | I5: SSH | J5: 039 | K5: 01
A6: Federal Practice 3906 | B6: 071 | C6: SP-071-Federal Practice 3906.pdf | D6: R1-040-01-071-Federal Practice 3906.pdf | F6: ➔ | G6: ➔ | I6: SSH | J6: 040 | K6: 01
A7: Metcalfe | B7: 072 | C7: SP-072-Metcalfe.pdf | D7: R1-040-02-072-Metcalfe.pdf | F7: ➔ | G7: ➔ | I7: SSH | J7: 040 | K7: 02
A8: Catlin v United States | B8: 073 | C8: SP-073-Catlin v United States.pdf | D8: R1-041-01-073-Catlin v United States.pdf | F8: ➔ | G8: ➔ | I8: SSH | J8: 041 | K8: 01
A9: 1291 | B9: 045 | C9: SP-045-1291.pdf | D9: R1-042-01-045-1291.pdf | F9: ➔ | G9: ➔ | I9: SSH | J9: 042 | K9: 01
A10: 62 Stat | B10: 074 | C10: SP-074-62 Stat.pdf | D10: R1-042-02-074-62 Stat.pdf | F10: ➔ | G10: ➔ | I10: SSH | J10: 042 | K10: 02
A11: Bachowski v Usery | B11: 075 | C11: SP-075-Bachowski v Usery.pdf | D11: R1-043-01-075-Bachowski v Usery.pdf | F11: ➔ | G11: ➔ | I11: SSH | J11: 043 | K11: 01
A12: Katz v Carte Blanche Corp | B12: 076 | C12: SP-076-Katz v Carte Blanche Corp.pdf | D12: R1-043-02-076-Katz v Carte Blanche Corp.pdf | F12: ➔ | G12: ➔ | I12: SSH | J12: 043 | K12: 02
A13: 1292 | B13: 046 | C13: SP-046-1292.pdf | D13: R1-043-03-046-1292.pdf | F13: ➔ | G13: ➔ | I13: SSH | J13: 043 | K13: 03
A14: Bachowski v Usery | B14: 075 | C14: SP-075-Bachowski v Usery.pdf | D14: R1-044-01-075-Bachowski v Usery.pdf | F14: ➔ | G14: ➔ | I14: SSH | J14: 044 | K14: 01
A15: 1291 | B15: 045 | C15: SP-045-1291.pdf | D15: R1-045-01-045-1291.pdf | F15: ➔ | G15: ➔ | I15: SSH | J15: 045 | K15: 01
A16: P. Law 79 | B16: 077 | C16: SP-077-P. Law 79.pdf | D16: R1-045-02-077-P. Law 79.pdf | F16: ➔ | G16: ➔ | I16: SSH | J16: 045 | K16: 02
A17: Cobbledick | B17: 078 | C17: SP-078-Cobbledick.pdf | D17: R1-046-01-078-Cobbledick.pdf | F17: ➔ | G17: ➔ | I17: SSH | J17: 046 | K17: 01
A18: Federal Practice 3907 | B18: 079 | C18: SP-079-Federal Practice 3907.pdf | D18: R1-046-02-079-Federal Practice 3907.pdf | F18: ➔ | G18: ➔ | I18: SSH | J18: 046 | K18: 02
A19: Microsoft Corp v Baker | B19: 080 | C19: SP-080-Microsoft Corp v Baker.pdf | D19: R1-047-01-080-Microsoft Corp v Baker.pdf | F19: ➔ | G19: ➔ | I19: SSH | J19: 047 | K19: 01
A20: Mohawk | B20: 081 | C20: SP-081-Mohawk.pdf | D20: R1-047-02-081-Mohawk.pdf | F20: ➔ | G20: ➔ | I20: SSH | J20: 047 | K20: 02
A21: Johnson v Jones | B21: 082 | C21: SP-082-Johnson v Jones.pdf | D21: R1-047-03-082-Johnson v Jones.pdf | F21: ➔ | G21: ➔ | I21: SSH | J21: 047 | K21: 03
A22: Digital Equip Corp | B22: 054 | C22: SP-054-Digital Equip Corp.pdf | D22: R1-047-04-054-Digital Equip Corp.pdf | F22: ➔ | G22: ➔ | I22: SSH | J22: 047 | K22: 04
A23: Di Bella v United States | B23: 083 | C23: SP-083-Di Bella v United States.pdf | D23: R1-047-05-083-Di Bella v United States.pdf | F23: ➔ | G23: ➔ | I23: SSH | J23: 047 | K23: 05
A24: Cobbledick | B24: 078 | C24: SP-078-Cobbledick.pdf | D24: R1-047-06-078-Cobbledick.pdf | F24: ➔ | G24: ➔ | I24: SSH | J24: 047 | K24: 06
A25: Federal Practice 3907 | B25: 079 | C25: SP-079-Federal Practice 3907.pdf | D25: R1-047-07-079-Federal Practice 3907.pdf | F25: ➔ | G25: ➔ | I25: SSH | J25: 047 | K25: 07
A26: Lammon Disarming | B26: 084 | C26: SP-084-Lammon Disarming.pdf | D26: R1-047-08-084-Lammon Disarming.pdf | F26: ➔ | G26: ➔ | I26: SSH | J26: 047 | K26: 08
A27: Frank | B27: 085 | C27: SP-085-Frank.pdf | D27: R1-047-09-085-Frank.pdf | F27: ➔ | G27: ➔ | I27: SSH | J27: 047 | K27: 09
... A82: Anderson | B82: 107 | C82: SP-107-Anderson.pdf | D82: R1-081-03-107-Anderson.pdf | F82: ➔ | G82: ➔ | I82: SSH | J82: 081 | K82: 03

Sheet CC (nn. 82-115); IG
A1: Source | F1: Drive | I1: Round 1 | Q1: Round 2
A2: Short Name | B2: ID | C2: SP String (DNE) | D2: R1 String (DNE) | E2: R2 String (DNE) | F2: SP | G2: R1 | H2: R2 | I2: MEM | J2: Fn# | K2: Cite# | L2: Supports? | M2: Citation Elements | N2: MEM Comments | O2: SE Response | P2: Kickback Response | Q2: MEM | R2: Fn# | S2: Cite# | T2: Supports? | U2: Citation Elements | V2: MEM Comments | W2: SE Response | X2: Kickback Response
A3: Keep this row hidden / do not edit! | B3: {=IF($A$3:$A83<>"", XLOOKUP($A$3:$A83, Sourcepull!$B$3:$B83, Sourcepull!$A$3:$A83, ""), "")} | C3: {=if($A$3:$A83<>"","SP-"&$B$3:$B83&"-"&$A$3:$A83&".pdf", "")} -> SP--Keep this row hidden / do not edit!.pdf | D3: {=if($J$3:$J83<>"","R1-"&$J$3:$J83&"-"&$K$3:$K83&"-"&$B$3:$B83&"-"&$A$3:$A83&".pdf", "")} | E3: {=if($R$3:$R83<>"","R2-"&$R$3:$R83&"-"&$S$3:$S83&"-"&$B$3:$B83&"-"&$A$3:$A83&".pdf", "")} | F3: {=if($C$3:$C83 <> "", hyperlink("https://drive.google.com/drive/search?q=parent:" & Properties!$C$8 & "%20" & char(34) & $C$3:$C83 & char(34), "➔"), "")} -> ➔ | G3: {=if($D$3:$D83 <> "", hyperlink("https://drive.google.com/drive/search?q=parent:" & Properties!$C$9 & "%20" & char(34) & $D$3:$D83 & char(34), "➔"), "")} | H3: {=if($E$3:$E83 <> "", hyperlink("https://drive.google.com/drive/search?q=parent:" & Properties!$C$10 & "%20" & char(34) & $E$3:$E83 & char(34), "➔"), "")}
A4: 437 US | B4: 105 | C4: SP-105-437 US.pdf | D4: R1-082-01-105-437 US.pdf | F4: ➔ | G4: ➔ | I4: IG | J4: 082 | K4: 01
A5: Firestone Tire and Rubber Co v Risjord | B5: 087 | C5: SP-087-Firestone Tire and Rubber Co v Risjord.pdf | D5: R1-083-01-087-Firestone Tire and Rubber Co v Risjord.pdf | F5: ➔ | G5: ➔ | I5: IG | J5: 083 | K5: 01
A6: Flanagan v United States | B6: 108 | C6: SP-108-Flanagan v United States.pdf | D6: R1-083-02-108-Flanagan v United States.pdf | F6: ➔ | G6: ➔ | I6: IG | J6: 083 | K6: 02
A7: Richardson-Merrell Inc v Koller | B7: 088 | C7: SP-088-Richardson-Merrell Inc v Koller.pdf | D7: R1-083-03-088-Richardson-Merrell Inc v Koller.pdf | F7: ➔ | G7: ➔ | I7: IG | J7: 083 | K7: 03
A8: Stringfellow v Concerned Neighbors in Action | B8: 109 | C8: SP-109-Stringfellow v Concerned Neighbors in Action.pdf | D8: R1-084-01-109-Stringfellow v Concerned Neighbors in Action.pdf | F8: ➔ | G8: ➔ | I8: IG | J8: 084 | K8: 01
A9: Dickinson v Petroleum Conversion Corp | B9: 103 | C9: SP-103-Dickinson v Petroleum Conversion Corp.pdf | D9: R1-084-02-103-Dickinson v Petroleum Conversion Corp.pdf | F9: ➔ | G9: ➔ | I9: IG | J9: 084 | K9: 02
A10: Digital Equip Corp | B10: 054 | C10: SP-054-Digital Equip Corp.pdf | D10: R1-085-01-054-Digital Equip Corp.pdf | F10: ➔ | G10: ➔ | I10: IG | J10: 085 | K10: 01
A11: 437 US | B11: 105 | C11: SP-105-437 US.pdf | D11: R1-086-01-105-437 US.pdf | F11: ➔ | G11: ➔ | I11: IG | J11: 086 | K11: 01
A12: 437 US | B12: 105 | C12: SP-105-437 US.pdf | D12: R1-087-01-105-437 US.pdf | F12: ➔ | G12: ➔ | I12: IG | J12: 087 | K12: 01
A13: Rules | B13: 110 | C13: SP-110-Rules.pdf | D13: R1-087-02-110-Rules.pdf | F13: ➔ | G13: ➔ | I13: IG | J13: 087 | K13: 02
A14: FRCP 23(f) | B14: 111 | C14: SP-111-FRCP 23(f).pdf | D14: R1-087-03-111-FRCP 23(f).pdf | F14: ➔ | G14: ➔ | I14: IG | J14: 087 | K14: 03
A15: Microsoft Corp v Baker | B15: 080 | C15: SP-080-Microsoft Corp v Baker.pdf | D15: R1-087-04-080-Microsoft Corp v Baker.pdf | F15: ➔ | G15: ➔ | I15: IG | J15: 087 | K15: 04
... A83: Nat'l Air Traffic Controllers | B83: 153 | C83: SP-153-Nat'l Air Traffic Controllers.pdf | D83: R1-115-08-153-Nat'l Air Traffic Controllers.pdf | F83: ➔ | G83: ➔ | I83: IG | J83: 115 | K83: 08

Sheet CC (nn. 116-150); BR
A1: Source | F1: Drive | I1: Round 1 | Q1: Round 2
A2: Short Name | B2: ID | C2: SP String (DNE) | D2: R1 String (DNE) | E2: R2 String (DNE) | F2: SP | G2: R1 | H2: R2 | I2: MEM | J2: Fn# | K2: Cite# | L2: Supports? | M2: Citation Elements | N2: MEM Comments | O2: SE Response | P2: Kickback Response | Q2: MEM | R2: Fn# | S2: Cite# | T2: Supports? | U2: Citation Elements | V2: MEM Comments | W2: SE Response | X2: Kickback Response
A3: Keep this row hidden / do not edit! | B3: {=IF($A$3:$A80<>"", XLOOKUP($A$3:$A80, Sourcepull!$B$3:$B80, Sourcepull!$A$3:$A80, ""), "")} | C3: {=if($A$3:$A80<>"","SP-"&$B$3:$B80&"-"&$A$3:$A80&".pdf", "")} -> SP--Keep this row hidden / do not edit!.pdf | D3: {=if($J$3:$J80<>"","R1-"&$J$3:$J80&"-"&$K$3:$K80&"-"&$B$3:$B80&"-"&$A$3:$A80&".pdf", "")} | E3: {=if($R$3:$R80<>"","R2-"&$R$3:$R80&"-"&$S$3:$S80&"-"&$B$3:$B80&"-"&$A$3:$A80&".pdf", "")} | F3: {=if($C$3:$C80 <> "", hyperlink("https://drive.google.com/drive/search?q=parent:" & Properties!$C$8 & "%20" & char(34) & $C$3:$C80 & char(34), "➔"), "")} -> ➔ | G3: {=if($D$3:$D80 <> "", hyperlink("https://drive.google.com/drive/search?q=parent:" & Properties!$C$9 & "%20" & char(34) & $D$3:$D80 & char(34), "➔"), "")} | H3: {=if($E$3:$E80 <> "", hyperlink("https://drive.google.com/drive/search?q=parent:" & Properties!$C$10 & "%20" & char(34) & $E$3:$E80 & char(34), "➔"), "")}
A4: Supra Notes 98-115 and Accompanying Text | B4: 154 | C4: SP-154-Supra Notes 98-115 and Accompanying Text.pdf | D4: R1-116-01-154-Supra Notes 98-115 and Accompanying Text.pdf | F4: ➔ | G4: ➔ | I4: BR | J4: 116 | K4: 01
A5: Cotton Petroleum Corp | B5: 155 | C5: SP-155-Cotton Petroleum Corp.pdf | D5: R1-116-02-155-Cotton Petroleum Corp.pdf | F5: ➔ | G5: ➔ | I5: BR | J5: 116 | K5: 02
A6: Infra Notes 177 | B6: 156 | C6: SP-156-Infra Notes 177.pdf | D6: R1-116-03-156-Infra Notes 177.pdf | F6: ➔ | G6: ➔ | I6: BR | J6: 116 | K6: 03
A7: Infra Notes 134-194 and Accompanying Text | B7: 157 | C7: SP-157-Infra Notes 134-194 and Accompanying Text.pdf | D7: R1-117-01-157-Infra Notes 134-194 and Accompanying Text.pdf | F7: ➔ | G7: ➔ | I7: BR | J7: 117 | K7: 01
A8: Infra Notes 134-194 and Accompanying Text | B8: 157 | C8: SP-157-Infra Notes 134-194 and Accompanying Text.pdf | D8: R1-118-01-157-Infra Notes 134-194 and Accompanying Text.pdf | F8: ➔ | G8: ➔ | I8: BR | J8: 118 | K8: 01
A9: Billboard (1987) | B9: 158 | C9: SP-158-Billboard (1987).pdf | D9: R1-119-01-158-Billboard (1987).pdf | F9: ➔ | G9: ➔ | I9: BR | J9: 119 | K9: 01
A10: Aja Assocs v Army Corps of Eng'rs | B10: 133 | C10: SP-133-Aja Assocs v Army Corps of Eng'rs.pdf | D10: R1-120-01-133-Aja Assocs v Army Corps of Eng'rs.pdf | F10: ➔ | G10: ➔ | I10: BR | J10: 120 | K10: 01
A11: Bachowski v Usery | B11: 075 | C11: SP-075-Bachowski v Usery.pdf | D11: R1-120-02-075-Bachowski v Usery.pdf | F11: ➔ | G11: ➔ | I11: BR | J11: 120 | K11: 02
A12: Harper v Bowen | B12: 127 | C12: SP-127-Harper v Bowen.pdf | D12: R1-121-01-127-Harper v Bowen.pdf | F12: ➔ | G12: ➔ | I12: BR | J12: 121 | K12: 01
A13: Stone v Heckler | B13: 138 | C13: SP-138-Stone v Heckler.pdf | D13: R1-122-01-138-Stone v Heckler.pdf | F13: ➔ | G13: ➔ | I13: BR | J13: 122 | K13: 01
A14: Regents of the Univ of Calif v Heckler | B14: 135 | C14: SP-135-Regents of the Univ of Calif v Heckler.pdf | D14: R1-122-02-135-Regents of the Univ of Calif v Heckler.pdf | F14: ➔ | G14: ➔ | I14: BR | J14: 122 | K14: 02
A15: Eluska v Andrus | B15: 144 | C15: SP-144-Eluska v Andrus.pdf | D15: R1-123-01-144-Eluska v Andrus.pdf | F15: ➔ | G15: ➔ | I15: BR | J15: 123 | K15: 01
... A80: Local 1982 | B80: 194 | C80: SP-194-Local 1982.pdf | D80: R1-150-04-194-Local 1982.pdf | F80: ➔ | G80: ➔ | I80: BR | J80: 150 | K80: 04

Sheet CC (nn. 151-184); LZ
A1: Source | F1: Drive | I1: Round 1 | Q1: Round 2
A2: Short Name | B2: ID | C2: SP String (DNE) | D2: R1 String (DNE) | E2: R2 String (DNE) | F2: SP | G2: R1 | H2: R2 | I2: MEM | J2: Fn# | K2: Cite# | L2: Supports? | M2: Citation Elements | N2: MEM Comments | O2: SE Response | P2: Kickback Response | Q2: MEM | R2: Fn# | S2: Cite# | T2: Supports? | U2: Citation Elements | V2: MEM Comments | W2: SE Response | X2: Kickback Response
A3: Keep this row hidden / do not edit! | B3: {=IF($A$3:$A82<>"", XLOOKUP($A$3:$A82, Sourcepull!$B$3:$B82, Sourcepull!$A$3:$A82, ""), "")} | C3: {=if($A$3:$A82<>"","SP-"&$B$3:$B82&"-"&$A$3:$A82&".pdf", "")} -> SP--Keep this row hidden / do not edit!.pdf | D3: {=if($J$3:$J82<>"","R1-"&$J$3:$J82&"-"&$K$3:$K82&"-"&$B$3:$B82&"-"&$A$3:$A82&".pdf", "")} | E3: {=if($R$3:$R82<>"","R2-"&$R$3:$R82&"-"&$S$3:$S82&"-"&$B$3:$B82&"-"&$A$3:$A82&".pdf", "")} | F3: {=if($C$3:$C82 <> "", hyperlink("https://drive.google.com/drive/search?q=parent:" & Properties!$C$8 & "%20" & char(34) & $C$3:$C82 & char(34), "➔"), "")} -> ➔ | G3: {=if($D$3:$D82 <> "", hyperlink("https://drive.google.com/drive/search?q=parent:" & Properties!$C$9 & "%20" & char(34) & $D$3:$D82 & char(34), "➔"), "")} | H3: {=if($E$3:$E82 <> "", hyperlink("https://drive.google.com/drive/search?q=parent:" & Properties!$C$10 & "%20" & char(34) & $E$3:$E82 & char(34), "➔"), "")}
A4: Matter | B4: 195 | C4: SP-195-Matter.pdf | D4: R1-151-01-195-Matter.pdf | F4: ➔ | G4: ➔ | I4: LZ | J4: 151 | K4: 01
A5: Am Train Dispatchers Dep't of Int'l BHD of Locomotive Eng'rs v Norfolk S Ry Co | B5: 196 | C5: SP-196-Am Train Dispatchers Dep't of Int'l BHD of Locomotive Eng'rs v Norfolk S Ry Co.pdf | D5: R1-152-01-196-Am Train Dispatchers Dep't of Int'l BHD of Locomotive Eng'rs v Norfolk S Ry Co.pdf | F5: ➔ | G5: ➔ | I5: LZ | J5: 152 | K5: 01
A6: Perlman v Swiss Bank Corp Comprehensive Disability Prot Plan | B6: 197 | C6: SP-197-Perlman v Swiss Bank Corp Comprehensive Disability Prot Plan.pdf | D6: R1-153-01-197-Perlman v Swiss Bank Corp Comprehensive Disability Prot Plan.pdf | F6: ➔ | G6: ➔ | I6: LZ | J6: 153 | K6: 01
A7: Travis v Sullivan | B7: 198 | C7: SP-198-Travis v Sullivan.pdf | D7: R1-154-01-198-Travis v Sullivan.pdf | F7: ➔ | G7: ➔ | I7: LZ | J7: 154 | K7: 01
A8: Crowder v Sullivan | B8: 051 | C8: SP-051-Crowder v Sullivan.pdf | D8: R1-154-02-051-Crowder v Sullivan.pdf | F8: ➔ | G8: ➔ | I8: LZ | J8: 154 | K8: 02
A9: Perlman v Swiss Bank Corp Comprehensive Disability Prot Plan | B9: 197 | C9: SP-197-Perlman v Swiss Bank Corp Comprehensive Disability Prot Plan.pdf | D9: R1-155-01-197-Perlman v Swiss Bank Corp Comprehensive Disability Prot Plan.pdf | F9: ➔ | G9: ➔ | I9: LZ | J9: 155 | K9: 01
A10: Matter | B10: 195 | C10: SP-195-Matter.pdf | D10: R1-155-02-195-Matter.pdf | F10: ➔ | G10: ➔ | I10: LZ | J10: 155 | K10: 02
A11: Izaak Walton | B11: 199 | C11: SP-199-Izaak Walton.pdf | D11: R1-156-01-199-Izaak Walton.pdf | F11: ➔ | G11: ➔ | I11: LZ | J11: 156 | K11: 01
A12: City | B12: 200 | C12: SP-200-City.pdf | D12: R1-157-01-200-City.pdf | F12: ➔ | G12: ➔ | I12: LZ | J12: 157 | K12: 01
A13: Davies v Johanns | B13: 201 | C13: SP-201-Davies v Johanns.pdf | D13: R1-157-02-201-Davies v Johanns.pdf | F13: ➔ | G13: ➔ | I13: LZ | J13: 157 | K13: 02
A14: City | B14: 200 | C14: SP-200-City.pdf | D14: R1-158-01-200-City.pdf | F14: ➔ | G14: ➔ | I14: LZ | J14: 158 | K14: 01
A15: Izaak Walton | B15: 199 | C15: SP-199-Izaak Walton.pdf | D15: R1-158-02-199-Izaak Walton.pdf | F15: ➔ | G15: ➔ | I15: LZ | J15: 158 | K15: 02
... A82: Trout Unlimited v US Dep't of Agric | B82: 221 | C82: SP-221-Trout Unlimited v US Dep't of Agric.pdf | D82: R1-184-03-221-Trout Unlimited v US Dep't of Agric.pdf | F82: ➔ | G82: ➔ | I82: LZ | J82: 184 | K82: 03

Sheet CC (nn. 185-224); JL
A1: Source | F1: Drive | I1: Round 1 | Q1: Round 2
A2: Short Name | B2: ID | C2: SP String (DNE) | D2: R1 String (DNE) | E2: R2 String (DNE) | F2: SP | G2: R1 | H2: R2 | I2: MEM | J2: Fn# | K2: Cite# | L2: Supports? | M2: Citation Elements | N2: MEM Comments | O2: SE Response | P2: Kickback Response | Q2: MEM | R2: Fn# | S2: Cite# | T2: Supports? | U2: Citation Elements | V2: MEM Comments | W2: SE Response | X2: Kickback Response
A3: Keep this row hidden / do not edit! | B3: {=IF($A$3:$A80<>"", XLOOKUP($A$3:$A80, Sourcepull!$B$3:$B80, Sourcepull!$A$3:$A80, ""), "")} | C3: {=if($A$3:$A80<>"","SP-"&$B$3:$B80&"-"&$A$3:$A80&".pdf", "")} -> SP--Keep this row hidden / do not edit!.pdf | D3: {=if($J$3:$J80<>"","R1-"&$J$3:$J80&"-"&$K$3:$K80&"-"&$B$3:$B80&"-"&$A$3:$A80&".pdf", "")} | E3: {=if($R$3:$R80<>"","R2-"&$R$3:$R80&"-"&$S$3:$S80&"-"&$B$3:$B80&"-"&$A$3:$A80&".pdf", "")} | F3: {=if($C$3:$C80 <> "", hyperlink("https://drive.google.com/drive/search?q=parent:" & Properties!$C$8 & "%20" & char(34) & $C$3:$C80 & char(34), "➔"), "")} -> ➔ | G3: {=if($D$3:$D80 <> "", hyperlink("https://drive.google.com/drive/search?q=parent:" & Properties!$C$9 & "%20" & char(34) & $D$3:$D80 & char(34), "➔"), "")} | H3: {=if($E$3:$E80 <> "", hyperlink("https://drive.google.com/drive/search?q=parent:" & Properties!$C$10 & "%20" & char(34) & $E$3:$E80 & char(34), "➔"), "")}
A4: Cherokee Nation v Bernhardt | B4: 229 | C4: SP-229-Cherokee Nation v Bernhardt.pdf | D4: R1-185-01-229-Cherokee Nation v Bernhardt.pdf | F4: ➔ | G4: ➔ | I4: JL | J4: 185 | K4: 01
A5: Crow Indian Tribe v United States | B5: 210 | C5: SP-210-Crow Indian Tribe v United States.pdf | D5: R1-185-02-210-Crow Indian Tribe v United States.pdf | F5: ➔ | G5: ➔ | I5: JL | J5: 185 | K5: 02
A6: Zen | B6: 213 | C6: SP-213-Zen.pdf | D6: R1-185-03-213-Zen.pdf | F6: ➔ | G6: ➔ | I6: JL | J6: 185 | K6: 03
A7: Supra Note 165 and Accompanying Text | B7: 230 | C7: SP-230-Supra Note 165 and Accompanying Text.pdf | D7: R1-186-01-230-Supra Note 165 and Accompanying Text.pdf | F7: ➔ | G7: ➔ | I7: JL | J7: 186 | K7: 01
A8: Pauly v US Dept of Agri | B8: 068 | C8: SP-068-Pauly v US Dept of Agri.pdf | D8: R1-187-01-068-Pauly v US Dept of Agri.pdf | F8: ➔ | G8: ➔ | I8: JL | J8: 187 | K8: 01
A9: Koyo Seiko Co v United States | B9: 174 | C9: SP-174-Koyo Seiko Co v United States.pdf | D9: R1-187-02-174-Koyo Seiko Co v United States.pdf | F9: ➔ | G9: ➔ | I9: JL | J9: 187 | K9: 02
A10: Federal Practice 3914 32 | B10: 026 | C10: SP-026-Federal Practice 3914 32.pdf | D10: R1-187-03-026-Federal Practice 3914 32.pdf | F10: ➔ | G10: ➔ | I10: JL | J10: 187 | K10: 03
A11: Administrative Office | B11: 231 | C11: SP-231-Administrative Office.pdf | D11: R1-188-01-231-Administrative Office.pdf | F11: ➔ | G11: ➔ | I11: JL | J11: 188 | K11: 01
A12: Pauly v US Dept of Agri | B12: 068 | C12: SP-068-Pauly v US Dept of Agri.pdf | D12: R1-189-01-068-Pauly v US Dept of Agri.pdf | F12: ➔ | G12: ➔ | I12: JL | J12: 189 | K12: 01
A13: Chang v United States | B13: 232 | C13: SP-232-Chang v United States.pdf | D13: R1-189-02-232-Chang v United States.pdf | F13: ➔ | G13: ➔ | I13: JL | J13: 189 | K13: 02
A14: Skagit Cnty | B14: 211 | C14: SP-211-Skagit Cnty.pdf | D14: R1-189-03-211-Skagit Cnty.pdf | F14: ➔ | G14: ➔ | I14: JL | J14: 189 | K14: 03
A15: Sierra Forest Legacy v Sherman | B15: 204 | C15: SP-204-Sierra Forest Legacy v Sherman.pdf | D15: R1-190-01-204-Sierra Forest Legacy v Sherman.pdf | F15: ➔ | G15: ➔ | I15: JL | J15: 190 | K15: 01
... A80: Supra Notes 184-185 and Accompanying Text | B80: 262 | C80: SP-262-Supra Notes 184-185 and Accompanying Text.pdf | D80: R1-224-01-262-Supra Notes 184-185 and Accompanying Text.pdf | F80: ➔ | G80: ➔ | I80: JL | J80: 224 | K80: 01

Sheet CC (nn. 225-279); BV
A1: Source | F1: Drive | I1: Round 1 | Q1: Round 2
A2: Short Name | B2: ID | C2: SP String (DNE) | D2: R1 String (DNE) | E2: R2 String (DNE) | F2: SP | G2: R1 | H2: R2 | I2: MEM | J2: Fn# | K2: Cite# | L2: Supports? | M2: Citation Elements | N2: MEM Comments | O2: SE Response | P2: Kickback Response | Q2: MEM | R2: Fn# | S2: Cite# | T2: Supports? | U2: Citation Elements | V2: MEM Comments | W2: SE Response | X2: Kickback Response
A3: Keep this row hidden / do not edit! | B3: {=IF($A$3:$A83<>"", XLOOKUP($A$3:$A83, Sourcepull!$B$3:$B83, Sourcepull!$A$3:$A83, ""), "")} | C3: {=if($A$3:$A83<>"","SP-"&$B$3:$B83&"-"&$A$3:$A83&".pdf", "")} -> SP--Keep this row hidden / do not edit!.pdf | D3: {=if($J$3:$J83<>"","R1-"&$J$3:$J83&"-"&$K$3:$K83&"-"&$B$3:$B83&"-"&$A$3:$A83&".pdf", "")} | E3: {=if($R$3:$R83<>"","R2-"&$R$3:$R83&"-"&$S$3:$S83&"-"&$B$3:$B83&"-"&$A$3:$A83&".pdf", "")} | F3: {=if($C$3:$C83 <> "", hyperlink("https://drive.google.com/drive/search?q=parent:" & Properties!$C$8 & "%20" & char(34) & $C$3:$C83 & char(34), "➔"), "")} -> ➔ | G3: {=if($D$3:$D83 <> "", hyperlink("https://drive.google.com/drive/search?q=parent:" & Properties!$C$9 & "%20" & char(34) & $D$3:$D83 & char(34), "➔"), "")} | H3: {=if($E$3:$E83 <> "", hyperlink("https://drive.google.com/drive/search?q=parent:" & Properties!$C$10 & "%20" & char(34) & $E$3:$E83 & char(34), "➔"), "")}
A4: Bagley | B4: 055 | C4: SP-055-Bagley.pdf | D4: R1-225-01-055-Bagley.pdf | F4: ➔ | G4: ➔ | I4: BV | J4: 225 | K4: 01
A5: Desert Survivors v United States Dep't of the Interior | B5: 263 | C5: SP-263-Desert Survivors v United States Dep't of the Interior.pdf | D5: R1-225-02-263-Desert Survivors v United States Dep't of the Interior.pdf | F5: ➔ | G5: ➔ | I5: BV | J5: 225 | K5: 02
A6: Supra Notes 35-38 and Accompanying Text | B6: 264 | C6: SP-264-Supra Notes 35-38 and Accompanying Text.pdf | D6: R1-226-01-264-Supra Notes 35-38 and Accompanying Text.pdf | F6: ➔ | G6: ➔ | I6: BV | J6: 226 | K6: 01
A7: Sierra Club v US Dep't of Agric | B7: 166 | C7: SP-166-Sierra Club v US Dep't of Agric.pdf | D7: R1-227-01-166-Sierra Club v US Dep't of Agric.pdf | F7: ➔ | G7: ➔ | I7: BV | J7: 227 | K7: 01
A8: Dine Citizens Against Ruining Our Env't v Klein | B8: 225 | C8: SP-225-Dine Citizens Against Ruining Our Env't v Klein.pdf | D8: R1-227-02-225-Dine Citizens Against Ruining Our Env't v Klein.pdf | F8: ➔ | G8: ➔ | I8: BV | J8: 227 | K8: 02
A9: S Utah Wilderness Alliance v Kempthorne | B9: 223 | C9: SP-223-S Utah Wilderness Alliance v Kempthorne.pdf | D9: R1-227-03-223-S Utah Wilderness Alliance v Kempthorne.pdf | F9: ➔ | G9: ➔ | I9: BV | J9: 227 | K9: 03
A10: Rocky MTN Wild v Dallas | B10: 220 | C10: SP-220-Rocky MTN Wild v Dallas.pdf | D10: R1-228-01-220-Rocky MTN Wild v Dallas.pdf | F10: ➔ | G10: ➔ | I10: BV | J10: 228 | K10: 01
A11: Cherokee Nation | B11: 265 | C11: SP-265-Cherokee Nation.pdf | D11: R1-228-02-265-Cherokee Nation.pdf | F11: ➔ | G11: ➔ | I11: BV | J11: 228 | K11: 02
A12: Crow Indian Tribe v United States | B12: 210 | C12: SP-210-Crow Indian Tribe v United States.pdf | D12: R1-229-01-210-Crow Indian Tribe v United States.pdf | F12: ➔ | G12: ➔ | I12: BV | J12: 229 | K12: 01
A13: Skagit Cnty | B13: 211 | C13: SP-211-Skagit Cnty.pdf | D13: R1-230-01-211-Skagit Cnty.pdf | F13: ➔ | G13: ➔ | I13: BV | J13: 230 | K13: 01
A14: Skagit Cnty | B14: 211 | C14: SP-211-Skagit Cnty.pdf | D14: R1-231-01-211-Skagit Cnty.pdf | F14: ➔ | G14: ➔ | I14: BV | J14: 231 | K14: 01
A15: Chang v United States | B15: 232 | C15: SP-232-Chang v United States.pdf | D15: R1-232-01-232-Chang v United States.pdf | F15: ➔ | G15: ➔ | I15: BV | J15: 232 | K15: 01
... A83: Spitzer | B83: 240 | C83: SP-240-Spitzer.pdf | D83: R1-279-01-240-Spitzer.pdf | F83: ➔ | G83: ➔ | I83: BV | J83: 279 | K83: 01

Sheet CC (nn. 280-324); ME
A1: Source | F1: Drive | I1: Round 1 | Q1: Round 2
A2: Short Name | B2: ID | C2: SP String (DNE) | D2: R1 String (DNE) | E2: R2 String (DNE) | F2: SP | G2: R1 | H2: R2 | I2: MEM | J2: Fn# | K2: Cite# | L2: Supports? | M2: Citation Elements | N2: MEM Comments | O2: SE Response | P2: Kickback Response | Q2: MEM | R2: Fn# | S2: Cite# | T2: Supports? | U2: Citation Elements | V2: MEM Comments | W2: SE Response | X2: Kickback Response
A3: Keep this row hidden / do not edit! | B3: {=IF($A$3:$A86<>"", XLOOKUP($A$3:$A86, Sourcepull!$B$3:$B86, Sourcepull!$A$3:$A86, ""), "")} | C3: {=if($A$3:$A86<>"","SP-"&$B$3:$B86&"-"&$A$3:$A86&".pdf", "")} -> SP--Keep this row hidden / do not edit!.pdf | D3: {=if($J$3:$J86<>"","R1-"&$J$3:$J86&"-"&$K$3:$K86&"-"&$B$3:$B86&"-"&$A$3:$A86&".pdf", "")} | E3: {=if($R$3:$R86<>"","R2-"&$R$3:$R86&"-"&$S$3:$S86&"-"&$B$3:$B86&"-"&$A$3:$A86&".pdf", "")} | F3: {=if($C$3:$C86 <> "", hyperlink("https://drive.google.com/drive/search?q=parent:" & Properties!$C$8 & "%20" & char(34) & $C$3:$C86 & char(34), "➔"), "")} -> ➔ | G3: {=if($D$3:$D86 <> "", hyperlink("https://drive.google.com/drive/search?q=parent:" & Properties!$C$9 & "%20" & char(34) & $D$3:$D86 & char(34), "➔"), "")} | H3: {=if($E$3:$E86 <> "", hyperlink("https://drive.google.com/drive/search?q=parent:" & Properties!$C$10 & "%20" & char(34) & $E$3:$E86 & char(34), "➔"), "")}
A4: Gallatin Wildlife Ass'n v US Forest Serv | B4: 206 | C4: SP-206-Gallatin Wildlife Ass'n v US Forest Serv.pdf | D4: R1-280-01-206-Gallatin Wildlife Ass'n v US Forest Serv.pdf | F4: ➔ | G4: ➔ | I4: ME | J4: 280 | K4: 01
A5: Miami Tribe | B5: 152 | C5: SP-152-Miami Tribe.pdf | D5: R1-280-02-152-Miami Tribe.pdf | F5: ➔ | G5: ➔ | I5: ME | J5: 280 | K5: 02
A6: Utah State Dep't of Health v Kennecott Corp | B6: 295 | C6: SP-295-Utah State Dep't of Health v Kennecott Corp.pdf | D6: R1-280-03-295-Utah State Dep't of Health v Kennecott Corp.pdf | F6: ➔ | G6: ➔ | I6: ME | J6: 280 | K6: 03
A7: Cabot Corp v United States | B7: 128 | C7: SP-128-Cabot Corp v United States.pdf | D7: R1-280-04-128-Cabot Corp v United States.pdf | F7: ➔ | G7: ➔ | I7: ME | J7: 280 | K7: 04
A8: McCoy v Schweiker | B8: 130 | C8: SP-130-McCoy v Schweiker.pdf | D8: R1-280-05-130-McCoy v Schweiker.pdf | F8: ➔ | G8: ➔ | I8: ME | J8: 280 | K8: 05
A9: Finkelstein | B9: 019 | C9: SP-019-Finkelstein.pdf | D9: R1-280-06-019-Finkelstein.pdf | F9: ➔ | G9: ➔ | I9: ME | J9: 280 | K9: 06
A10: 15a Wright | B10: 296 | C10: SP-296-15a Wright.pdf | D10: R1-280-07-296-15a Wright.pdf | F10: ➔ | G10: ➔ | I10: ME | J10: 280 | K10: 07
A11: Fed 54(b | B11: 297 | C11: SP-297-Fed 54(b.pdf | D11: R1-280-08-297-Fed 54(b.pdf | F11: ➔ | G11: ➔ | I11: ME | J11: 280 | K11: 08
A12: 1292 | B12: 046 | C12: SP-046-1292.pdf | D12: R1-280-09-046-1292.pdf | F12: ➔ | G12: ➔ | I12: ME | J12: 280 | K12: 09
A13: Dcor | B13: 013 | C13: SP-013-Dcor.pdf | D13: R1-281-01-013-Dcor.pdf | F13: ➔ | G13: ➔ | I13: ME | J13: 281 | K13: 01
A14: Aaron P v Dep't of Educ | B14: 298 | C14: SP-298-Aaron P v Dep't of Educ.pdf | D14: R1-281-02-298-Aaron P v Dep't of Educ.pdf | F14: ➔ | G14: ➔ | I14: ME | J14: 281 | K14: 02
A15: Miami Tribe Distr. Ct. | B15: 299 | C15: SP-299-Miami Tribe Distr. Ct..pdf | D15: R1-281-03-299-Miami Tribe Distr. Ct..pdf | F15: ➔ | G15: ➔ | I15: ME | J15: 281 | K15: 03
A16: Associated Mortg | B16: 300 | C16: SP-300-Associated Mortg.pdf | D16: R1-281-04-300-Associated Mortg.pdf | F16: ➔ | G16: ➔ | I16: ME | J16: 281 | K16: 04
A17: Wild Rockies | B17: 301 | C17: SP-301-Wild Rockies.pdf | D17: R1-282-01-301-Wild Rockies.pdf | F17: ➔ | G17: ➔ | I17: ME | J17: 282 | K17: 01
A18: Sierra Forest Legacy v Sherman | B18: 204 | C18: SP-204-Sierra Forest Legacy v Sherman.pdf | D18: R1-282-02-204-Sierra Forest Legacy v Sherman.pdf | F18: ➔ | G18: ➔ | I18: ME | J18: 282 | K18: 02
A19: Miami Tribe | B19: 152 | C19: SP-152-Miami Tribe.pdf | D19: R1-283-01-152-Miami Tribe.pdf | F19: ➔ | G19: ➔ | I19: ME | J19: 283 | K19: 01
A20: McBride v Citgo Petroleum Corp | B20: 302 | C20: SP-302-McBride v Citgo Petroleum Corp.pdf | D20: R1-283-02-302-McBride v Citgo Petroleum Corp.pdf | F20: ➔ | G20: ➔ | I20: ME | J20: 283 | K20: 02
A21: Federal Practice 3949 4 | B21: 303 | C21: SP-303-Federal Practice 3949 4.pdf | D21: R1-283-03-303-Federal Practice 3949 4.pdf | F21: ➔ | G21: ➔ | I21: ME | J21: 283 | K21: 03
A22: Wild Rockies | B22: 301 | C22: SP-301-Wild Rockies.pdf | D22: R1-284-01-301-Wild Rockies.pdf | F22: ➔ | G22: ➔ | I22: ME | J22: 284 | K22: 01
A23: Wild Rockies | B23: 301 | C23: SP-301-Wild Rockies.pdf | D23: R1-285-01-301-Wild Rockies.pdf | F23: ➔ | G23: ➔ | I23: ME | J23: 285 | K23: 01
A24: Miami Tribe | B24: 152 | C24: SP-152-Miami Tribe.pdf | D24: R1-286-01-152-Miami Tribe.pdf | F24: ➔ | G24: ➔ | I24: ME | J24: 286 | K24: 01
... A42: Rule 54(b) | B42: 308 | C42: SP-308-Rule 54(b).pdf | D42: R1-297-01-308-Rule 54(b).pdf | F42: ➔ | G42: ➔ | I42: ME | J42: 297 | K42: 01
A43: 1292 | B43: 046 | C43: SP-046-1292.pdf | D43: R1-297-02-046-1292.pdf | F43: ➔ | G43: ➔ | I43: ME | J43: 297 | K43: 02
A44: Jeannette Sheet Glass Corp v United States | B44: 141 | C44: SP-141-Jeannette Sheet Glass Corp v United States.pdf | D44: R1-297-03-141-Jeannette Sheet Glass Corp v United States.pdf | F44: ➔ | G44: ➔ | I44: ME | J44: 297 | K44: 03
A45: Supra Notes 67 | B45: 309 | C45: SP-309-Supra Notes 67.pdf | D45: R1-297-04-309-Supra Notes 67.pdf | F45: ➔ | G45: ➔ | I45: ME | J45: 297 | K45: 04
A46: Supra Notes 132-194 and Accompanying Text | B46: 310 | C46: SP-310-Supra Notes 132-194 and Accompanying Text.pdf | D46: R1-298-01-310-Supra Notes 132-194 and Accompanying Text.pdf | F46: ➔ | G46: ➔ | I46: ME | J46: 298 | K46: 01
A47: Supra Notes 127 | B47: 311 | C47: SP-311-Supra Notes 127.pdf | D47: R1-299-01-311-Supra Notes 127.pdf | F47: ➔ | G47: ➔ | I47: ME | J47: 299 | K47: 01
A48: Lammon Appealability | B48: 021 | C48: SP-021-Lammon Appealability.pdf | D48: R1-300-01-021-Lammon Appealability.pdf | F48: ➔ | G48: ➔ | I48: ME | J48: 300 | K48: 01
A49: Supra Note 163 and Accompanying Text | B49: 312 | C49: SP-312-Supra Note 163 and Accompanying Text.pdf | D49: R1-301-01-312-Supra Note 163 and Accompanying Text.pdf | F49: ➔ | G49: ➔ | I49: ME | J49: 301 | K49: 01
A50: Supra Note 136 and Accompanying Text | B50: 313 | C50: SP-313-Supra Note 136 and Accompanying Text.pdf | D50: R1-302-01-313-Supra Note 136 and Accompanying Text.pdf | F50: ➔ | G50: ➔ | I50: ME | J50: 302 | K50: 01
A51: Supra Notes 136-137 and Accompanying Text | B51: 266 | C51: SP-266-Supra Notes 136-137 and Accompanying Text.pdf | D51: R1-303-01-266-Supra Notes 136-137 and Accompanying Text.pdf | F51: ➔ | G51: ➔ | I51: ME | J51: 303 | K51: 01
A52: Lammon Disarming | B52: 084 | C52: SP-084-Lammon Disarming.pdf | D52: R1-303-02-084-Lammon Disarming.pdf | F52: ➔ | G52: ➔ | I52: ME | J52: 303 | K52: 02
A53: Supra Note 175 and Accompanying Text | B53: 314 | C53: SP-314-Supra Note 175 and Accompanying Text.pdf | D53: R1-304-01-314-Supra Note 175 and Accompanying Text.pdf | F53: ➔ | G53: ➔ | I53: ME | J53: 304 | K53: 01
A54: Supra Note 174 and Accompanying Text | B54: 315 | C54: SP-315-Supra Note 174 and Accompanying Text.pdf | D54: R1-304-02-315-Supra Note 174 and Accompanying Text.pdf | F54: ➔ | G54: ➔ | I54: ME | J54: 304 | K54: 02
A55: S Utah Wilderness Alliance v Kempthorne | B55: 223 | C55: SP-223-S Utah Wilderness Alliance v Kempthorne.pdf | D55: R1-305-01-223-S Utah Wilderness Alliance v Kempthorne.pdf | F55: ➔ | G55: ➔ | I55: ME | J55: 305 | K55: 01
... A79: 28 USC 2702(c) | B79: 324 | C79: SP-324-28 USC 2702(c).pdf | D79: R1-320-01-324-28 USC 2702(c).pdf | F79: ➔ | G79: ➔ | I79: ME | J79: 320 | K79: 01
A80: 1292 | B80: 046 | C80: SP-046-1292.pdf | D80: R1-320-02-046-1292.pdf | F80: ➔ | G80: ➔ | I80: ME | J80: 320 | K80: 02
A81: Walker James | B81: 325 | C81: SP-325-Walker James.pdf | D81: R1-321-01-325-Walker James.pdf | F81: ➔ | G81: ➔ | I81: ME | J81: 321 | K81: 01
A82: Walker Referral | B82: 060 | C82: SP-060-Walker Referral.pdf | D82: R1-321-02-060-Walker Referral.pdf | F82: ➔ | G82: ➔ | I82: ME | J82: 321 | K82: 02
A83: Bagley | B83: 055 | C83: SP-055-Bagley.pdf | D83: R1-322-01-055-Bagley.pdf | F83: ➔ | G83: ➔ | I83: ME | J83: 322 | K83: 01
A84: Supra Notes 299-301 and Accompanying Text | B84: 326 | C84: SP-326-Supra Notes 299-301 and Accompanying Text.pdf | D84: R1-323-01-326-Supra Notes 299-301 and Accompanying Text.pdf | F84: ➔ | G84: ➔ | I84: ME | J84: 323 | K84: 01
A85: Supra Note 116 | B85: 327 | C85: SP-327-Supra Note 116.pdf | D85: R1-324-01-327-Supra Note 116.pdf | F85: ➔ | G85: ➔ | I85: ME | J85: 324 | K85: 01
A86: Cotton Petroleum Corp | B86: 155 | C86: SP-155-Cotton Petroleum Corp.pdf | D86: R1-324-02-155-Cotton Petroleum Corp.pdf | F86: ➔ | G86: ➔ | I86: ME | J86: 324 | K86: 02
